{
  "eventKey": "24158_20260629_20260713",
  "eventId": "24158",
  "eventUrl": "https://mixch.tv/live/event/24158",
  "title": "デフォルメキャライラスト&アクスタ制作オーディション！Vol.2",
  "openedUrl": "https://mixch.tv/live/event/24158",
  "capturedAt": "2026-07-08T14:05:00.605Z",
  "tabs": [
    {
      "key": "ranking",
      "label": "ランキング",
      "order": 1
    },
    {
      "key": "live",
      "label": "ライブ",
      "order": 2
    },
    {
      "key": "movie",
      "label": "ムービー",
      "order": 3
    },
    {
      "key": "about",
      "label": "概要",
      "order": 4
    }
  ],
  "rankingHtml": "<div class=\"css-xlejcj ecbtkat0\"><ul class=\"list\"><li class=\"e1jtukx00 css-w1rca4 ex3haug0\"><span class=\"css-1eu4g1y ehnruze0\">1</span><a class=\"user-name css-0 e10qwino0\" href=\"/u/11185663\"><span class=\"css-14dzdfy e1bokax20\"><img src=\"https://d2jtsb989t238a.cloudfront.net/p/11185663/1781610700/small\" alt=\"べいべーあゆ🌈🐤  \" class=\"thumb-img\" loading=\"lazy\"></span><span class=\"css-qrjx5q ejhaeu10\">べいべーあゆ🌈🐤  </span></a><span class=\"css-1xxlsgn ewf2cv0\"><span class=\"num\">354,769</span><span class=\"unit\">pt</span></span></li><li class=\"e1jtukx00 css-w1rca4 ex3haug0\"><span class=\"css-1eu4g1y ehnruze0\">2</span><a class=\"user-name css-0 e10qwino0\" href=\"/u/17373942\"><span class=\"css-14dzdfy e1bokax20\"><img src=\"https://d2jtsb989t238a.cloudfront.net/p/17373942/1780481278/small\" alt=\"うえきあやか🐺🌹like求\" class=\"thumb-img\" loading=\"lazy\"></span><span class=\"css-qrjx5q ejhaeu10\">うえきあやか🐺🌹like求</span></a><span class=\"css-1xxlsgn ewf2cv0\"><span class=\"num\">199,700</span><span class=\"unit\">pt</span></span></li><li class=\"e1jtukx00 css-w1rca4 ex3haug0\"><span class=\"css-1eu4g1y ehnruze0\">3</span><a class=\"user-name css-0 e10qwino0\" href=\"/u/18790983\"><span class=\"css-14dzdfy e1bokax20\"><img src=\"https://d2jtsb989t238a.cloudfront.net/p/18790983/1783253813/small\" alt=\"ゆうり✈️💫#アクスタ\" class=\"thumb-img\" loading=\"lazy\"></span><span class=\"css-qrjx5q ejhaeu10\">ゆうり✈️💫#アクスタ</span></a><span class=\"css-1xxlsgn ewf2cv0\"><span class=\"num\">149,137</span><span class=\"unit\">pt</span></span></li><li class=\"e1jtukx00 css-w1rca4 ex3haug0\"><span class=\"css-cjsdul ehnruze0\">4</span><a class=\"user-name css-0 e10qwino0\" href=\"/u/13897866\"><span class=\"css-14dzdfy e1bokax20\"><img src=\"https://d2jtsb989t238a.cloudfront.net/p/13897866/1782945451/small\" alt=\"🍵💖#ｱｸｽﾀ\" class=\"thumb-img\" loading=\"lazy\"></span><span class=\"css-qrjx5q ejhaeu10\">🍵💖#ｱｸｽﾀ</span></a><span class=\"css-1xxlsgn ewf2cv0\"><span class=\"num\">103,850</span><span class=\"unit\">pt</span></span></li><li class=\"e1jtukx00 css-w1rca4 ex3haug0\"><span class=\"css-cjsdul ehnruze0\">5</span><a class=\"user-name css-0 e10qwino0\" href=\"/u/18370704\"><span class=\"css-14dzdfy e1bokax20\"><img src=\"https://d2jtsb989t238a.cloudfront.net/p/18370704/1774982075/small\" alt=\"とめいと🍅🐮アクスタAD\" class=\"thumb-img\" loading=\"lazy\"></span><span class=\"css-qrjx5q ejhaeu10\">とめいと🍅🐮アクスタAD</span></a><span class=\"css-1xxlsgn ewf2cv0\"><span class=\"num\">94,052</span><span class=\"unit\">pt</span></span></li><li class=\"e1jtukx00 css-w1rca4 ex3haug0\"><span class=\"css-cjsdul ehnruze0\">6</span><a class=\"user-name css-0 e10qwino0\" href=\"/u/17484959\"><span class=\"css-14dzdfy e1bokax20\"><img src=\"https://d2jtsb989t238a.cloudfront.net/p/17484959/1780874258/small\" alt=\"ちゃーさん🐥🍀\" class=\"thumb-img\" loading=\"lazy\"></span><span class=\"css-qrjx5q ejhaeu10\">ちゃーさん🐥🍀</span></a><span class=\"css-1xxlsgn ewf2cv0\"><span class=\"num\">75,373</span><span class=\"unit\">pt</span></span></li><li class=\"e1jtukx00 css-w1rca4 ex3haug0\"><span class=\"css-cjsdul ehnruze0\">7</span><a class=\"user-name css-0 e10qwino0\" href=\"/u/18831170\"><span class=\"css-14dzdfy e1bokax20\"><img src=\"https://d2jtsb989t238a.cloudfront.net/p/18831170/1782740527/small\" alt=\"ドラクエのゆう✒️👗#感謝会✨#アクスタ\" class=\"thumb-img\" loading=\"lazy\"></span><span class=\"css-qrjx5q ejhaeu10\">ドラクエのゆう✒️👗#感謝会✨#アクスタ</span></a><span class=\"css-1xxlsgn ewf2cv0\"><span class=\"num\">74,896</span><span class=\"unit\">pt</span></span></li><li class=\"e1jtukx00 css-w1rca4 ex3haug0\"><span class=\"css-cjsdul ehnruze0\">8</span><a class=\"user-name css-0 e10qwino0\" href=\"/u/15073760\"><span class=\"css-14dzdfy e1bokax20\"><img src=\"https://d2jtsb989t238a.cloudfront.net/p/15073760/1782225518/small\" alt=\"☁💙ﾔｽﾔｽ🌼💜‪\" class=\"thumb-img\" loading=\"lazy\"></span><span class=\"css-qrjx5q ejhaeu10\">☁💙ﾔｽﾔｽ🌼💜‪</span></a><span class=\"css-1xxlsgn ewf2cv0\"><span class=\"num\">47,280</span><span class=\"unit\">pt</span></span></li><li class=\"e1jtukx00 css-w1rca4 ex3haug0\"><span class=\"css-cjsdul ehnruze0\">9</span><a class=\"user-name css-0 e10qwino0\" href=\"/u/4426348\"><span class=\"css-14dzdfy e1bokax20\"><img src=\"https://d2jtsb989t238a.cloudfront.net/p/4426348/1782611290/small\" alt=\"ྀིおしょこ🌻🐈‍⬛ྀི限定復活👑\" class=\"thumb-img\" loading=\"lazy\"></span><span class=\"css-qrjx5q ejhaeu10\">ྀིおしょこ🌻🐈‍⬛ྀི限定復活👑</span></a><span class=\"css-1xxlsgn ewf2cv0\"><span class=\"num\">34,543</span><span class=\"unit\">pt</span></span></li><li class=\"e1jtukx00 css-w1rca4 ex3haug0\"><span class=\"css-cjsdul ehnruze0\">10</span><a class=\"user-name css-0 e10qwino0\" href=\"/u/18805914\"><span class=\"css-14dzdfy e1bokax20\"><img src=\"https://d2jtsb989t238a.cloudfront.net/p/18805914/1777757928/small\" alt=\"ろぜ🥀🦢 \" class=\"thumb-img\" loading=\"lazy\"></span><span class=\"css-qrjx5q ejhaeu10\">ろぜ🥀🦢 </span></a><span class=\"css-1xxlsgn ewf2cv0\"><span class=\"num\">23,888</span><span class=\"unit\">pt</span></span></li><li class=\"e1jtukx00 css-w1rca4 ex3haug0\"><span class=\"css-cjsdul ehnruze0\">11</span><a class=\"user-name css-0 e10qwino0\" href=\"/u/18844219\"><span class=\"css-14dzdfy e1bokax20\"><img src=\"https://d2jtsb989t238a.cloudfront.net/p/18844219/1776614764/small\" alt=\"さとうのごはん🍚💭\" class=\"thumb-img\" loading=\"lazy\"></span><span class=\"css-qrjx5q ejhaeu10\">さとうのごはん🍚💭</span></a><span class=\"css-1xxlsgn ewf2cv0\"><span class=\"num\">19,000</span><span class=\"unit\">pt</span></span></li><li class=\"e1jtukx00 css-w1rca4 ex3haug0\"><span class=\"css-cjsdul ehnruze0\">12</span><a class=\"user-name css-0 e10qwino0\" href=\"/u/18467120\"><span class=\"css-14dzdfy e1bokax20\"><img src=\"https://d2jtsb989t238a.cloudfront.net/p/18467120/1762068189/small\" alt=\"稲村ｼﾞｪｰﾝ🧸▶︎🐻️ﾃﾞﾌｫﾙﾒ  ｷｬﾗ \" class=\"thumb-img\" loading=\"lazy\"></span><span class=\"css-qrjx5q ejhaeu10\">稲村ｼﾞｪｰﾝ🧸▶︎🐻️ﾃﾞﾌｫﾙﾒ  ｷｬﾗ </span></a><span class=\"css-1xxlsgn ewf2cv0\"><span class=\"num\">18,947</span><span class=\"unit\">pt</span></span></li><li class=\"e1jtukx00 css-w1rca4 ex3haug0\"><span class=\"css-cjsdul ehnruze0\">13</span><a class=\"user-name css-0 e10qwino0\" href=\"/u/17840918\"><span class=\"css-14dzdfy e1bokax20\"><img src=\"https://d2jtsb989t238a.cloudfront.net/p/17840918/1782917777/small\" alt=\"誕生月moge🍶🍊\" class=\"thumb-img\" loading=\"lazy\"></span><span class=\"css-qrjx5q ejhaeu10\">誕生月moge🍶🍊</span></a><span class=\"css-1xxlsgn ewf2cv0\"><span class=\"num\">16,358</span><span class=\"unit\">pt</span></span></li><li class=\"e1jtukx00 css-w1rca4 ex3haug0\"><span class=\"css-cjsdul ehnruze0\">14</span><a class=\"user-name css-0 e10qwino0\" href=\"/u/18691202\"><span class=\"css-14dzdfy e1bokax20\"><img src=\"https://d2jtsb989t238a.cloudfront.net/p/18691202/1777391267/small\" alt=\"akiko🎀🎗️#ｱｸｽﾀ制作\" class=\"thumb-img\" loading=\"lazy\"></span><span class=\"css-qrjx5q ejhaeu10\">akiko🎀🎗️#ｱｸｽﾀ制作</span></a><span class=\"css-1xxlsgn ewf2cv0\"><span class=\"num\">14,370</span><span class=\"unit\">pt</span></span></li><li class=\"e1jtukx00 css-w1rca4 ex3haug0\"><span class=\"css-cjsdul ehnruze0\">15</span><a class=\"user-name css-0 e10qwino0\" href=\"/u/15668205\"><span class=\"css-14dzdfy e1bokax20\"><img src=\"https://d2jtsb989t238a.cloudfront.net/p/15668205/1752293024/small\" alt=\"りくな🌻💎\" class=\"thumb-img\" loading=\"lazy\"></span><span class=\"css-qrjx5q ejhaeu10\">りくな🌻💎</span></a><span class=\"css-1xxlsgn ewf2cv0\"><span class=\"num\">11,860</span><span class=\"unit\">pt</span></span></li><li class=\"e1jtukx00 css-w1rca4 ex3haug0\"><span class=\"css-cjsdul ehnruze0\">16</span><a class=\"user-name css-0 e10qwino0\" href=\"/u/18521508\"><span class=\"css-14dzdfy e1bokax20\"><img src=\"https://d2jtsb989t238a.cloudfront.net/p/18521508/1782661104/small\" alt=\"龍聖~Ryusei~ \" class=\"thumb-img\" loading=\"lazy\"></span><span class=\"css-qrjx5q ejhaeu10\">龍聖~Ryusei~ </span></a><span class=\"css-1xxlsgn ewf2cv0\"><span class=\"num\">11,850</span><span class=\"unit\">pt</span></span></li><li class=\"e1jtukx00 css-w1rca4 ex3haug0\"><span class=\"css-cjsdul ehnruze0\">17</span><a class=\"user-name css-0 e10qwino0\" href=\"/u/17915845\"><span class=\"css-14dzdfy e1bokax20\"><img src=\"https://d2jtsb989t238a.cloudfront.net/p/17915845/1768777770/small\" alt=\"かぴてん🌺🦀7/19（日）ザラン大阪出演\" class=\"thumb-img\" loading=\"lazy\"></span><span class=\"css-qrjx5q ejhaeu10\">かぴてん🌺🦀7/19（日）ザラン大阪出演</span></a><span class=\"css-1xxlsgn ewf2cv0\"><span class=\"num\">8,772</span><span class=\"unit\">pt</span></span></li><li class=\"e1jtukx00 css-w1rca4 ex3haug0\"><span class=\"css-cjsdul ehnruze0\">18</span><a class=\"user-name css-0 e10qwino0\" href=\"/u/18664094\"><span class=\"css-14dzdfy e1bokax20\"><img src=\"https://d2jtsb989t238a.cloudfront.net/p/18664094/1783069328/small\" alt=\"友結（ゆい）⛄️🎀#AngelAward💖\" class=\"thumb-img\" loading=\"lazy\"></span><span class=\"css-qrjx5q ejhaeu10\">友結（ゆい）⛄️🎀#AngelAward💖</span></a><span class=\"css-1xxlsgn ewf2cv0\"><span class=\"num\">6,912</span><span class=\"unit\">pt</span></span></li><li class=\"e1jtukx00 css-w1rca4 ex3haug0\"><span class=\"css-cjsdul ehnruze0\">19</span><a class=\"user-name css-0 e10qwino0\" href=\"/u/18622332\"><span class=\"css-14dzdfy e1bokax20\"><img src=\"https://d2jtsb989t238a.cloudfront.net/p/18622332/1772076529/small\" alt=\"のの🌸☀️＃イラスト&amp;アクスタ制作\" class=\"thumb-img\" loading=\"lazy\"></span><span class=\"css-qrjx5q ejhaeu10\">のの🌸☀️＃イラスト&amp;アクスタ制作</span></a><span class=\"css-1xxlsgn ewf2cv0\"><span class=\"num\">6,692</span><span class=\"unit\">pt</span></span></li><li class=\"e1jtukx00 css-w1rca4 ex3haug0\"><span class=\"css-cjsdul ehnruze0\">20</span><a class=\"user-name css-0 e10qwino0\" href=\"/u/18618128\"><span class=\"css-14dzdfy e1bokax20\"><img src=\"https://d2jtsb989t238a.cloudfront.net/p/18618128/1760158548/small\" alt=\"さきの♯🌸 キャラスタンド&amp;アクスタ🌸\" class=\"thumb-img\" loading=\"lazy\"></span><span class=\"css-qrjx5q ejhaeu10\">さきの♯🌸 キャラスタンド&amp;アクスタ🌸</span></a><span class=\"css-1xxlsgn ewf2cv0\"><span class=\"num\">4,700</span><span class=\"unit\">pt</span></span></li><li class=\"e1jtukx00 css-w1rca4 ex3haug0\"><span class=\"css-cjsdul ehnruze0\">21</span><a class=\"user-name css-0 e10qwino0\" href=\"/u/18066289\"><span class=\"css-14dzdfy e1bokax20\"><img src=\"https://d2jtsb989t238a.cloudfront.net/p/18066289/1783227636/small\" alt=\"れいにゃん🍙🐈#LARME🎀7/15~\" class=\"thumb-img\" loading=\"lazy\"></span><span class=\"css-qrjx5q ejhaeu10\">れいにゃん🍙🐈#LARME🎀7/15~</span></a><span class=\"css-1xxlsgn ewf2cv0\"><span class=\"num\">4,470</span><span class=\"unit\">pt</span></span></li><li class=\"e1jtukx00 css-w1rca4 ex3haug0\"><span class=\"css-cjsdul ehnruze0\">22</span><a class=\"user-name css-0 e10qwino0\" href=\"/u/18464974\"><span class=\"css-14dzdfy e1bokax20\"><img src=\"https://d2jtsb989t238a.cloudfront.net/p/18464974/1761655727/small\" alt=\"🇹🇭もっさん🇯🇵🧊\" class=\"thumb-img\" loading=\"lazy\"></span><span class=\"css-qrjx5q ejhaeu10\">🇹🇭もっさん🇯🇵🧊</span></a><span class=\"css-1xxlsgn ewf2cv0\"><span class=\"num\">3,890</span><span class=\"unit\">pt</span></span></li><li class=\"e1jtukx00 css-w1rca4 ex3haug0\"><span class=\"css-cjsdul ehnruze0\">23</span><a class=\"user-name css-0 e10qwino0\" href=\"/u/18707893\"><span class=\"css-14dzdfy e1bokax20\"><img src=\"https://d2jtsb989t238a.cloudfront.net/p/18707893/1758809015/small\" alt=\"4me🍬\" class=\"thumb-img\" loading=\"lazy\"></span><span class=\"css-qrjx5q ejhaeu10\">4me🍬</span></a><span class=\"css-1xxlsgn ewf2cv0\"><span class=\"num\">3,010</span><span class=\"unit\">pt</span></span></li><li class=\"e1jtukx00 css-w1rca4 ex3haug0\"><span class=\"css-cjsdul ehnruze0\">24</span><a class=\"user-name css-0 e10qwino0\" href=\"/u/18462200\"><span class=\"css-14dzdfy e1bokax20\"><img src=\"https://d2jtsb989t238a.cloudfront.net/p/18462200/1780033710/small\" alt=\"りさ🐰🖤ファン1500人目標🥹❤️\" class=\"thumb-img\" loading=\"lazy\"></span><span class=\"css-qrjx5q ejhaeu10\">りさ🐰🖤ファン1500人目標🥹❤️</span></a><span class=\"css-1xxlsgn ewf2cv0\"><span class=\"num\">2,990</span><span class=\"unit\">pt</span></span></li><li class=\"e1jtukx00 css-w1rca4 ex3haug0\"><span class=\"css-cjsdul ehnruze0\">25</span><a class=\"user-name css-0 e10qwino0\" href=\"/u/18492739\"><span class=\"css-14dzdfy e1bokax20\"><img src=\"https://d2jtsb989t238a.cloudfront.net/p/18492739/1743617198/small\" alt=\"宮司大雅 🎙️🐅🐧\" class=\"thumb-img\" loading=\"lazy\"></span><span class=\"css-qrjx5q ejhaeu10\">宮司大雅 🎙️🐅🐧</span></a><span class=\"css-1xxlsgn ewf2cv0\"><span class=\"num\">2,260</span><span class=\"unit\">pt</span></span></li><li class=\"e1jtukx00 css-w1rca4 ex3haug0\"><span class=\"css-cjsdul ehnruze0\">26</span><a class=\"user-name css-0 e10qwino0\" href=\"/u/18308650\"><span class=\"css-14dzdfy e1bokax20\"><img src=\"https://d2jtsb989t238a.cloudfront.net/p/18308650/1767221877/small\" alt=\"ガチイベまなちむ🐣🍖#\" class=\"thumb-img\" loading=\"lazy\"></span><span class=\"css-qrjx5q ejhaeu10\">ガチイベまなちむ🐣🍖#</span></a><span class=\"css-1xxlsgn ewf2cv0\"><span class=\"num\">2,142</span><span class=\"unit\">pt</span></span></li><li class=\"e1jtukx00 css-w1rca4 ex3haug0\"><span class=\"css-cjsdul ehnruze0\">27</span><a class=\"user-name css-0 e10qwino0\" href=\"/u/18481090\"><span class=\"css-14dzdfy e1bokax20\"><img src=\"https://d2jtsb989t238a.cloudfront.net/p/18481090/1783230471/small\" alt=\"点p💚🐟#パール \" class=\"thumb-img\" loading=\"lazy\"></span><span class=\"css-qrjx5q ejhaeu10\">点p💚🐟#パール </span></a><span class=\"css-1xxlsgn ewf2cv0\"><span class=\"num\">1,696</span><span class=\"unit\">pt</span></span></li><li class=\"e1jtukx00 css-w1rca4 ex3haug0\"><span class=\"css-cjsdul ehnruze0\">28</span><a class=\"user-name css-0 e10qwino0\" href=\"/u/16090231\"><span class=\"css-14dzdfy e1bokax20\"><img src=\"https://d2jtsb989t238a.cloudfront.net/p/16090231/1781430412/small\" alt=\"チョコ🤤🤤🤤🤤🤤🤤\" class=\"thumb-img\" loading=\"lazy\"></span><span class=\"css-qrjx5q ejhaeu10\">チョコ🤤🤤🤤🤤🤤🤤</span></a><span class=\"css-1xxlsgn ewf2cv0\"><span class=\"num\">1,402</span><span class=\"unit\">pt</span></span></li><li class=\"e1jtukx00 css-w1rca4 ex3haug0\"><span class=\"css-cjsdul ehnruze0\">29</span><a class=\"user-name css-0 e10qwino0\" href=\"/u/18713378\"><span class=\"css-14dzdfy e1bokax20\"><img src=\"https://d2uqarpmf42qy0.cloudfront.net/torte_web/_next/static/media/mysteryman.747a7706.png\" alt=\"🌹 🌹람보르기니【ランボルギーニ】🐹🍭\" class=\"thumb-img\" loading=\"lazy\"></span><span class=\"css-qrjx5q ejhaeu10\">🌹 🌹람보르기니【ランボルギーニ】🐹🍭</span></a><span class=\"css-1xxlsgn ewf2cv0\"><span class=\"num\">532</span><span class=\"unit\">pt</span></span></li><li class=\"e1jtukx00 css-w1rca4 ex3haug0\"><span class=\"css-cjsdul ehnruze0\">30</span><a class=\"user-name css-0 e10qwino0\" href=\"/u/18669353\"><span class=\"css-14dzdfy e1bokax20\"><img src=\"https://d2jtsb989t238a.cloudfront.net/p/18669353/1774769967/small\" alt=\"ひろと🦋☘️💜🍒🦄🌈🎀🫶#アクスタ\" class=\"thumb-img\" loading=\"lazy\"></span><span class=\"css-qrjx5q ejhaeu10\">ひろと🦋☘️💜🍒🦄🌈🎀🫶#アクスタ</span></a><span class=\"css-1xxlsgn ewf2cv0\"><span class=\"num\">240</span><span class=\"unit\">pt</span></span></li><li class=\"e1jtukx00 css-w1rca4 ex3haug0\"><span class=\"css-cjsdul ehnruze0\">31</span><a class=\"user-name css-0 e10qwino0\" href=\"/u/16908605\"><span class=\"css-14dzdfy e1bokax20\"><img src=\"https://d2jtsb989t238a.cloudfront.net/p/16908605/1779281629/small\" alt=\"imasi🍫🎙️\" class=\"thumb-img\" loading=\"lazy\"></span><span class=\"css-qrjx5q ejhaeu10\">imasi🍫🎙️</span></a><span class=\"css-1xxlsgn ewf2cv0\"><span class=\"num\">202</span><span class=\"unit\">pt</span></span></li><li class=\"e1jtukx00 css-w1rca4 ex3haug0\"><span class=\"css-cjsdul ehnruze0\">32</span><a class=\"user-name css-0 e10qwino0\" href=\"/u/18744825\"><span class=\"css-14dzdfy e1bokax20\"><img src=\"https://d2jtsb989t238a.cloudfront.net/p/18744825/1781141011/small\" alt=\"🍀🐷みじゅまる🐷🍀#MV参加バトル\" class=\"thumb-img\" loading=\"lazy\"></span><span class=\"css-qrjx5q ejhaeu10\">🍀🐷みじゅまる🐷🍀#MV参加バトル</span></a><span class=\"css-1xxlsgn ewf2cv0\"><span class=\"num\">30</span><span class=\"unit\">pt</span></span></li><li class=\"e1jtukx00 css-w1rca4 ex3haug0\"><span class=\"css-cjsdul ehnruze0\">33</span><a class=\"user-name css-0 e10qwino0\" href=\"/u/17907116\"><span class=\"css-14dzdfy e1bokax20\"><img src=\"https://d2jtsb989t238a.cloudfront.net/p/17907116/1783505531/small\" alt=\"なおみデフォルメキャラアクスタ参加中\" class=\"thumb-img\" loading=\"lazy\"></span><span class=\"css-qrjx5q ejhaeu10\">なおみデフォルメキャラアクスタ参加中</span></a><span class=\"css-1xxlsgn ewf2cv0\"><span class=\"num\">2</span><span class=\"unit\">pt</span></span></li></ul></div>",
  "ogDescription": "開催期間 2026/06/29 12:00 ~ 2026/07/13 00:00",
  "bannerImageUrl": "https://d2uqarpmf42qy0.cloudfront.net/torte/event/24158/banner.png",
  "startAt": "2026-06-29T12:00:00+09:00",
  "endAt": "2026-07-13T00:00:00+09:00",
  "detailHtml": "<div class=\"content\"><style>*{max-width:100% !important;}*::before{max-width:100% !important;}*::after{max-width:100% !important;};  .cf:after{content:&apos; &apos;;display:block;clear:both;height:0;}.cf{display:inline-block;}.cf{display:block;}body{background:#f8f7f4;font-family:Hiragino Kaku Gothic Pro,Meiryo,MS PGothic,sans-serif;font-size:16px;line-height:1.4;letter-spacing:0.05em;margin:0px;color:#3c3c3c;overflow-y:hidden;overflow-x:hidden;padding:0px 5px;}img{vertical-align:bottom;border:none;outline:none;}a,.text-link{text-decoration:none;outline:none;color:#ef9500;cursor:pointer;}a:hover,.text-link:hover{text-decoration:underline;}input,select,option,textarea{font-family:Hiragino Kaku Gothic Pro,Meiryo,MS PGothic,sans-serif;}.center{text-align:center;}.right{text-align:right;}.button-green{color:#fff;display:block;width:100%;box-sizing:border-box;padding:10px 0 9px 0;margin:0 auto;cursor:pointer;font-size:15px;font-weight:bold;text-align:center;border-radius:3px;-moz-border-radius:3px;-webkit-border-radius:3px;background-color:#65b721;background-image:-webkit-gradient(\n      linear,left top,left bottom,from(#6ac023),to(#65b721)\n    );background-image:-webkit-linear-gradient(top,#6ac023,#65b721);background-image:-moz-linear-gradient(top,#6ac023,#65b721);background-image:-o-linear-gradient(top,#6ac023,#65b721);background-image:linear-gradient(top,#6ac023,#65b721);border:solid 1px #61bc14;text-shadow:0 1px 1px #135e00;box-shadow:0 3px 0 #467f17;}.button-green:hover{text-decoration:none;background:#84d933;}.button-green-s{color:#fff;box-sizing:border-box;cursor:pointer;font-weight:bold;text-align:center;border-radius:3px;-moz-border-radius:3px;-webkit-border-radius:3px;background-color:#65b721;background-image:-webkit-gradient(\n      linear,left top,left bottom,from(#6ac023),to(#65b721)\n    );background-image:-webkit-linear-gradient(top,#6ac023,#65b721);background-image:-moz-linear-gradient(top,#6ac023,#65b721);background-image:-o-linear-gradient(top,#6ac023,#65b721);background-image:linear-gradient(top,#6ac023,#65b721);text-shadow:0 1px 1px #135e00;display:inline-block;font-size:16px;padding:8px 11px 7px 11px;margin:0;width:auto;border:solid 1px #61bc14;box-shadow:0 3px 0 #467f17;}.button-green-s:hover{text-decoration:none;background:#84d933;}.content{background:#fff;margin:0 0 20px 0;padding:0 0 1px 0;box-shadow:0 1px 1px #ccc;}.content p{padding:0 10px;margin:0 0 10px 0;}.content h1{display:none;}.content h2{font-size:16px;background:#f5f5f5;border-left:solid 8px #cece2b;padding:8px 0 8px 8px;}.content h3{padding:0 0 0 5px;margin:0;}.menu{background-color:#333;padding:5px 30px;color:white;width:100%;}</style><p>\n<style>h1 { display: none; }\n</style>\n</p><div style=\"background:repeat center/100% url(https://d2uqarpmf42qy0.cloudfront.net/event/hong25/24957382.jpg);\">\n<!-- <center><img src=\"https://d2uqarpmf42qy0.cloudfront.net/event/hong25/banner1154.png\" width=\"100%\"></center> -->\n<div style=\"padding:5px;border:2px solid #afeeee;background-color:#afeeee;color:white;\"> <center><span style=\"color:white;font-size:16px;font-weight:bold;\">このイベントは本選期間中でもすぐに参加可能</span>です!! </center></div>\n<div class=\"box\"><p></p>\n\n<div class=\"box1\">\n<h3 class=\"logo\">イベント概要</h3>\n<p style=\"margin:10px;\">\n<b>\nあなたの写真やイラストをもとに、可愛いデフォルメキャラクターイラストを制作！✨️<br>\nさらに、可愛くイラスト化したデザインでアクスタにもしちゃおう✨<u>今回はソロイベントとしてVol.2を開催😉</u></b><br>\n<br>\n<b>\n<span style=\"background:linear-gradient(transparent 40%, #FFFF99 10%);\">●ガチファン特典のプレゼントにも🌟<br>\n●オフラインイベントで配るのもあり🛍️<br>\n●SNSのアイコンに👍️</span><br><br>\n</b>\n</p><center><img src=\"https://d2uqarpmf42qy0.cloudfront.net/event/34furukawa/45ut05hth5rhogotnog.jpg\" width=\"75%\"></center><br>\n<center><small>※画像はイメージです。実際の制作物とは異なります。</small></center>\n<!--\n<center><img src=\"https://d2uqarpmf42qy0.cloudfront.net/event/34furukawa/45ut05hth5rhogotnog.jpg\" width=\"80%\" /></center>\n-->\n\n<p></p>\n\n\n<!--\n\n<center><div style=\"margin: 10px; background: #FFFF99; text-align: left; padding: 10px; font-size:9px; width: 85%;\" >\n※本イベントは<font color=red>参加ペア数<b>7組</b></font>の応募がありましたら開催となります。2025年9月28日(日)12時00分までに7組に満たない場合は、<u><b>ミクチャアプリ内の「あなたへのお知らせ」にて19時00分までに開催中止をご連絡</b>させていただきますので予めご了承ください</u>。中止になった場合はソロイベントとして別日程で再度募集する場合がございます。\n\n<br>\n<b><p hidden>【2025.06.12 19:00追記】</b><br>\n7組以上応募がありましたので開催致します。</p>\n</div></center>\n-->\n\n\n</div>\n\n<p></p><p></p>\n\n<!--\n\n<div class=\"box1\">\n<h3 class=\"logo\">イベント参加方法</h3>\n<p style=\"margin:9px;\">\n<br>\n今回は<font color = \"#00bfff\"><B>ペアイベント</center></B></font>となります。オレンジ色の「イベントに応募する」ボタンからはエントリーできません！<BR>\n<br>\n<center>\n<b>応募はこちらをタップ→</b><a href=\"https://docs.google.com/forms/d/e/1FAIpQLSdLBdSmZaF-VIsZgRzpZlBrd1gMFKXNsqrAUiVHg_k1yNs7xg/viewform?usp=dialog\"><font color=#FE2E64><button class=\"gradient-button\">イベントに応募する</button></a></font><br><br>\n</center>\n<p style=\"margin:9px;\">\n下記フォームでも回答可能！<br><b>どちらか代表1名</b>が記入してください。<br>\n<font color=RED><small>※同じユーザーが複数チームの掛け持ちをすることもできません。</small></font><br>\n<font color=RED><small>※相手の同意なしに応募することは絶対におやめください。</small></font><br>\n\n<center>\n<iframe src=\"https://docs.google.com/forms/d/e/1FAIpQLSdLBdSmZaF-VIsZgRzpZlBrd1gMFKXNsqrAUiVHg_k1yNs7xg/viewform?usp=dialog\" width=\"90%\" height=\"400px\" frameborder=\"0\" marginheight=\"0\" marginwidth=\"0\">読み込んでいます…</iframe>\n</center>\n\n<p style=\"margin:10px;\">\n※フォームが表示されない場合は<a href=\"https://docs.google.com/forms/d/e/1FAIpQLSdLBdSmZaF-VIsZgRzpZlBrd1gMFKXNsqrAUiVHg_k1yNs7xg/viewform\">こちら</a>から<BR><br>\n\n</font></p>\n</div>\n-->\n\n<div class=\"box1\">\n<br>\n<h3 class=\"logo\">イベント期間</h3>\n<br>\n<p style=\"margin:10px;\">\n<b>【募集】<small>※途中からでも参加可能</small></b>\n<br>\n　06/19(金)12:00 〜 07/12(日)24:00\n<br><br>\n<b>【本選】</b> \n<br>\n　06/29(月)12:00 〜 07/12(日)24:00\n<br><br>\n</p></div>\n\n<div class=\"box1\">\n<h3 class=\"logo\">特典</h3>\n<h4><span style=\"background:linear-gradient(transparent 40%, #FFFF99 10%);\">🥇ポイントランキング1位</span></h4>\n<p style=\"margin:10px;font-size:16px;color:#ff7f50;font-weight:bold;\"><span style=\"font-size:15px;\">　●</span>デフォルメキャライラストを制作決定！\n</p>\n<p style=\"margin:10px;font-size:15px;font-weight:bold;\">　　∟個人イラスト2種作成</p>\n<p style=\"margin:10px;font-size:16px;color:#ff7f50;font-weight:bold;\"><span style=\"font-size:15px;\">　●</span>アクスタの制作も決定！</p>\n<p style=\"margin:10px;font-size:15px;font-weight:bold;\">　　∟各種6体プレゼント✨</p>\n<h4><span style=\"background:linear-gradient(transparent 40%, #FFFF99 10%);\">🥈ポイントランキング2位</span></h4>\n<p style=\"margin:10px;font-size:16px;color:#ff7f50;font-weight:bold;\"><span style=\"font-size:15px;\">　●</span>デフォルメキャライラストを制作決定！</p>\n<p style=\"margin:10px;font-size:15px;font-weight:bold;\">　　∟個人イラスト1種作成</p><br>\n<p style=\"margin:10px;font-size:16px;color:#ff7f50;font-weight:bold;\"><span style=\"font-size:15px;\">　●</span>アクスタの制作も決定！</p>\n<p style=\"margin:10px;font-size:15px;font-weight:bold;\">　　∟1種6体プレゼント✨</p>\n<br>\n<center><img src=\"https://d2uqarpmf42qy0.cloudfront.net/event/34furukawa/58th9w5rh0gtiownjwgiortg.jpg\" width=\"75%\"></center><br>\n<div style=\"margin:10px 20px;background:#f4f4f4;opacity:0.8;padding:3px;text-align:left;font-size:14px;\">\n<p style=\"margin:10px 0px;\">\n</p><center>【備考】</center>\n<p style=\"margin:20px;font-size:14px;\">\n※イラスト制作期間は1〜2ヶ月間内を目安に履行致します。イラストが完成してからアクスタの制作をいたします。アクスタの納品が終わるまでを含めると2〜3ヶ月かかりますので予めご了承ください。\n</p>\n</div>\n</div>\n\n<div class=\"box1\">\n<h3 class=\"logo\">注意事項</h3>\n<ul style=\"padding:20px 20px;font-size:15px;\">\n<li>※提供を受けたイラストはミクチャプロフィール写真やSNSなどでご自由にご使用いただけます。商用利用を目的とした二次利用も可能です。</li>\n<li>※イラストはイベント終了後から約1〜2ヶ月で制作いたします。</li>\n<li>※イラストは制作過程において1度のみ修正依頼が可能です。複数回の修正対応は承れませんので予めご了承ください。</li>\n<li>※イラストは本人を対象とするものに限らせていただきます。ペットなどをイラストのメインモチーフとすることはできませんのでご了承ください。</li>\n<li>※現在保有しているキャラクターをもとにイラストの制作依頼する場合はキャラクターの著作権（商用化利用含む）をご自身で保有しているものに限ります。</li>\n<li>※スケジュールは前後する可能性もございますのであらかじめご了承ください。</li>\n</ul>\n\n</div>\n\n<div class=\"box1\">\n<br>\n<center>\n<font color=\"#0000\">このイベントでは<br>\n<span style=\"color:#00bfff;font-size:16px;font-weight:bold;\">ムービー + ライブ配信  合算</span><br>\nのポイントがランキングに表示されます！\n</font>\n<br><br>\n</center>\n</div>\n\n<div class=\"box1\">\n\n<h3 class=\"logo\">動画投稿も活用しよう！</h3>\n<center><a href=\"https://mixch.tv/p/obcl5stv\" target=\"_blank\" referrerpolicy=\"no-referrer\"><img src=\"https://d2uqarpmf42qy0.cloudfront.net/torte/home_banner/1472/banner.png\" width=\"90%\"></a></center>\n<p>\nイベント選択して、\n<span style=\"background:linear-gradient(transparent 90%, #00bfff 0%);\"><b>投稿した動画で獲得したpt</b></span>\nと\n<span style=\"background:linear-gradient(transparent 90%, #00bfff 0%);\"><b>ライブ配信で獲得したpt</b></span>\nの合算からランキング入賞者に賞品をプレゼント！<br>\n<br>\n今回のリニューアルでは投稿動画にもアイテムで応援できるようになったので、「配信する時間がなかなか取れないときに、\n<span style=\"background:linear-gradient(transparent 90%, #00bfff 0%);\"><b>スキマ時間に撮った動画でアイテムを受け取る</b></span>」なんてことも出来ちゃいます🎁<br>\n<br>\nダンスや楽器演奏など場所や時間が限られるパフォーマンスだって、動画なら<span style=\"background:linear-gradient(transparent 90%, #00bfff 0%);\"><b>いつでも投稿・視聴・応援が可能！</b></span><br>\n<br>\n</p><center><a class=\"link-btn\" href=\"https://mixch.tv/p/obcl5stv\" target=\"_blank\" referrerpolicy=\"no-referrer\">動画投稿機能について</a></center>\n<center><a class=\"link-btn\" href=\"https://mixch.tv/p/0dwekkca\" target=\"_blank\" referrerpolicy=\"no-referrer\">機能にまつわるヘルプページ</a></center>\n\n<br></div>\n\n<p></p><div class=\"box1\">\n<br>\n<a href=\"https://mixch.tv/p/qjtg97sp\" target=\"_blank\" referrerpolicy=\"no-referrer\"><center><img src=\"https://d2uqarpmf42qy0.cloudfront.net/event/koizumi/1811_kokoroe.png\" width=\"90%\"></center></a>\n<br><p></p>\n\n<p></p><div style=\"margin:10px;border:#00bfff solid 1px;display:block;padding:.2em .3em;\">\n<h3 style=\"border-left:#00bfff solid 6px;padding:.3em.3em.3em.8em;\">審査について</h3>\n</div>\n<p style=\"margin:10px;\">\n●ライブ配信・動画投稿をする際は必ず<b><font color=\"red\">[デフォルメキャライラスト&amp;アクスタ制作オーディション！Vol.2]</font></b>のイベント選択をお願いします。正しく選択をしていない場合は獲得したミクチャポイントがランキングに反映されませんのでご注意ください。また、誤ってイベント選択した際にポイントを対象イベントに反映することはできかねますので予めご了承ください。<br>\n●当該ページの審査項目に沿って受賞者が決定いたします。なお、審査の過程や受賞者の決定に至った理由等につきましてはお答え出来ませんのであらかじめご了承ください。<br>\n●獲得したポイントが同一の場合は、下記の条件に従って順位を決定します。((1)から条件を適用し、順位が決定しない場合はその次の条件を適用して決定し、以下同様の処理をします。)<br>\n<br>\n<font size=\"3\">\n　(1) 対象となるイベントを選択してライブ配信をした「配信時間」の合計が多いユーザーを上位とします。<br>\n　(2) 対象となるイベントを選択してライブ配信をした「配信回数」の合計が多いユーザーを上位とします。<br>\n　(3) 対象となるイベントを選択して行ったライブ配信・投稿動画に対して受け取った「コメント数」の合計が多いユーザーを上位とします。<br>\n　(4) 対象となるイベントへの応募申し込みが早かったユーザーを上位とします。<br>\n　(5) もし(1)～(5)全てが同じ場合はミクチャの「ユーザーIDの数字が小さい」ユーザーを上位とします。<br>\n</font>\n</p>\n<p>※下記の注意事項も必ずお読みください。</p><p></p>\n\n<p></p><div style=\"margin:10px;border:#00bfff solid 1px;display:block;padding:.2em .3em;\">\n<h3 style=\"border-left:#00bfff solid 6px;padding:.3em.3em.3em.8em;\">アイテム送信に関する注意点</h3>\n</div>\n<p style=\"margin:10px;\">\n●ライブ配信で、イベント終了間際など同時間帯に大量のアイテムを投げると、多数のアイテムリクエストによりコイン消費に遅延が生じる可能性がございます。ムービーでは遅延が生じることはないので、ムービーイベントの場合は投稿動画への積極的な送信をご検討ください。<br>\n●ライブ配信の場合、イベント期間中にライバーの端末側でアイテムのアニメーション再生が始まったアイテムはイベントのポイントに加算されます。イベント期間中に再生失敗したアイテムやイベント期間をすぎてから再生されたアイテムは、イベントのポイントに加算されません。<br>\n●なお、上記の事象が発生した場合においても、イベントへのポイント反映やコインの返却などのご対応は出来かねますのでご了承くださいませ。<br>\nそのため、ライブ配信ではできるだけ一気に大量に送るのではなく、定期的にアイテムを送るかムービーへのアイテム送信を推奨いたします。<br>\n</p><p></p>\n\n<p></p><div style=\"margin:10px;border:#00bfff solid 1px;display:block;padding:.2em .3em;\">\n<h3 style=\"border-left:#00bfff solid 6px;padding:.3em.3em.3em.8em;\">応募規約</h3>\n</div>\n<p style=\"margin:10px;\">\n本キャンペーンに応募いただける方（以下、「応募者」といいます。）は、以下をよくお読みいただき、同意の上ご応募ください。<br><br>\nミクチャにて、「イベントに参加する」をタップした時点で本規約に同意したものとみなします。万が一ご同意いただけない場合は応募を中止してください。<br>\n本規約の内容は、事前の告知なく変更される場合がありますので、予めご了承ください。<br>\n</p>\n<div style=\"font-size:16px;padding:.75em 0;border-top:1px solid #00bfff;border-bottom:1px solid #00bfff;\">\n　▪️動画投稿・ライブ配信での注意事項\n</div>\n<p style=\"margin:10px;\">\n●撮影・ライブ配信が禁止されている場所または危険な場所での撮影やライブ配信はお控え下さい。<br>\n●楽曲を使用する場合は著作権者から楽曲利用の許可がおりているものをお使いください。<br>\n●大声を出す・大音量で音楽を流す、道を塞ぐなど、人の迷惑になる行為は控えて、撮影やライブ配信を実施してください。<br>\n</p>\n<p style=\"margin:10px;\">\n●応募者と一緒に投稿動画・ライブ配信に写っている方がいらっしゃる場合や、第三者の知的財産権が含まれる場合、必ず投稿やライブ配信前に権利者から使用許諾を得てください。<br>\nまた、応募者は投稿動画・ライブ配信について自らが投稿・ライブ配信することについての適法な権利を有していること及び第三者の一切の権利を侵害していないことについて当社に対し表明し、保証するものとします。万が一、第三者からの権利侵害等の申し立てがあった場合には、投稿者や配信者ご自身の責任をもって解決していただきますので、予めご了承ください。<br>\n●ミクチャ以外のプラットフォームで作成した動画をミクチャでアップロードする場合、当該プラットフォームの利用規約に沿って投稿してください。<br>\n●未成年の方は保護者の同意を得た上でご応募ください。また、必要に応じて、在籍する学校または所属する部活動が加盟する連盟等へ確認をとったうえで応募してください。<br>\n●事務所、劇団、その他の団体（以下「事務所等」といいます）に所属されている方は、ご自身の責任で事務所等に本キャンペーンへの応募の可否につきご確認ください。<br>\n●コンテストなどの新しい才能の発掘を目的としたものや、事務所所属者や新グループメンバーの選定を目的とした一般的な「オーディション」に関するイベントには、キャッシュバックのお支払いはございません。なお、一部対象外のものもございますので、ご不明な場合はお問い合わせください。<br>\n●上記各項への違反や極端に他人に不快感を与えるような言動や、法律に抵触する内容、ミクチャの利用規約に違反した内容、運営事務局が不適切と判断した動画やライブ配信については削除、もしくはキャッシュバックや審査、受賞の対象外とする可能性がございますのでご了承ください。<br>\n●本応募規約に定める事項のほか、ミクチャ利用規約及びプライバシーポリシーが適用されますので、確認の上、ご応募ください。<br>\n</p><p></p>\n\n<p></p><div style=\"font-size:16px;padding:.75em 0;border-top:1px solid #00bfff;border-bottom:1px solid #00bfff;\">\n　▪️賞品・受賞について\n</div>\n<p style=\"margin:10px;\">\n●受賞者と連絡がつかない場合、賞品受領の意思が確認できない場合、指定された期日までに連絡先をご返信いただけない場合等には、受賞を辞退されたものとみなし、受賞を無効とさせていただきます。予めご了承ください。<br>\n●受賞の権利は受賞者ご本人のものであって、第三者へ譲渡・換金等することはできません。また、受領した賞品の紛失等による再送付、受賞者の事情による変更、その他クレーム等には一切応じることができません。<br>\n●当社は、賞品の品質及び、目的適合性について何ら保証することはできかねます。賞品の使用に当たっては、賞品に記載の注意事項をご確認の上、ご使用ください。受賞された賞品の使用中に生じた事故等のトラブルについての責任は、当社では負いかねます。<br>\n●賞品提供元の何らかの事由により特典不履行となる事案が生じた場合は、代替賞品による補填などで対応することがございますのでご了承くださいませ。<br>\n</p><p></p>\n\n<p></p><div style=\"font-size:16px;padding:.75em 0;border-top:1px solid #00bfff;border-bottom:1px solid #00bfff;\">\n　▪️禁止事項\n</div>\n<p style=\"margin:10px;\">\n本キャンペーンへの応募に際し、以下の行為を禁止します。当社は、応募者が以下に該当する行為を行ったと判断した場合は、応募者への事前通告なく、対象投稿を掲載しない、掲載後削除する、応募・受賞を無効とするなどの対応をとる場合があります。<br>\n<br>\n・本規約または法令に違反する行為<br>\n・本キャンペーンの運営を妨げる行為<br>\n・他人に迷惑、不利益、損害または不快感を与える行為<br>\n・他人を誹謗中傷し、またはその名誉若しくは信用を毀損する行為<br>\n・第三者の著作権その他の知的財産権を侵害する行為<br>\n・他人の財産、プライバシー若しくは肖像権を侵害する行為<br>\n・わいせつ、児童ポルノ及び児童の性的搾取を助長するデータを投稿する行為<br>\n・営利を目的とした情報提供、広告宣伝もしくは勧誘行為<br>\n・公序良俗に反する行為<br>\n・ミクチャの利用規約に違反する行為<br>\n・その他、前各号に類する行為<br>\n</p><p></p>\n\n<p></p><div style=\"font-size:16px;padding:.75em 0;border-top:1px solid #00bfff;border-bottom:1px solid #00bfff;\">\n　▪️免責・その他\n</div>\n<p style=\"margin:10px;\">\n本キャンペーンは、細心の注意を払って運営をしていますが、提供する情報、プログラム、各種サービス、その他本キャンペーンに関するすべての事項について、その完全性、正確性、安全性、有用性等について、いかなる保証もするものではありません。また、利用者または第三者が被った以下の事例を含む損害については、当社は責任を負いかねます。<br>\n<br>\n1.本キャンペーンへの応募に際して、ソフトウェア・ハードウェア上の事故、火災、停電、通信環境の悪化、地震、事変等の非常事態が発生した場合。<br>\n2.本キャンペーンにおけるシステムの保守を定期的あるいは緊急に行う場合。<br>\n3.利用者間または利用者と第三者の間におけるトラブル等が生じた場合。<br>\n4.第三者による本キャンペーンのサービスの妨害、情報改変などによりサービスが中断もしくは遅延し、何らかの欠陥が生じた場合。<br>\n5.当社が推奨する環境以外から本キャンペーンに応募したために情報を完全に取得できない場合。<br>\n6.故意または重過失なくして本キャンペーンが提供する情報が誤送信されるか、もしくは欠陥があった場合。<br>\n<br>\n当社は、本キャンペーンの応募により応募者に生じた一切のトラブル・損害（直接・間接を問いません）について、如何なる責任も負いません。<br>\n本キャンペーンの応募にかかるインターネット接続料及び通信費は応募者のご負担となります。<br>\n本キャンペーンは、ミクチャを提供している当社（株式会社Donuts）が運営しているものであり、Apple社によって提供されているものではございません。<br>\n</p><p></p>\n\n<p></p><div style=\"font-size:16px;padding:.75em 0;border-top:1px solid #00bfff;border-bottom:1px solid #00bfff;\">\n　▪️個人情報の取り扱いについて\n</div>\n<p style=\"margin:10px;\">\n住所、電話番号、氏名、性別、年齢、ミクチャアカウントURLの情報（以下「個人情報」といいます。）は、株式会社Donutsが管理します（管理責任者：ミクチャグループリーダー）。お客様の個人情報は、本キャンペーンの当選者への連絡・賞品の送付等の目的で利用し、それ以外の目的では使用致しません。また、お客様の個人情報をお客様の同意なしに業務委託先以外の第三者に開示・提供することはありません（法令等により開示を求められた場合を除きます。）。<br>\nまた、個人情報開示、訂正等のお問い合わせは、ミクチャ運営事務局（mixch-support@donuts.ne.jp）までお願い致します。<br>\n</p><p></p>\n\n<p></p><div style=\"font-size:16px;padding:.75em 0;border-top:1px solid #00bfff;border-bottom:1px solid #00bfff;\">\n　▪️キャンペーンに関するお問い合わせ窓口\n</div>\n<p style=\"margin:10px;\">\n[ミクチャスポンサー事務局]<br>\nmixch-support@donuts.ne.jp<br>\n</p>\n</div>\n<br>\n<center><img src=\"https://d2uqarpmf42qy0.cloudfront.net/event/NIKU/mixch_LOGO.png\" width=\"20%\"></center>\n<!-- 1タブの中身おわり💡 --><p></p>\n\n<!-- 💡CSSセクションはじめ -->\n\n<style type=\"text/css\">.box1 { height: auto; padding: 2px; margin: 1em; background-color: rgb(255, 255, 255); border: double rgb(0, 191, 255); font-size: 15px; }\nbody { background: rgb(255, 255, 255); }\ndiv.content { color: rgb(112, 112, 112); line-height: 1.75; max-width: 480px; margin: 0px auto; font-size: 15px; }\ndiv.content .header-info { text-align: center; font-size: 16px; margin: 20px 0px; }\ndiv.content h4 { margin: 40px 20px 10px; font-size: 16px; }\ndiv.content h3.logo { margin: 0px 15px 10px; padding: 15px 5px 10px; background-image: linear-gradient(-120deg, rgb(128, 128, 128) 10%, rgb(128, 128, 128) 100%); background-repeat: no-repeat; background-size: 60% 2px; background-position: 0px 100%; line-height: 2em; }\ndiv.content h3.logo::before { background: url(\"https://d2uqarpmf42qy0.cloudfront.net/event/25_hatamura/img/common/mixcha-logo-black-outline-512x512px.png\") center center / contain no-repeat; display: inline-block; margin: 0px 10px 0px 0px; content: \"\"; width: 2em; height: 2em; vertical-align: bottom; }\ndiv.content p { margin: 10px; }\ndiv.content ul { padding: 0px 2em 0px 3em; }\ndiv.button-container { margin: 20px 20px 30px; font-size: 16px; font-weight: bold; text-align: center; }\ndiv.button-container img { display: inline-block; }\n.precaution { line-height: 1.25; color: rgb(96, 96, 96); margin-bottom: 20px; }\ndiv.content img.footer-logo { width: 20%; margin: 0px auto; padding: 40px 0px; display: block; }\ndiv.content a.link-button, div.content a.link-button:link, div.content a.link-button:visited { display: inline-block; color: rgb(141, 201, 111); border: 2px solid rgb(139, 82, 161); padding: 5px 10px; font-size: 16px; font-weight: bold; border-radius: 2em; text-decoration: none; margin: 0px 0px 20px; }\ndiv.content a.link-button:hover, div.content a.link-button:active { opacity: 0.5; }\nli { margin: 5px 0px; list-style-type: none; }\ndiv.content span.fbg-y { font-weight: bold; color: rgb(255, 140, 0); font-size: 16px; }\ndiv.content a.promo-link:hover { text-decoration: none; }\n.box { background: rgba(255, 255, 255, 0.5); text-align: left; padding: 15px 0px; }\ndiv.content link-btn { margin: 20px; padding: 5px; border-radius: 20px; background-color: rgb(255, 255, 255); color: rgb(0, 0, 0); border: 2px solid rgb(0, 191, 255); }\ndiv.content a.link-btn, div.content a.link-btn:link, div.content a.link-btn:visited { display: inline-block; padding: 5px 10px; border: 2px solid rgb(0, 191, 255); border-radius: 70px; transition: 0.125s; text-decoration: none; margin: 5px; font-size: 14px; font-weight: bold; line-height: 1.5; color: rgb(0, 191, 255); }\ndiv.content a.link-btn > span, div.content a.link-btn:link > span, div.content a.link-btn:visited > span { color: rgb(0, 191, 255); transition: 0.125s; font-size: 14px; }\ndiv.content a.link-btn:hover { background-color: rgb(0, 191, 255); color: rgb(255, 255, 255); }\ndiv.content a.link-btn:hover > span { color: rgb(0, 191, 255); }\ndiv.content a.link-btn:active { background-color: rgb(0, 191, 255); box-shadow: rgba(0, 0, 0, 0) 0px 0px 0px; transition: all; }\n</style>\n\n<!-- CSSセクションおわり💡 -->\n</div></div></div>"
}