{
  "profileId": "18641424",
  "currentName": "愛🆘パトンがちまじ🤍🪽＃PopGirl",
  "nameHistory": [
    {
      "name": "愛🆘パトンがちまじ🤍🪽＃PopGirl",
      "firstSeenAt": "2026-07-09T13:44:58.241Z",
      "lastSeenAt": "2026-07-09T13:44:58.241Z"
    }
  ],
  "profileUrl": "https://mixch.tv/u/18641424",
  "iconUrl": "https://d2jtsb989t238a.cloudfront.net/p/18641424/1782370498/small",
  "firstSeenAt": "2026-07-09T13:44:58.241Z",
  "lastSeenAt": "2026-07-09T13:44:58.241Z",
  "eventKeys": [
    "23628_20260622_20260712"
  ]
}