{
  "eventKey": "24084_20260615_20260717",
  "eventId": "24084",
  "eventUrl": "https://mixch.tv/live/event/24084",
  "title": "【楽天イーグルス応援企画】けっぱって東北 全国ツアー＆めんこいな東北 仙台ワンマン開催記念！ 東北応援＆ミクチャプロモーションプロジェクト",
  "openedUrl": "https://mixch.tv/live/event/24084",
  "capturedAt": "2026-07-08T13:05:27.165Z",
  "tabs": [
    {
      "key": "ranking",
      "label": "ランキング",
      "order": 1
    },
    {
      "key": "live",
      "label": "ライブ",
      "order": 2
    },
    {
      "key": "movie",
      "label": "ムービー",
      "order": 3
    },
    {
      "key": "about",
      "label": "概要",
      "order": 4
    }
  ],
  "rankingHtml": "<div class=\"e1aytmbs0 css-x8t1qc ear2k6j0\"><ul class=\"team-list\"><li class=\"e4ddjh0 css-186ana7 ex3haug0\"><span class=\"css-1eu4g1y ehnruze0\">1</span><span class=\"team-color\"><div class=\"team-background-color\" style=\"background-color:#2A2D78\"></div></span><span class=\"css-qrjx5q ejhaeu10\"><button class=\"team-name-button\" type=\"button\">けっぱって東北 </button></span><span class=\"thumbs\"><a class=\"css-0 e10qwino0\" href=\"/u/18911085\"><div class=\"item-thumbs\"><span class=\"css-14dzdfy e1bokax20\" tabindex=\"0\"><img src=\"https://d2jtsb989t238a.cloudfront.net/p/18911085/1781519038/small\" alt=\"けっぱって東北\" class=\"thumb-img\" loading=\"lazy\"></span></div></a></span><span class=\"css-1xxlsgn ewf2cv0\"><span class=\"num\">1,537,396</span><span class=\"unit\">pt</span></span></li><li class=\"e4ddjh0 css-186ana7 ex3haug0\"><span class=\"css-1eu4g1y ehnruze0\">2</span><span class=\"team-color\"><div class=\"team-background-color\" style=\"background-color:#F19EC2\"></div></span><span class=\"css-qrjx5q ejhaeu10\"><button class=\"team-name-button\" type=\"button\">めんこいな東北</button></span><span class=\"thumbs\"><a class=\"css-0 e10qwino0\" href=\"/u/18849884\"><div class=\"item-thumbs\"><span class=\"css-14dzdfy e1bokax20\" tabindex=\"0\"><img src=\"https://d2jtsb989t238a.cloudfront.net/p/18849884/1781518965/small\" alt=\"東北応援プロジェクト『めんこいな東北』\" class=\"thumb-img\" loading=\"lazy\"></span></div></a></span><span class=\"css-1xxlsgn ewf2cv0\"><span class=\"num\">886,920</span><span class=\"unit\">pt</span></span></li></ul></div>",
  "ogDescription": "開催期間 2026/06/15 18:00 ~ 2026/07/17 22:00",
  "bannerImageUrl": "https://d2uqarpmf42qy0.cloudfront.net/torte/event/24084/banner.png",
  "detailHtml": "<div class=\"content\"><style>*{max-width:100% !important;}*::before{max-width:100% !important;}*::after{max-width:100% !important;};  .cf:after{content:&apos; &apos;;display:block;clear:both;height:0;}.cf{display:inline-block;}.cf{display:block;}body{background:#f8f7f4;font-family:Hiragino Kaku Gothic Pro,Meiryo,MS PGothic,sans-serif;font-size:16px;line-height:1.4;letter-spacing:0.05em;margin:0px;color:#3c3c3c;overflow-y:hidden;overflow-x:hidden;padding:0px 5px;}img{vertical-align:bottom;border:none;outline:none;}a,.text-link{text-decoration:none;outline:none;color:#ef9500;cursor:pointer;}a:hover,.text-link:hover{text-decoration:underline;}input,select,option,textarea{font-family:Hiragino Kaku Gothic Pro,Meiryo,MS PGothic,sans-serif;}.center{text-align:center;}.right{text-align:right;}.button-green{color:#fff;display:block;width:100%;box-sizing:border-box;padding:10px 0 9px 0;margin:0 auto;cursor:pointer;font-size:15px;font-weight:bold;text-align:center;border-radius:3px;-moz-border-radius:3px;-webkit-border-radius:3px;background-color:#65b721;background-image:-webkit-gradient(\n      linear,left top,left bottom,from(#6ac023),to(#65b721)\n    );background-image:-webkit-linear-gradient(top,#6ac023,#65b721);background-image:-moz-linear-gradient(top,#6ac023,#65b721);background-image:-o-linear-gradient(top,#6ac023,#65b721);background-image:linear-gradient(top,#6ac023,#65b721);border:solid 1px #61bc14;text-shadow:0 1px 1px #135e00;box-shadow:0 3px 0 #467f17;}.button-green:hover{text-decoration:none;background:#84d933;}.button-green-s{color:#fff;box-sizing:border-box;cursor:pointer;font-weight:bold;text-align:center;border-radius:3px;-moz-border-radius:3px;-webkit-border-radius:3px;background-color:#65b721;background-image:-webkit-gradient(\n      linear,left top,left bottom,from(#6ac023),to(#65b721)\n    );background-image:-webkit-linear-gradient(top,#6ac023,#65b721);background-image:-moz-linear-gradient(top,#6ac023,#65b721);background-image:-o-linear-gradient(top,#6ac023,#65b721);background-image:linear-gradient(top,#6ac023,#65b721);text-shadow:0 1px 1px #135e00;display:inline-block;font-size:16px;padding:8px 11px 7px 11px;margin:0;width:auto;border:solid 1px #61bc14;box-shadow:0 3px 0 #467f17;}.button-green-s:hover{text-decoration:none;background:#84d933;}.content{background:#fff;margin:0 0 20px 0;padding:0 0 1px 0;box-shadow:0 1px 1px #ccc;}.content p{padding:0 10px;margin:0 0 10px 0;}.content h1{display:none;}.content h2{font-size:16px;background:#f5f5f5;border-left:solid 8px #cece2b;padding:8px 0 8px 8px;}.content h3{padding:0 0 0 5px;margin:0;}.menu{background-color:#333;padding:5px 30px;color:white;width:100%;}</style><div style=\"max-width:480px;margin:0 auto;\">\n<div style=\"background:center/9% url(https://d2uqarpmf42qy0.cloudfront.net/event/24matsutani/260427_rakuten_bg.png);background-position:top;\">\n<br>\n\n<!-- 💡タブセクションはじめ -->\n<div class=\"tab-content\">\n<input type=\"radio\" id=\"tab1\" name=\"tab\" checked=\"\">\n<label for=\"tab1\" style=\"margin:0px 0px 0px 15px;\">イベント概要</label>\n<input type=\"radio\" id=\"tab2\" name=\"tab\">\n<label for=\"tab2\">特典</label>\n<input type=\"radio\" id=\"tab3\" name=\"tab\">\n<label for=\"tab3\">メンバー紹介</label>\n<!--<input type=\"radio\" id=\"tab4\" name=\"tab\">\n<label for=\"tab4\">2次審査</label>-->\n\n<!-- 💡タブセクションおわり -->\n<div class=\"tab-box\">\n<!-- 💡1タブの中身はじめ -->\n<div id=\"tabView1\">\n\n<div class=\"box\">\n<h3 class=\"logo\">　現在の合計得点　</h3>\n<p style=\"margin:10px;font-size:15px;\">\n</p><center>\n<iframe src=\"https://docs.google.com/spreadsheets/d/e/2PACX-1vRVsl5RICWmg2mSUjHoLkTheE10DpuCmBA_2S6dOKHV-ic2L4NBzLwqZ9vq6tO9MhcWbQXUKlI4Hwsp/pubhtml?gid=661505369&amp;single=false&amp;chrome=false&amp;range=A1%3AC20\" width=\"70%\" height=\"120px\"></iframe>\n</center>\n<p></p>\n\n</div>\n\n<div class=\"box\">\n<h3 class=\"logo\">　概要　</h3>\n<br>\n<center>\n<p style=\"margin:10px;font-size:15px;\">\n関東を拠点として活動する東北出身メンバー！<br>\n奥羽山脈のてっぺんを目指して、<br>\nライブやSNSを通して東北を！日本を！<br>\n元気にすべく活動するアイドルグループ<br>\nこの夏、東北を盛り上げるのは、<br>\n<font size=\"3\"><b>＼ <span style=\"background:linear-gradient(transparent 80%, #FBDCEB 10%);\">けっぱって東北</span></b> ／</font><br>\n<font size=\"3\"><b>＼ <span style=\"background:linear-gradient(transparent 80%, #FBDCEB 10%);\">めんこいな東北</span></b> ／</font><br><br>\n\n東北6県出身メンバー全11名が、<br>東北の魅力を全国に届けるべく活動中。<br><br>\n今回は、けっぱって東北・めんこいな東北の<br><b><big>チーム戦‼️</big></b><br>\nチームワークで素敵な特典をGETしよう！<br>\n<br>\n今回はなんと！<br>\n8月13日(木)に楽天モバイル 最強パーク宮城にて行われる<br>\n「 <b><font color=\"#870011\"><big><u>ミクチャDAY</u></big></font></b> 」<br>\nのPRステージへの出演権やビジョン掲載、のぼり掲載も…📣⚾️</p>\n<img src=\"https://d2uqarpmf42qy0.cloudfront.net/event/24matsutani/260509_rakutenKV.png\" width=\"80%\">\n<p style=\"margin:10px;font-size:15px;\">\n<a href=\"https://mixch.tv/p/n5zxlvjc\" target=\"_blank\" referrerpolicy=\"no-referrer\">⚾️ <b>ミクチャDAY詳細はこちら</b> ⚾️</a>\n</p>\n\n<p style=\"margin:10px;font-size:15px;\">\nみんなでけっぱって東北とめんこいな東北を<br>全力応援しよう🌈</p>\n</center></div>\n\n<div class=\"box\">\n<h3 class=\"logo\"><center> スケジュール </center></h3>\n<p style=\"margin:15px;font-size:15px;\">\n<b>🌟 本選</b>\n</p><p style=\"margin:8px;font-size:16px;\">\n　　06/15(月)18:00～07/17(金)22:00<br><br>\n\n</p><p style=\"margin:15px;font-size:15px;\">\n<b>【配信時間について】</b><br>\n6/15(月)18:00〜6/21(日)23:59で20時間以内、以降、月曜～日曜で最大20時間以内となります。<br>\n最終週は7/13(月)00:00〜7/17(金)22:00で10時間以内の配信となります。\n<br>\n</p></div>\n\n<div class=\"box\">\n<center><br>\nこのイベントでは<br>\n<span class=\"emphasized-text font-big\">ムービー + ライブ配信  合算</span><br>\nのポイントがランキングに表示されます！<br>\n<br></center>\n</div>\n\n<div class=\"box\">\n<h3 class=\"logo\"><center>イベントの審査基準について</center></h3>\n<p style=\"margin:20px;font-size:14px;\">\n<iframe width=\"100%\" height=\"220\" src=\"https://www.youtube-nocookie.com/embed/nI804sGCn5c\" frameborder=\"0\" allow=\"accelerometer; autoplay; clipboard-write; encrypted-media; gyroscope; picture-in-picture\" allowfullscreen=\"\"></iframe></p><p>\n<br>\n<b>●審査基準</b><br>\n・イベント選択して、\n<span style=\"background:linear-gradient(transparent 90%, #ff0000 0%);\"><b>投稿した動画で獲得したpt</b></span>\nと\n<span style=\"background:linear-gradient(transparent 90%, #ff0000 0%);\"><b>ライブ配信で獲得したpt</b></span>\nの合算からランキング入賞者に賞品をプレゼント！<br>\n<br>\n・今回のリニューアルでは投稿動画にもアイテムで応援できるようになったので、「配信する時間がなかなか取れないときに、\n<span style=\"background:linear-gradient(transparent 90%, #ff0000 0%);\"><b>スキマ時間に撮った動画でアイテムを受け取る</b></span>」なんてことも出来ちゃいます🎁<br>\n<br>\n・さらにダンスや楽器演奏など場所や時間が限られるパフォーマンスだって、動画なら\n<span style=\"background:linear-gradient(transparent 90%, #ff0000 0%);\"><b>いつでも投稿・視聴・応援が可能！</b></span><br>\n<br>\n<b>●動画投稿に関しての紹介</b><br>\n</p><center><a class=\"link-btn\" href=\"https://mixch.tv/p/obcl5stv\" target=\"_blank\" referrerpolicy=\"no-referrer\"><center>動画投稿機能について</center></a></center>\n<center><a class=\"link-btn\" href=\"https://mixch.tv/p/0dwekkca\" target=\"_blank\" referrerpolicy=\"no-referrer\"><center>機能にまつわるヘルプページ</center></a></center>\n\n<p></p>\n</div>\n\n<div class=\"box\">\n<br>\n<p style=\"margin:20px;font-size:14px;\">\n※賞品が複数の場合、別々にお送りする場合がございます。<br>\n※賞品は日本国内のご住所にのみ発送が可能です。<br>\n※入賞者へのお知らせは、<u>ミクチャアプリ内の「あなたへのお知らせ」に届きます</u>ので、必ずご確認ください。<br><br>\n</p><div style=\"text-align:center;\">\n<a href=\"https://mixch.tv/p/qjtg97sp\" target=\"_blank\" referrerpolicy=\"no-referrer\">\n<img src=\"https://d2uqarpmf42qy0.cloudfront.net/event/koizumi/1811_kokoroe.png\" width=\"70%\">\n</a>\n</div>\n<br>\n<div style=\"font-size:15px;line-height:1.25;\">\n<div style=\"margin:10px;border:#192f60 solid 1px;display:block;padding:.2em .3em;\"><h3 style=\"border-left:#192f60 solid 6px;padding:.3em.3em.3em.8em;\">審査について</h3></div>\n<p style=\"margin:10px;\">\n●ライブ配信・動画投稿をする際は必ず<b><font color=\"#870011\">[ けっぱって東北 全国ツアー＆めんこいな東北 仙台ワンマン開催記念！ 東北応援＆ミクチャプロモーションプロジェクト ]のイベント選択</font></b>をお願いします。正しく選択をしていない場合は獲得したミクチャポイントがランキングに反映されませんのでご注意ください。また、誤ってイベント選択した際にポイントを対象イベントに反映することはできかねますので予めご了承ください。<br>\n<br>\n●当該ページの審査項目に沿って受賞者が決定いたします。なお、審査の過程や受賞者の決定に至った理由等につきましてはお答え出来ませんのであらかじめご了承ください。<br>\n<br>\n●獲得したポイントが同一の場合は、下記の条件に従って順位を決定します。((1)から条件を適用し、順位が決定しない場合はその次の条件を適用して決定し、以下同様の処理をします。)<br>\n<br>\n<font size=\"3\">\n　(1) 対象となるイベントを選択してライブ配信をした「配信時間」の合計が多いユーザーを上位とします。<br>\n　(2) 対象となるイベントを選択してライブ配信をした「配信回数」の合計が多いユーザーを上位とします。<br>\n　(3) 対象となるイベントを選択して行ったライブ配信・投稿動画に対して受け取った「コメント数」の合計が多いユーザーを上位とします。<br>\n　(4) 対象となるイベントへの応募申し込みが早かったユーザーを上位とします。<br>\n　(5) もし(1)～(5)全てが同じ場合はミクチャの「ユーザーIDの数字が小さい」ユーザーを上位とします。<br>\n</font>\n</p>\n<br>\n<p>※下記の注意事項も必ずお読みください。</p>\n<div style=\"margin:10px;border:#192f60 solid 1px;display:block;padding:.2em .3em;\"><h3 style=\"border-left:#192f60 solid 6px;padding:.3em.3em.3em.8em;\">アイテム送信に関する注意点</h3></div>\n<p>\n●ライブ配信で、イベント終了間際など同時間帯に大量のアイテムを投げると、多数のアイテムリクエストによりコイン消費に遅延が生じる可能性がございます。ムービーでは遅延が生じることはないので、ムービーイベントの場合は投稿動画への積極的な送信をご検討ください。<br>\n●ライブ配信の場合、イベント期間中にライバーの端末側でアイテムのアニメーション再生が始まったアイテムはイベントのポイントに加算されます。イベント期間中に再生失敗したアイテムやイベント期間をすぎてから再生されたアイテムは、イベントのポイントに加算されません。<br>\n●なお、上記の事象が発生した場合においても、イベントへのポイント反映やコインの返却などのご対応は出来かねますのでご了承くださいませ。<br>\nそのため、ライブ配信ではできるだけ一気に大量に送るのではなく、定期的にアイテムを送るかムービーへのアイテム送信を推奨いたします。<br>\n</p>\n<div style=\"margin:10px;border:#192f60 solid 1px;display:block;padding:.2em .3em;\"><h3 style=\"border-left:#192f60 solid 6px;padding:.3em.3em.3em.8em;\">応募規約</h3></div>\n<p>\n本キャンペーンに応募いただける方（以下、「応募者」といいます。）は、以下をよくお読みいただき、同意の上ご応募ください。<br><br>\nミクチャにて、「イベントに参加する」をタップした時点で本規約に同意したものとみなします。万が一ご同意いただけない場合は応募を中止してください。<br>\n本規約の内容は、事前の告知なく変更される場合がありますので、予めご了承ください。<br>\n</p><div style=\"font-size:16px;padding:.75em 0;border-top:1px solid #192f60;border-bottom:1px solid #192f60;\">　▪️動画投稿・ライブ配信での注意事項</div>\n<br><p>\n●撮影・ライブ配信が禁止されている場所または危険な場所での撮影やライブ配信はお控え下さい。<br>\n●楽曲を使用する場合は著作権者から楽曲利用の許可がおりているものをお使いください。<br>\n●大声を出す・大音量で音楽を流す、道を塞ぐなど、人の迷惑になる行為は控えて、撮影やライブ配信を実施してください。<br>\n\n●応募者と一緒に投稿動画・ライブ配信に写っている方がいらっしゃる場合や、第三者の知的財産権が含まれる場合、必ず投稿やライブ配信前に権利者から使用許諾を得てください。<br>\nまた、応募者は投稿動画・ライブ配信について自らが投稿・ライブ配信することについての適法な権利を有していること及び第三者の一切の権利を侵害していないことについて当社に対し表明し、保証するものとします。万が一、第三者からの権利侵害等の申し立てがあった場合には、投稿者や配信者ご自身の責任をもって解決していただきますので、予めご了承ください。<br>\n●ミクチャ以外のプラットフォームで作成した動画をミクチャでアップロードする場合、当該プラットフォームの利用規約に沿って投稿してください。<br>\n●未成年の方は保護者の同意を得た上でご応募ください。また、必要に応じて、在籍する学校または所属する部活動が加盟する連盟等へ確認をとったうえで応募してください。<br>\n●事務所、劇団、その他の団体（以下「事務所等」といいます）に所属されている方は、ご自身の責任で事務所等に本キャンペーンへの応募の可否につきご確認ください。<br>\n●コンテストなどの新しい才能の発掘を目的としたものや、事務所所属者や新グループメンバーの選定を目的とした一般的な「オーディション」に関するイベントには、キャッシュバックのお支払いはございません。なお、一部対象外のものもございますので、ご不明な場合はお問い合わせください。<br>\n●上記各項への違反や極端に他人に不快感を与えるような言動や、法律に抵触する内容、ミクチャの利用規約に違反した内容、運営事務局が不適切と判断した動画やライブ配信については削除、もしくはキャッシュバックや審査、受賞の対象外とする可能性がございますのでご了承ください。<br>\n●本応募規約に定める事項のほか、ミクチャ利用規約及びプライバシーポリシーが適用されますので、確認の上、ご応募ください。<br>\n\n</p><div style=\"font-size:16px;padding:.75em 0;border-top:1px solid #192f60;border-bottom:1px solid #192f60;\">　▪️賞品・受賞について</div>\n<br>\n<p>\n●受賞者と連絡がつかない場合、賞品受領の意思が確認できない場合、指定された期日までに連絡先をご返信いただけない場合等には、受賞を辞退されたものとみなし、受賞を無効とさせていただきます。予めご了承ください。<br>\n●受賞の権利は受賞者ご本人のものであって、第三者へ譲渡・換金等することはできません。また、受領した賞品の紛失等による再送付、受賞者の事情による変更、その他クレーム等には一切応じることができません。<br>\n●当社は、賞品の品質及び、目的適合性について何ら保証することはできかねます。賞品の使用に当たっては、賞品に記載の注意事項をご確認の上、ご使用ください。受賞された賞品の使用中に生じた事故等のトラブルについての責任は、当社では負いかねます。<br>\n●賞品提供元の何らかの事由により特典不履行となる事案が生じた場合は、代替賞品による補填などで対応することがございますのでご了承くださいませ。<br>\n<br>\n</p><div style=\"font-size:16px;padding:.75em 0;border-top:1px solid #192f60;border-bottom:1px solid #192f60;\">　▪️禁止事項</div>\n<br>\n<p>\n本キャンペーンへの応募に際し、以下の行為を禁止します。当社は、応募者が以下に該当する行為を行ったと判断した場合は、応募者への事前通告なく、対象投稿を掲載しない、掲載後削除する、応募・受賞を無効とするなどの対応をとる場合があります。<br>\n<br>\n・本規約または法令に違反する行為<br>\n・本キャンペーンの運営を妨げる行為<br>\n・他人に迷惑、不利益、損害または不快感を与える行為<br>\n・他人を誹謗中傷し、またはその名誉若しくは信用を毀損する行為<br>\n・第三者の著作権その他の知的財産権を侵害する行為<br>\n・他人の財産、プライバシー若しくは肖像権を侵害する行為<br>\n・わいせつ、児童ポルノ及び児童の性的搾取を助長するデータを投稿する行為<br>\n・営利を目的とした情報提供、広告宣伝もしくは勧誘行為<br>\n・公序良俗に反する行為<br>\n・ミクチャの利用規約に違反する行為<br>\n・その他、前各号に類する行為<br>\n<br>\n</p><div style=\"font-size:16px;padding:.75em 0;border-top:1px solid #192f60;border-bottom:1px solid #192f60;\">　▪️免責・その他</div>\n<br>\n<p>\n本キャンペーンは、細心の注意を払って運営をしていますが、提供する情報、プログラム、各種サービス、その他本キャンペーンに関するすべての事項について、その完全性、正確性、安全性、有用性等について、いかなる保証もするものではありません。また、利用者または第三者が被った以下の事例を含む損害については、当社は責任を負いかねます。 <br>\n<br>\n1.本キャンペーンへの応募に際して、ソフトウェア・ハードウェア上の事故、火災、停電、通信環境の悪化、地震、事変等の非常事態が発生した場合。<br>\n2.本キャンペーンにおけるシステムの保守を定期的あるいは緊急に行う場合。<br>\n3.利用者間または利用者と第三者の間におけるトラブル等が生じた場合。<br>\n4.第三者による本キャンペーンのサービスの妨害、情報改変などによりサービスが中断もしくは遅延し、何らかの欠陥が生じた場合。<br>\n5.当社が推奨する環境以外から本キャンペーンに応募したために情報を完全に取得できない場合。<br>\n6.故意または重過失なくして本キャンペーンが提供する情報が誤送信されるか、もしくは欠陥があった場合。<br>\n<br>\n当社は、本キャンペーンの応募により応募者に生じた一切のトラブル・損害（直接・間接を問いません）について、如何なる責任も負いません。<br>\n本キャンペーンの応募にかかるインターネット接続料及び通信費は応募者のご負担となります。<br>\n本キャンペーンは、ミクチャを提供している当社（株式会社Donuts）が運営しているものであり、Apple社によって提供されているものではございません。<br>\n<br>\n</p><div style=\"font-size:16px;padding:.75em 0;border-top:1px solid #192f60;border-bottom:1px solid #192f60;\">　▪️個人情報の取り扱いについて</div>\n<br>\n<p>住所、電話番号、氏名、性別、年齢、ミクチャアカウントURLの情報（以下「個人情報」といいます。）は、株式会社Donutsが管理します（管理責任者：ミクチャグループリーダー）。お客様の個人情報は、本キャンペーンの当選者への連絡・賞品の送付等の目的で利用し、それ以外の目的では使用致しません。また、お客様の個人情報をお客様の同意なしに業務委託先以外の第三者に開示・提供することはありません（法令等により開示を求められた場合を除きます。）。<br>\nまた、個人情報開示、訂正等のお問い合わせは、ミクチャ運営事務局（mixch-support@donuts.ne.jp）までお願い致します。<br>\n<br>\n</p><div style=\"font-size:16px;padding:.75em 0;border-top:1px solid #192f60;border-bottom:1px solid #192f60;\">　▪️キャンペーンに関するお問い合わせ窓口</div>\n<br>\n<p>[ミクチャスポンサー事務局]<br>\nmixch-support@donuts.ne.jp<br><br>\n</p></div>\n</div>\n<center><img src=\"https://d2uqarpmf42qy0.cloudfront.net/event/NIKU/mixch_LOGO.png\" width=\"20%\"></center>\n\n</div>\n\n<!-- 1タブの中身おわり💡 -->\n\n<!-- 💡2タブの中身はじめ -->\n\n<div id=\"tabView2\">\n\n\n<div class=\"box\">\n<h3 class=\"logo\"><center>けっぱって東北チームポイント達成特典 </center></h3>\n\n<center><img src=\"https://d2uqarpmf42qy0.cloudfront.net/event/24matsutani/2605_KPT-B05_A01_123.jpg\" width=\"85%\"></center>\n\n<p style=\"margin:8px;\"><br><br>\n<font size=\"3\"><span style=\"background:linear-gradient(transparent 80%, #FBDCEB 10%);\">🎖️<b> 500,000pt達成</b></span></font><br>\n</p><p style=\"margin:8px;\"><br>\n</p><center><b><font size=\"3\">✨<s>8/1(土)</s>7/10(金) 起動画面掲載✨</font></b><p></p></center>\n\n<p style=\"margin:8px;\"><br><br>\n<font size=\"3\"><span style=\"background:linear-gradient(transparent 80%, #FBDCEB 10%);\">🎖️<b> 1,000,000pt達成</b></span></font><br>\n</p><p style=\"margin:8px;\"><br>\n</p><center><b><font size=\"3\">✨都内ビジョン掲載✨</font></b><p></p></center>\n\n<p style=\"margin:8px;\"><br>\n<font size=\"3\"><span style=\"background:linear-gradient(transparent 80%, #FBDCEB 10%);\">🎖️<b> 2,000,000pt達成</b></span></font><br>\n</p><p style=\"margin:8px;\"><br>\n</p><center>⚾️<b><font size=\"3\">楽天イーグルス応援企画 8/13『ミクチャDAY』<br>球場サンプリングうちわに掲載</font></b>🦅</center><br>\n<br>\n<p></p>\n<p style=\"margin:8px;\">\n<font size=\"3\"><span style=\"background:linear-gradient(transparent 80%, #FBDCEB 10%);\">🎖️<b> 3,000,000pt達成</b></span></font><br>\n</p><p style=\"margin:8px;\"><br>\n</p><center>🎤<b><font size=\"3\">楽天イーグルス応援企画 8/13『ミクチャDAY』<br>\nステージ出演</font>🎶</b></center><br>\n<br>\n<p></p>\n<p style=\"margin:8px;\">\n<font size=\"3\"><span style=\"background:linear-gradient(transparent 80%, #FBDCEB 10%);\">🎖️<b> 4,000,000pt達成</b></span></font><br>\n</p><p style=\"margin:8px;\"><br>\n</p><center>🌟<b><font size=\"3\">全国ツアー大型プロモーション決定</font></b>🌟</center><br>\n<br>\n<p></p>\n\n</div>\n\n<div class=\"box\">\n<h3 class=\"logo\"><center>めんこいな東北チームポイント達成特典 </center></h3>\n<center><img src=\"https://d2uqarpmf42qy0.cloudfront.net/event/24matsutani/2607_MKN-07_A01_0.jpg\" width=\"85%\"></center>\n\n<p style=\"margin:8px;\"><br><br>\n<font size=\"3\"><span style=\"background:linear-gradient(transparent 80%, #FBDCEB 10%);\">🎖️<b> 500,000pt達成</b></span></font><br>\n</p><p style=\"margin:8px;\"><br>\n</p><center><b><font size=\"3\">✨<s>8/2(日)</s>7/10(金) 起動画面掲載✨</font></b><p></p></center>\n\n\n<p style=\"margin:8px;\"><br><br>\n<font size=\"3\"><span style=\"background:linear-gradient(transparent 80%, #FBDCEB 10%);\">🎖️<b> 1,000,000pt達成</b></span></font><br>\n</p><p style=\"margin:8px;\"><br>\n</p><center><b><font size=\"3\">✨都内ビジョン掲載✨</font></b><p></p></center>\n\n<p style=\"margin:8px;\"><br>\n<font size=\"3\"><span style=\"background:linear-gradient(transparent 80%, #FBDCEB 10%);\">🎖️<b> 2,000,000pt達成</b></span></font><br>\n</p><p style=\"margin:8px;\"><br>\n</p><center>⚾️<b><font size=\"3\">楽天イーグルス応援企画 8/13『ミクチャDAY』<br>球場サンプリングうちわに掲載</font></b>🦅</center><br>\n<br>\n<p></p>\n<p style=\"margin:8px;\">\n<font size=\"3\"><span style=\"background:linear-gradient(transparent 80%, #FBDCEB 10%);\">🎖️<b> 3,000,000pt達成</b></span></font><br>\n</p><p style=\"margin:8px;\"><br>\n</p><center>🎤<b><font size=\"3\">楽天イーグルス応援企画 8/13『ミクチャDAY』<br>\nステージ出演</font>🎶</b></center><br>\n<br>\n<p></p>\n<p style=\"margin:8px;\">\n<font size=\"3\"><span style=\"background:linear-gradient(transparent 80%, #FBDCEB 10%);\">🎖️<b> 4,000,000pt達成</b></span></font><br>\n</p><p style=\"margin:8px;\"><br>\n</p><center>🌟<b><font size=\"3\">11/28 仙台MACANAワンマン大型プロモーション決定！</font></b>🌟</center><br>\n<br>\n<p></p>\n\n</div>\n\n<div class=\"box\">\n<h3 class=\"logo\"><center>全体チームポイント達成特典 </center></h3>\n\n<p style=\"margin:8px;\">\n<font size=\"3\"><span style=\"background:linear-gradient(transparent 80%, #FBDCEB 10%);\">🎖️<b> 合計6,000,000pt達成</b></span></font><br>\n</p><p style=\"margin:8px;\"><br>\n</p><center>🚩<b><font size=\"3\">楽天イーグルス応援企画 8/13『ミクチャDAY』<br>\n球場ビジョン掲載</font>🎶</b></center><br>\n<br>\n<p></p>\n\n<p style=\"margin:8px;\">\n<font size=\"3\"><span style=\"background:linear-gradient(transparent 80%, #FBDCEB 10%);\">🎖️<b> 合計7,000,000pt達成</b></span></font><br>\n</p><p style=\"margin:8px;\"><br>\n</p><center>🚩<b><font size=\"3\">楽天イーグルス応援企画 8/13『ミクチャDAY』<br>\n全メンバー！球場ののぼり掲載</font>🎶</b></center><br>\n<br>\n<p></p>\n\n<p style=\"margin:8px;\">\n<font size=\"3\"><span style=\"background:linear-gradient(transparent 80%, #FBDCEB 10%);\">🎖️<b> 合計8,000,000pt達成</b></span></font><br>\n</p><p style=\"margin:8px;\"><br>\n</p><center>💿️<b><font size=\"3\">けっぱって東北＆めんこいな東北<br>\n全メンバーの新曲制作決定🎶🌟</font>🎶</b></center><br>\n<br>\n<p></p>\n\n</div>\n\n<div class=\"box\">\n<h3 class=\"logo\"><center>注意事項 </center></h3>\n\n<p style=\"margin:15px;font-size:15px;\">\n※サンプリングうちわへの掲載は、他のミクチャにて実施しているイベントとの合同掲載となります。予めご注意ください。<br>\n※球場でのビジョン放映は、タイミング等非公開となっておりますので予めご了承ください。詳細は受賞者に別途ご共有いたします。<br>\n※都内ビジョン放映は2026年9月以降を予定しております。<br>\n※のぼりの設置場所は当日までご共有できかねますので、ミクチャDAY当日にお探しいただくようお願いいたします。なお、強風や悪天候等の場合、球団判断にて掲出を取りやめる可能性もございます。掲出が取りやめになった場合も、補填や代替対応、コインの返金等は一切ございませんので予めご了承ください。<br>\n※「のぼり掲出」はけっぱって東北とめんこいな東北のチーム獲得合計ポイント達成にてメンバー全員分ののぼりを掲出いたします。\n</p>\n\n</div>\n\n<p></p><center><img src=\"https://d2uqarpmf42qy0.cloudfront.net/event/NIKU/mixch_LOGO.png\" width=\"20%\"></center><br><p></p>\n\n<p></p></div><p></p>\n\n<!-- 2タブの中身おわり💡 -->\n\n<!-- 💡3タブの中身はじめ -->\n\n<div id=\"tabView3\">\n\n<div class=\"box\">\n<h3 class=\"logo\"><center>メンバー募集中！ </center></h3>\n\n<center>\n<p style=\"margin:10px;font-size:15px;\">\n<font size=\"3\"><b><span style=\"background:linear-gradient(transparent 80%, #FBDCEB 10%);\">東北応援プロジェクト<br>「けっぱって東北」「めんこいな東北」</span><br>\n東北出身者限定！新メンバー募集中！</b></font></p><font size=\"3\">\n<a class=\"link-btn\" href=\"https://lin.ee/WujcdNS\" style=\"font-size:14px;\" target=\"_blank\" referrerpolicy=\"no-referrer\">応募はこちらから</a>\n</font></center><font size=\"3\">\n\n\n</font></div><font size=\"3\">\n\n<div class=\"box\">\n<h3 class=\"logo\"><center>メンバー紹介 </center></h3>\n\n<center><img src=\"https://d2uqarpmf42qy0.cloudfront.net/event/24matsutani/260605_logo_kpt.png\" width=\"50%\"></center>\n\n<div style=\"margin:15px;padding:7px;background-color:#870011;text-align:center;font-size:16px;color:#fff;width:85%;border-radius:10px;\">\n<b>＼ けっぱって東北メンバー一覧 ／</b>\n</div>\n\n<table width=\"100%\">\n<tbody><tr><td width=\"50%\">\n<center><img src=\"https://d2uqarpmf42qy0.cloudfront.net/event/24matsutani/KPT_FK-A_65076_ue8.png\" width=\"83%\">\n<br><br>\n<b><font style=\"background:linear-gradient(transparent 80%, #e95464 0%);\">福島 ゆか</font></b><br><br>\n<center><b> <a class=\"link-btn\" href=\"https://mixch.tv/u/14637175\" style=\"font-size:14px;\" target=\"_blank\" referrerpolicy=\"no-referrer\">ミクチャページ</a> </b></center>\n<div style=\"filter:invert(50%) sepia(15%) saturate(17%) hue-rotate(10deg) brightness(90%) contrast(95%);\">\n<a href=\"https://x.com/veryuka\" target=\"_blank\" referrerpolicy=\"no-referrer\"><img src=\"https://d2uqarpmf42qy0.cloudfront.net/event/41haba/ツイッター素材青.png\" width=\"20%\"></a>\n<a href=\"https://www.instagram.com/yuka_fukushima_/\" target=\"_blank\" referrerpolicy=\"no-referrer\"><img src=\"https://d2uqarpmf42qy0.cloudfront.net/event/35ishimatsu/Instagram丸_黒.png\" width=\"20%\"></a>\n<a href=\"https://www.tiktok.com/@yuka_fukushima_\" target=\"_blank\" referrerpolicy=\"no-referrer\"><img src=\"https://d2uqarpmf42qy0.cloudfront.net/event/41haba/ティックトック素材青.png\" width=\"20%\"></a></div>\n</center></td>\n\n<td width=\"50%\">\n<center><img src=\"https://d2uqarpmf42qy0.cloudfront.net/event/24matsutani/KPT_KH-A_9427_ue8.png\" width=\"88%\">\n<br><br>\n<b><font style=\"background:linear-gradient(transparent 80%, #3eb370 0%);\">小日向 あおい</font></b><br><br>\n<center><b> <a class=\"link-btn\" href=\"https://mixch.tv/u/16067761\" style=\"font-size:14px;\" target=\"_blank\" referrerpolicy=\"no-referrer\">ミクチャページ</a> </b></center>\n<div style=\"filter:invert(50%) sepia(15%) saturate(17%) hue-rotate(10deg) brightness(90%) contrast(95%);\">\n<a href=\"https://x.com/aoikopinata\" target=\"_blank\" referrerpolicy=\"no-referrer\"><img src=\"https://d2uqarpmf42qy0.cloudfront.net/event/41haba/ツイッター素材青.png\" width=\"20%\"></a>\n<a href=\"https://www.instagram.com/aoi_kopinata/\" target=\"_blank\" referrerpolicy=\"no-referrer\"><img src=\"https://d2uqarpmf42qy0.cloudfront.net/event/35ishimatsu/Instagram丸_黒.png\" width=\"20%\"></a>\n<a href=\"https://www.tiktok.com/@aoikopinata\" target=\"_blank\" referrerpolicy=\"no-referrer\"><img src=\"https://d2uqarpmf42qy0.cloudfront.net/event/41haba/ティックトック素材青.png\" width=\"20%\"></a></div>\n</center>\n</td>\n</tr></tbody></table>\n<br>\n\n<table width=\"100%\">\n<tbody><tr><td width=\"50%\">\n<center><img src=\"https://d2uqarpmf42qy0.cloudfront.net/event/24matsutani/KPT_SK-A_47688_ue8.png\" width=\"78%\">\n<br><br>\n<b><font style=\"background:linear-gradient(transparent 80%, #eebbcb 0%);\">佐藤 櫻子</font></b><br><br>\n<center><b> <a class=\"link-btn\" href=\"https://mixch.tv/u/17786123\" style=\"font-size:14px;\" target=\"_blank\" referrerpolicy=\"no-referrer\">ミクチャページ</a> </b></center>\n<div style=\"filter:invert(50%) sepia(15%) saturate(17%) hue-rotate(10deg) brightness(90%) contrast(95%);\">\n<a href=\"https://x.com/shakuranoko\" target=\"_blank\" referrerpolicy=\"no-referrer\"><img src=\"https://d2uqarpmf42qy0.cloudfront.net/event/41haba/ツイッター素材青.png\" width=\"20%\"></a>\n<a href=\"https://www.instagram.com/shakuranoko/\" target=\"_blank\" referrerpolicy=\"no-referrer\"><img src=\"https://d2uqarpmf42qy0.cloudfront.net/event/35ishimatsu/Instagram丸_黒.png\" width=\"20%\"></a>\n<a href=\"https://www.tiktok.com/@yama_kano\" target=\"_blank\" referrerpolicy=\"no-referrer\"><img src=\"https://d2uqarpmf42qy0.cloudfront.net/event/41haba/ティックトック素材青.png\" width=\"20%\"></a></div>\n</center>\n</td>\n\n<td width=\"50%\">\n<center><img src=\"https://d2uqarpmf42qy0.cloudfront.net/event/24matsutani/KPT_SD-A_0416_ue8.png\" width=\"87%\">\n<br><br>\n<b><font style=\"background:linear-gradient(transparent 80%, #2792c3 0%);\">志田 結華</font></b><br><br>\n<center><b> <a class=\"link-btn\" href=\"https://mixch.tv/u/18368703\" style=\"font-size:14px;\" target=\"_blank\" referrerpolicy=\"no-referrer\">ミクチャページ</a> </b></center>\n<div style=\"filter:invert(50%) sepia(15%) saturate(17%) hue-rotate(10deg) brightness(90%) contrast(95%);\">\n<a href=\"https://x.com/shidadabe\" target=\"_blank\" referrerpolicy=\"no-referrer\"><img src=\"https://d2uqarpmf42qy0.cloudfront.net/event/41haba/ツイッター素材青.png\" width=\"20%\"></a>\n<a href=\"https://www.instagram.com/shidadabe/\" target=\"_blank\" referrerpolicy=\"no-referrer\"><img src=\"https://d2uqarpmf42qy0.cloudfront.net/event/35ishimatsu/Instagram丸_黒.png\" width=\"20%\"></a>\n<a href=\"https://www.tiktok.com/@shidadabe&gt;&lt;img src=\" https:=\"\" d2uqarpmf42qy0.cloudfront.net=\"\" event=\"\" 41haba=\"\" ティックトック素材青.png\"=\"\" width=\"20%\" target=\"_blank\" referrerpolicy=\"no-referrer\"></a></div>\n</center></td>\n</tr></tbody></table>\n<br>\n\n<table width=\"100%\">\n<tbody><tr><td width=\"50%\">\n<center><img src=\"https://d2uqarpmf42qy0.cloudfront.net/event/24matsutani/KPT_MN-A_61184_ue8.png\" width=\"38%\">\n<br><br>\n<b><font style=\"background:linear-gradient(transparent 80%, #ba55d3 0%);\">山本 奏羽</font></b><br><br>\n<center><b> <a class=\"link-btn\" href=\"https://mixch.tv/u/18907564\" style=\"font-size:14px;\" target=\"_blank\" referrerpolicy=\"no-referrer\">ミクチャページ</a> </b></center>\n<div style=\"filter:invert(50%) sepia(15%) saturate(17%) hue-rotate(10deg) brightness(90%) contrast(95%);\">\n<a href=\"https://x.com/kanau__yamamoto\" target=\"_blank\" referrerpolicy=\"no-referrer\"><img src=\"https://d2uqarpmf42qy0.cloudfront.net/event/41haba/ツイッター素材青.png\" width=\"10%\"></a>\n<a href=\"https://www.instagram.com/kanau_yamamoto/\" target=\"_blank\" referrerpolicy=\"no-referrer\"><img src=\"https://d2uqarpmf42qy0.cloudfront.net/event/35ishimatsu/Instagram丸_黒.png\" width=\"10%\"></a>\n<a href=\"https://www.tiktok.com/@kanau_yamamoto\" target=\"_blank\" referrerpolicy=\"no-referrer\"><img src=\"https://d2uqarpmf42qy0.cloudfront.net/event/41haba/ティックトック素材青.png\" width=\"10%\"></a></div>\n</center>\n</td>\n\n</tr></tbody></table>\n\n<p><br><br>\n</p><p style=\"margin:10px;font-size:15px;\">\nけっぱって東北 4thワンマンライブ<br>\n<font size=\"3\"><b><span style=\"background:linear-gradient(transparent 80%, #FBDCEB 10%);\">\n『ふるさと2026』全国ツアー開催！<br></span></b></font>\n</p><center><iframe width=\"320\" height=\"180\" src=\"https://www.youtube.com/embed/uYnR7EAYv88?si=SC6NRMfIKaXEln0z\" title=\"YouTube video player\" frameborder=\"0\" allow=\"accelerometer; autoplay; clipboard-write; encrypted-media; gyroscope; picture-in-picture; web-share\" referrerpolicy=\"strict-origin-when-cross-origin\" allowfullscreen=\"\"></iframe></center>\n<p style=\"margin:10px;font-size:15px;\">\n7/26(日) 秋田SWINDLE<br>\n<br>\n8/1(土) 大阪RUIDO<br>\n<br>\n8/8(土) 盛岡CHANGE WAVE<br>\n<br>\n8/15(土) 札幌cube garden<br>\n<br>\n8/22(土) 山形MUSIC SHOWA<br>\n<br>\n9/5(土) 名古屋レジェンドルホール<br>\n<br>\n9/12(土) 仙台MACANA<br>\n<br>\n9/27(日) 青森Quater<br>\n<br>\n10/12(祝) 郡山#9<br>\n<br>\n10/17(土) 福岡CB<br>\n<br>\n10/31(土) 東京ツアーファイナル 赤羽ReNY\n</p>\n <center><b> <a class=\"link-btn\" href=\"https://event.tiget.net/kpt-tohoku_tour2026\" style=\"font-size:14px;\" target=\"_blank\" referrerpolicy=\"no-referrer\">特設ページはこちらから</a> </b></center>\n<br>\n</div><p></p>\n\n<div class=\"box\">\n<h3 class=\"logo\"><center>メンバー紹介 </center></h3>\n\n<center><img src=\"https://d2uqarpmf42qy0.cloudfront.net/event/24matsutani/2505_MKN_logo_B.png\" width=\"50%\"></center>\n\n<div style=\"margin:15px;padding:7px;background-color:#870011;text-align:center;font-size:16px;color:#fff;width:85%;border-radius:10px;\">\n<b>＼ めんこいな東北メンバー一覧 ／</b>\n</div>\n\n<table width=\"100%\">\n<tbody><tr><td width=\"50%\">\n<center><img src=\"https://d2uqarpmf42qy0.cloudfront.net/event/24matsutani/MKN_成瀬花音_0023.png\" width=\"78%\">\n<br><br>\n<b><font style=\"background:linear-gradient(transparent 80%, #ff69b4 0%);\">成瀬花音</font></b><br><br>\n<center><b> <a class=\"link-btn\" href=\"https://mixch.tv/u/17493265\" style=\"font-size:14px;\" target=\"_blank\" referrerpolicy=\"no-referrer\">ミクチャページ</a> </b></center>\n<div style=\"filter:invert(50%) sepia(15%) saturate(17%) hue-rotate(10deg) brightness(90%) contrast(95%);\">\n<a href=\"https://x.com/kanon321_\" target=\"_blank\" referrerpolicy=\"no-referrer\"><img src=\"https://d2uqarpmf42qy0.cloudfront.net/event/41haba/ツイッター素材青.png\" width=\"20%\"></a>\n<a href=\"https://www.instagram.com/kanon321_/\" target=\"_blank\" referrerpolicy=\"no-referrer\"><img src=\"https://d2uqarpmf42qy0.cloudfront.net/event/35ishimatsu/Instagram丸_黒.png\" width=\"20%\"></a>\n<a href=\"https://www.tiktok.com/@k_.0321\" target=\"_blank\" referrerpolicy=\"no-referrer\"><img src=\"https://d2uqarpmf42qy0.cloudfront.net/event/41haba/ティックトック素材青.png\" width=\"20%\"></a></div>\n</center></td>\n\n<td width=\"50%\">\n<center><img src=\"https://d2uqarpmf42qy0.cloudfront.net/event/24matsutani/MKN_天野玲菜_0310.png\" width=\"73%\">\n<br><br>\n<b><font style=\"background:linear-gradient(transparent 80%, #ffd700 0%);\">天野玲菜</font></b><br><br>\n<center><b> <a class=\"link-btn\" href=\"https://mixch.tv/u/18525892\" style=\"font-size:14px;\" target=\"_blank\" referrerpolicy=\"no-referrer\">ミクチャページ</a> </b></center>\n<div style=\"filter:invert(50%) sepia(15%) saturate(17%) hue-rotate(10deg) brightness(90%) contrast(95%);\">\n<a href=\"https://x.com/amano_o11\" target=\"_blank\" referrerpolicy=\"no-referrer\"><img src=\"https://d2uqarpmf42qy0.cloudfront.net/event/41haba/ツイッター素材青.png\" width=\"20%\"></a>\n<a href=\"https://www.instagram.com/amano.o11/\" target=\"_blank\" referrerpolicy=\"no-referrer\"><img src=\"https://d2uqarpmf42qy0.cloudfront.net/event/35ishimatsu/Instagram丸_黒.png\" width=\"20%\"></a>\n<a href=\"https://www.tiktok.com/@amano.o11\" target=\"_blank\" referrerpolicy=\"no-referrer\"><img src=\"https://d2uqarpmf42qy0.cloudfront.net/event/41haba/ティックトック素材青.png\" width=\"20%\"></a></div>\n</center>\n</td>\n</tr></tbody></table>\n<br>\n\n<table width=\"100%\">\n<tbody><tr><td width=\"50%\">\n<center><img src=\"https://d2uqarpmf42qy0.cloudfront.net/event/24matsutani/MKN_深月星来_0868.png\" width=\"78%\">\n<br><br>\n<b><font style=\"background:linear-gradient(transparent 80%, #1e90ff 0%);\">深月 星来</font></b><br><br>\n<center><b> <a class=\"link-btn\" href=\"https://mixch.tv/u/14467836\" style=\"font-size:14px;\" target=\"_blank\" referrerpolicy=\"no-referrer\">ミクチャページ</a> </b></center>\n<div style=\"filter:invert(50%) sepia(15%) saturate(17%) hue-rotate(10deg) brightness(90%) contrast(95%);\">\n<a href=\"https://x.com/seira_ichibann\" target=\"_blank\" referrerpolicy=\"no-referrer\"><img src=\"https://d2uqarpmf42qy0.cloudfront.net/event/41haba/ツイッター素材青.png\" width=\"20%\"></a>\n<a href=\"https://www.instagram.com/sei._.ichibannn/\" target=\"_blank\" referrerpolicy=\"no-referrer\"><img src=\"https://d2uqarpmf42qy0.cloudfront.net/event/35ishimatsu/Instagram丸_黒.png\" width=\"20%\"></a>\n<!-- <a href=\"https://www.tiktok.com/@yama_kano\"><img src=\"https://d2uqarpmf42qy0.cloudfront.net/event/41haba/ティックトック素材青.png\" width=\"20%\"></a> --></div>\n</center>\n</td>\n\n<td width=\"50%\">\n<center><img src=\"https://d2uqarpmf42qy0.cloudfront.net/event/24matsutani/MKN_今野夢子_0476.png\" width=\"78%\">\n<br><br>\n<b><font style=\"background:linear-gradient(transparent 80%, #7fffd4 0%);\">今野 夢子</font></b><br><br>\n<center><b> <a class=\"link-btn\" href=\"https://mixch.tv/u/18370129\" style=\"font-size:14px;\" target=\"_blank\" referrerpolicy=\"no-referrer\">ミクチャページ</a> </b></center>\n<div style=\"filter:invert(50%) sepia(15%) saturate(17%) hue-rotate(10deg) brightness(90%) contrast(95%);\">\n<a href=\"https://x.com/yume___kooo\" target=\"_blank\" referrerpolicy=\"no-referrer\"><img src=\"https://d2uqarpmf42qy0.cloudfront.net/event/41haba/ツイッター素材青.png\" width=\"20%\"></a>\n<a href=\"https://www.instagram.com/yumeko.konno/\" target=\"_blank\" referrerpolicy=\"no-referrer\"><img src=\"https://d2uqarpmf42qy0.cloudfront.net/event/35ishimatsu/Instagram丸_黒.png\" width=\"20%\"></a>\n<a href=\"https://www.tiktok.com/@yume.8.11\" target=\"_blank\" referrerpolicy=\"no-referrer\"><img src=\"https://d2uqarpmf42qy0.cloudfront.net/event/41haba/ティックトック素材青.png\" width=\"20%\"></a></div> \n</center></td>\n</tr></tbody></table>\n<br>\n\n<table width=\"100%\">\n<tbody><tr><td width=\"50%\">\n<center><img src=\"https://d2uqarpmf42qy0.cloudfront.net/event/24matsutani/MKN_涼風もな_0396.png\" width=\"74%\">\n<br><br>\n<b><font style=\"background:linear-gradient(transparent 80%, #c71585 0%);\">涼風 もな</font></b><br><br>\n<center><b> <a class=\"link-btn\" href=\"https://mixch.tv/u/18715576\" style=\"font-size:14px;\" target=\"_blank\" referrerpolicy=\"no-referrer\">ミクチャページ</a> </b></center>\n<div style=\"filter:invert(50%) sepia(15%) saturate(17%) hue-rotate(10deg) brightness(90%) contrast(95%);\">\n<a href=\"https://x.com/mona_suzukaze\" target=\"_blank\" referrerpolicy=\"no-referrer\"><img src=\"https://d2uqarpmf42qy0.cloudfront.net/event/41haba/ツイッター素材青.png\" width=\"20%\"></a>\n<a href=\"https://www.instagram.com/mona_suzukaze/\" target=\"_blank\" referrerpolicy=\"no-referrer\"><img src=\"https://d2uqarpmf42qy0.cloudfront.net/event/35ishimatsu/Instagram丸_黒.png\" width=\"20%\"></a>\n<a href=\"https://www.tiktok.com/@mona_suzukaze\" target=\"_blank\" referrerpolicy=\"no-referrer\"><img src=\"https://d2uqarpmf42qy0.cloudfront.net/event/41haba/ティックトック素材青.png\" width=\"20%\"></a></div>\n</center>\n</td>\n\n<td width=\"50%\">\n<center><img src=\"https://d2uqarpmf42qy0.cloudfront.net/event/24matsutani/MKN_KR_60948_ue8_0.png\" width=\"78%\">\n<br><br>\n<b><font style=\"background:linear-gradient(transparent 80%, #dcdcdc 0%);\">水谷 花鈴</font></b><br><br>\n<center><b> <a class=\"link-btn\" href=\"https://mixch.tv/u/18127545\" style=\"font-size:14px;\" target=\"_blank\" referrerpolicy=\"no-referrer\">ミクチャページ</a> </b></center>\n<div style=\"filter:invert(50%) sepia(15%) saturate(17%) hue-rotate(10deg) brightness(90%) contrast(95%);\">\n<a href=\"https://x.com/karitanpo\" target=\"_blank\" referrerpolicy=\"no-referrer\"><img src=\"https://d2uqarpmf42qy0.cloudfront.net/event/41haba/ツイッター素材青.png\" width=\"20%\"></a>\n<a href=\"https://www.instagram.com/karitanp0/\" target=\"_blank\" referrerpolicy=\"no-referrer\"><img src=\"https://d2uqarpmf42qy0.cloudfront.net/event/35ishimatsu/Instagram丸_黒.png\" width=\"20%\"></a>\n<a href=\"https://www.tiktok.com/@karitanp0\" target=\"_blank\" referrerpolicy=\"no-referrer\"><img src=\"https://d2uqarpmf42qy0.cloudfront.net/event/41haba/ティックトック素材青.png\" width=\"20%\"></a></div>\n</center>\n</td>\n\n</tr></tbody></table>\n\n<table width=\"100%\">\n<tbody><tr><td width=\"50%\">\n<center><img src=\"https://d2uqarpmf42qy0.cloudfront.net/event/24matsutani/MKN_四ノ宮すい_78760R.png\" width=\"38%\">\n<br><br>\n<b><font style=\"background:linear-gradient(transparent 80%, #ffa07a 0%);\">四ノ宮 すい</font></b><br><br>\n<center><b> <a class=\"link-btn\" href=\"https://mixch.tv/u/18911558\" style=\"font-size:14px;\" target=\"_blank\" referrerpolicy=\"no-referrer\">ミクチャページ</a> </b></center>\n<div style=\"filter:invert(50%) sepia(15%) saturate(17%) hue-rotate(10deg) brightness(90%) contrast(95%);\">\n<a href=\"https://x.com/sui_shinomiya\" target=\"_blank\" referrerpolicy=\"no-referrer\"><img src=\"https://d2uqarpmf42qy0.cloudfront.net/event/41haba/ツイッター素材青.png\" width=\"10%\"></a>\n<a href=\"https://www.instagram.com/suiss024\" target=\"_blank\" referrerpolicy=\"no-referrer\"><img src=\"https://d2uqarpmf42qy0.cloudfront.net/event/35ishimatsu/Instagram丸_黒.png\" width=\"10%\"></a>\n<a href=\"https://www.tiktok.com/@sui_2424\" target=\"_blank\" referrerpolicy=\"no-referrer\"><img src=\"https://d2uqarpmf42qy0.cloudfront.net/event/41haba/ティックトック素材青.png\" width=\"10%\"></a></div>\n</center>\n</td>\n\n</tr></tbody></table>\n\n<p><br><br>\n</p><p style=\"margin:10px;font-size:15px;\">\n<font size=\"3\"><b><span style=\"background:linear-gradient(transparent 80%, #FBDCEB 10%);\">めんこいな東北『めんこいL♡VE』CDデビュー！</span></b></font></p>\n<iframe allow=\"autoplay *; encrypted-media *; fullscreen *; clipboard-write\" frameborder=\"0\" height=\"450\" style=\"width:100%;max-width:660px;overflow:hidden;border-radius:10px;\" sandbox=\"allow-forms allow-popups allow-same-origin allow-scripts allow-storage-access-by-user-activation allow-top-navigation-by-user-activation\" src=\"https://embed.music.apple.com/jp/album/menkoi-love-single/1876108032\"></iframe><p></p>\n\n<p></p><center>\n<p style=\"margin:10px;font-size:15px;\">\n<font size=\"3\"><b><span style=\"background:linear-gradient(transparent 80%, #FBDCEB 10%);\">めんこいな東北1stワンマンライブ</span></b><br>\n11/28(土) ＠仙台MACANA\n</font></p><font size=\"3\">\n</font></center><font size=\"3\">\n</font></div><p></p><font size=\"3\">\n\n<!-- \n<div class=box>\n<h3 class=\"logo\"><center>メンバー募集中！ </center></h3>\n\n<center>\n<p style=\"margin:10px; font-size:11px;\">\n<font size=3><b><span style=\"background:linear-gradient(transparent 80%, #FBDCEB 10%);\">東北応援プロジェクト<br>「けっぱって東北」「めんこいな東北」</span><br>\n東北出身者限定！新メンバー募集中！</span></b></p>\n<a class=\"link-btn\" href=\"https://lin.ee/WujcdNS\" style=\"font-size:8px;\">応募はこちらから</a>\n</center>\n\n</div>\n-->\n\n<p></p><center><img src=\"https://d2uqarpmf42qy0.cloudfront.net/event/NIKU/mixch_LOGO.png\" width=\"20%\"></center><br><p></p>\n\n<p></p></font></font></div><p></p><font size=\"3\"><font size=\"3\">\n\n<style type=\"text/css\">.tab-content { max-width: 480px; margin: 0px auto; color: rgb(51, 51, 51); line-height: 1.75; font-size: 15px; font-family: \"Gill Sans\"; }\n.tab-content input[type=\"radio\"] { display: none; }\n.tab-content label { display: inline-block; margin: 10px 0px 0px; padding: 5px 17px; font-weight: bold; color: rgb(135, 0, 17); background: rgb(255, 255, 255); cursor: pointer; border: 2px solid rgb(135, 0, 17); border-radius: 14px; box-sizing: border-box; box-shadow: rgba(0, 0, 0, 0.45) 0px 3px 4px; }\n.tab-content input[type=\"radio\"]:checked + label { color: rgb(255, 255, 255); background-color: rgb(135, 0, 17); }\n.tab-content .tab-box { width: 100%; box-sizing: border-box; }\n.tab-content > .tab-box > div { display: none; }\n#tab1:checked ~ .tab-box > #tabView1, #tab2:checked ~ .tab-box > #tabView2, #tab3:checked ~ .tab-box > #tabView3, #tab4:checked ~ .tab-box > #tabView4, #tab5:checked ~ .tab-box > #tabView5 { display: block; }\nh3.logo { width: 90%; margin: 5px auto 10px; padding: 15px 0px 12px; border-bottom: 1.5px solid rgb(135, 0, 17); color: rgb(135, 0, 17); font-weight: bold; font-size: 16px; text-align: center; }\ndiv.content a.link-btn, div.content a.link-btn:link, div.content a.link-btn:visited { display: inline-block; padding: 5px 10px; border: 1px solid rgb(214, 232, 194); border-radius: 70px; transition: 0.125s; text-decoration: none; margin: 0px 0px 20px; font-size: 14px; font-weight: bold; line-height: 1.5; color: rgb(214, 232, 194); }\ndiv.content a.link-btn > span, div.content a.link-btn:link > span, div.content a.link-btn:visited > span { color: rgb(214, 232, 194); transition: 0.125s; font-size: 14px; }\ndiv.content a.link-btn:hover { background-color: rgb(214, 232, 194); color: rgb(216, 230, 152); }\ndiv.content a.link-btn:hover > span { color: rgb(214, 232, 194); }\ndiv.content a.link-btn:active { background-color: rgb(214, 232, 194); box-shadow: rgba(0, 0, 0, 0) 0px 0px 0px; transition: all; }\n.box { height: auto; padding: 0px; background-color: rgba(255, 255, 255, 0.95); color: rgb(51, 51, 51); border: 3px solid rgb(135, 0, 17); border-radius: 10px; position: relative; margin: 2em; }\n.modern-outline-text4 { color: rgb(216, 230, 152); font-family: \"Gill Sans\", Helvetica, Arial, sans-serif; font-weight: bold; letter-spacing: 1.5px; text-shadow: rgb(220, 231, 240) 2px 2px 0px, rgba(0, 0, 0, 0.15) 4px 4px 0px; padding: 20px; text-align: center; font-size: 16px; }\n.emphasized-text { color: rgb(49, 53, 98); font-weight: bold; }\n.font-big { font-size: 16px; }\np.prize { margin: 20px 10px 10px; font-weight: bold; }\n.point { color: rgb(131, 169, 216); font-weight: bold; font-size: 14px; }\n.gradbox { width: 50%; margin: 20px auto 30px; padding: 1%; text-align: center; color: rgb(255, 255, 255); font-weight: bold; border-radius: 30px; background-image: linear-gradient(97deg, rgb(131, 169, 216) 0%, rgb(131, 169, 216) 100%); }\nh3.titlebox { width: 95%; margin: 5px auto 10px; padding: 9px 0px; border-top: 1px solid rgb(135, 0, 17); border-bottom: 1px solid rgb(135, 0, 17); color: rgb(131, 169, 216); font-size: 16px; text-align: center; }\ntable.aaa { margin: 20px 0px 0px; padding: 5px 30px; }\ntable.aaa tr { line-height: 1.5; }\ntable.aaa th { font-weight: bold; text-align: left; }\ntable.aaa td { padding: 0px 5px; }\ntable.bbb { margin: 0px auto; width: 80%; }\ntable.bbb th { background: rgb(131, 169, 216); color: white; padding: 5px 0px; }\ntable.bbb tr { font-size: 15px; text-align: center; }\ntable.bbb td { padding: 0px; }\ntable.bbb tr th:nth-of-type(1) { background: rgba(255, 255, 255, 0); color: rgb(131, 169, 216); }\ntable.ccc { margin: 0px auto; width: 90%; padding: 15px 0px; }\ntable.ccc tr { font-size: 15px; text-align: center; }\ntable.ccc td { padding: 5px 0px; }\ntable.ccc img { width: 40%; }\nimg.magazine { margin: 0px auto; width: 70%; display: block; padding: 30px 0px 0px; }\nimg.sponsor1 { margin: 0px auto; width: 70%; display: block; padding: 30px 0px 20px; }\nimg.model { width: 90%; margin: 20px auto 25px; display: block; }\nimg.prize_kv { margin: 5px auto 30px; width: 97%; display: block; }\nimg.logo { display: block; width: 18%; margin: 0px auto; padding: 30px 0px 20px; filter: invert(64%) sepia(59%) saturate(244%) hue-rotate(173deg) brightness(91%) contrast(92%); }\n.snow { color: snow; font-size: 15px; position: fixed; top: -5%; text-shadow: 5vw -100px 2px, 10vw -400px 3px, 20vw -500px 4px, 30vw -580px 1px, 39vw -250px 2px, 42vw -340px 5px, 56vw -150px 2px, 63vw -180px 0px, 78vw -220px 4px, 86vw -320px 9px, 94vw -170px 7px; animation: 3s linear 0s infinite normal none running roll; }\n.snow2nd { animation: 5s linear 0s infinite normal none running anim; }\n@keyframes roll { \n  0% { transform: rotate(0deg); }\n  90% { opacity: 1; }\n  100% { transform: rotate(20deg); top: 100%; opacity: 0; }\n}\n@keyframes anim { \n  100% { color: transparent; top: 150%; }\n}\n.centered-content { text-align: center; margin: auto; }\n.link-button { display: inline-block; width: 60%; margin: 10px; padding: 7px; border-radius: 30px; text-align: center; text-decoration: none; font-weight: bold; transition: background-color 0.3s; }\n.hp-link { background-color: rgb(241, 158, 194); color: rgb(255, 255, 255); }\n.instagram-link { background-color: rgb(241, 158, 194); color: rgb(255, 255, 255); }\n.link-button:hover { opacity: 0.9; }\ndiv.content div.apply-button-container { max-width: 480px; float: left; position: fixed; width: 100%; font-weight: bold; top: 0px; text-align: center; background-color: rgba(255, 255, 255, 0.75); backdrop-filter: blur(8px); z-index: 1; box-shadow: rgba(0, 0, 0, 0.66) 0px 2px 4px; }\ndiv.content div.apply-button-container img { max-width: 116px; margin: 0px 0px 8px; }\ndiv.content a.link-btn, div.content a.link-btn:link, div.content a.link-btn:visited { display: inline-block; padding: 10px 30px; border: 2px solid rgb(214, 232, 194); border-radius: 70px; transition: 0.125s; text-decoration: none; font-size: 14px; font-weight: bold; line-height: 1.5; background-color: rgb(135, 0, 17); color: rgb(255, 255, 255); }\ndiv.content a.link-btn:hover { background-color: rgb(247, 171, 0); color: rgb(135, 0, 17); filter: drop-shadow(rgb(25, 47, 96) 0px 0px 1px) drop-shadow(rgb(25, 47, 96) 0px 0px 2px) drop-shadow(rgb(255, 255, 255) 0px 0px 2px); }\ndiv.content a.link-btn:active { background-color: rgb(255, 255, 255); box-shadow: rgba(0, 0, 0, 0) 0px 0px 0px; transition: all; filter: drop-shadow(rgb(25, 47, 96) 0px 0px 1px) drop-shadow(rgb(25, 47, 96) 0px 0px 2px) drop-shadow(rgb(255, 255, 255) 0px 0px 2px); }\n.sample { margin: 8px auto; text-align: center; display: block; }\n.sample .text { text-align: left; display: inline-block; }\n</style>\n</font></font></div></div></div></div></div>"
}