{
  "eventKey": "24234_20260629_20260708",
  "eventId": "24234",
  "eventUrl": "https://mixch.tv/live/event/24234",
  "title": "TIF2026×andGIRL ビューティーミューズオーディション",
  "openedUrl": "https://mixch.tv/live/event/24234",
  "capturedAt": "2026-07-08T12:06:24.443Z",
  "tabs": [
    {
      "key": "ranking",
      "label": "ランキング",
      "order": 1
    },
    {
      "key": "live",
      "label": "ライブ",
      "order": 2
    },
    {
      "key": "movie",
      "label": "ムービー",
      "order": 3
    },
    {
      "key": "about",
      "label": "概要",
      "order": 4
    }
  ],
  "rankingHtml": "<div class=\"css-xlejcj ecbtkat0\"><ul class=\"list\"><li class=\"e1jtukx00 css-w1rca4 ex3haug0\"><span class=\"css-1eu4g1y ehnruze0\">1</span><a class=\"user-name css-0 e10qwino0\" href=\"/u/18185788\"><span class=\"css-14dzdfy e1bokax20\"><img src=\"https://d2jtsb989t238a.cloudfront.net/p/18185788/1782465719/small\" alt=\"灯田にじ【パラディーク】\" class=\"thumb-img\" loading=\"lazy\"></span><span class=\"css-qrjx5q ejhaeu10\">灯田にじ【パラディーク】</span></a><span class=\"css-1xxlsgn ewf2cv0\"><span class=\"num\">2,195,003</span><span class=\"unit\">pt</span></span></li><li class=\"e1jtukx00 css-w1rca4 ex3haug0\"><span class=\"css-1eu4g1y ehnruze0\">2</span><a class=\"user-name css-0 e10qwino0\" href=\"/u/18159189\"><span class=\"css-14dzdfy e1bokax20\"><img src=\"https://d2jtsb989t238a.cloudfront.net/p/18159189/1781928351/small\" alt=\"茅野風花(KRD8)\" class=\"thumb-img\" loading=\"lazy\"></span><span class=\"css-qrjx5q ejhaeu10\">茅野風花(KRD8)</span></a><span class=\"css-1xxlsgn ewf2cv0\"><span class=\"num\">1,598,774</span><span class=\"unit\">pt</span></span></li><li class=\"e1jtukx00 css-w1rca4 ex3haug0\"><span class=\"css-1eu4g1y ehnruze0\">3</span><a class=\"user-name css-0 e10qwino0\" href=\"/u/18920505\"><span class=\"css-14dzdfy e1bokax20\"><img src=\"https://d2jtsb989t238a.cloudfront.net/p/18920505/1782703078/small\" alt=\"マジスペYUYU🦋🫧\" class=\"thumb-img\" loading=\"lazy\"></span><span class=\"css-qrjx5q ejhaeu10\">マジスペYUYU🦋🫧</span></a><span class=\"css-1xxlsgn ewf2cv0\"><span class=\"num\">1,499,417</span><span class=\"unit\">pt</span></span></li><li class=\"e1jtukx00 css-w1rca4 ex3haug0\"><span class=\"css-cjsdul ehnruze0\">4</span><a class=\"user-name css-0 e10qwino0\" href=\"/u/17375163\"><span class=\"css-14dzdfy e1bokax20\"><img src=\"https://d2jtsb989t238a.cloudfront.net/p/17375163/1767444327/small\" alt=\"最終日🩷宮脇はる ファーストプレイリスト\" class=\"thumb-img\" loading=\"lazy\"></span><span class=\"css-qrjx5q ejhaeu10\">最終日🩷宮脇はる ファーストプレイリスト</span></a><span class=\"css-1xxlsgn ewf2cv0\"><span class=\"num\">1,050,804</span><span class=\"unit\">pt</span></span></li><li class=\"e1jtukx00 css-w1rca4 ex3haug0\"><span class=\"css-cjsdul ehnruze0\">5</span><a class=\"user-name css-0 e10qwino0\" href=\"/u/18919689\"><span class=\"css-14dzdfy e1bokax20\"><img src=\"https://d2jtsb989t238a.cloudfront.net/p/18919689/1782310831/small\" alt=\"兵頭美波 アップアップガールズ（２）\" class=\"thumb-img\" loading=\"lazy\"></span><span class=\"css-qrjx5q ejhaeu10\">兵頭美波 アップアップガールズ（２）</span></a><span class=\"css-1xxlsgn ewf2cv0\"><span class=\"num\">480,647</span><span class=\"unit\">pt</span></span></li><li class=\"e1jtukx00 css-w1rca4 ex3haug0\"><span class=\"css-cjsdul ehnruze0\">6</span><a class=\"user-name css-0 e10qwino0\" href=\"/u/18918993\"><span class=\"css-14dzdfy e1bokax20\"><img src=\"https://d2jtsb989t238a.cloudfront.net/p/18918993/1782234424/small\" alt=\"himawari(船橋)きらり\" class=\"thumb-img\" loading=\"lazy\"></span><span class=\"css-qrjx5q ejhaeu10\">himawari(船橋)きらり</span></a><span class=\"css-1xxlsgn ewf2cv0\"><span class=\"num\">433,342</span><span class=\"unit\">pt</span></span></li><li class=\"e1jtukx00 css-w1rca4 ex3haug0\"><span class=\"css-cjsdul ehnruze0\">7</span><a class=\"user-name css-0 e10qwino0\" href=\"/u/18891953\"><span class=\"css-14dzdfy e1bokax20\"><img src=\"https://d2jtsb989t238a.cloudfront.net/p/18891953/1779200305/small\" alt=\"羽田心咲『Lumiétoile』\" class=\"thumb-img\" loading=\"lazy\"></span><span class=\"css-qrjx5q ejhaeu10\">羽田心咲『Lumiétoile』</span></a><span class=\"css-1xxlsgn ewf2cv0\"><span class=\"num\">223,892</span><span class=\"unit\">pt</span></span></li><li class=\"e1jtukx00 css-w1rca4 ex3haug0\"><span class=\"css-cjsdul ehnruze0\">8</span><a class=\"user-name css-0 e10qwino0\" href=\"/u/15303329\"><span class=\"css-14dzdfy e1bokax20\"><img src=\"https://d2jtsb989t238a.cloudfront.net/p/15303329/1782384325/small\" alt=\"中村日菜【AQUAPLANET】\" class=\"thumb-img\" loading=\"lazy\"></span><span class=\"css-qrjx5q ejhaeu10\">中村日菜【AQUAPLANET】</span></a><span class=\"css-1xxlsgn ewf2cv0\"><span class=\"num\">215,515</span><span class=\"unit\">pt</span></span></li><li class=\"e1jtukx00 css-w1rca4 ex3haug0\"><span class=\"css-cjsdul ehnruze0\">9</span><a class=\"user-name css-0 e10qwino0\" href=\"/u/18912416\"><span class=\"css-14dzdfy e1bokax20\"><img src=\"https://d2jtsb989t238a.cloudfront.net/p/18912416/1782654570/small\" alt=\"須名優月(ルージュブック)\" class=\"thumb-img\" loading=\"lazy\"></span><span class=\"css-qrjx5q ejhaeu10\">須名優月(ルージュブック)</span></a><span class=\"css-1xxlsgn ewf2cv0\"><span class=\"num\">143,849</span><span class=\"unit\">pt</span></span></li><li class=\"e1jtukx00 css-w1rca4 ex3haug0\"><span class=\"css-cjsdul ehnruze0\">10</span><a class=\"user-name css-0 e10qwino0\" href=\"/u/18919952\"><span class=\"css-14dzdfy e1bokax20\"><img src=\"https://d2jtsb989t238a.cloudfront.net/p/18919952/1782558565/small\" alt=\"【myojou】澪奈ゆん\" class=\"thumb-img\" loading=\"lazy\"></span><span class=\"css-qrjx5q ejhaeu10\">【myojou】澪奈ゆん</span></a><span class=\"css-1xxlsgn ewf2cv0\"><span class=\"num\">59,380</span><span class=\"unit\">pt</span></span></li><li class=\"e1jtukx00 css-w1rca4 ex3haug0\"><span class=\"css-cjsdul ehnruze0\">11</span><a class=\"user-name css-0 e10qwino0\" href=\"/u/18920643\"><span class=\"css-14dzdfy e1bokax20\"><img src=\"https://d2jtsb989t238a.cloudfront.net/p/18920643/1782461318/small\" alt=\"星野さゆ【ノベルノア】\" class=\"thumb-img\" loading=\"lazy\"></span><span class=\"css-qrjx5q ejhaeu10\">星野さゆ【ノベルノア】</span></a><span class=\"css-1xxlsgn ewf2cv0\"><span class=\"num\">49,617</span><span class=\"unit\">pt</span></span></li><li class=\"e1jtukx00 css-w1rca4 ex3haug0\"><span class=\"css-cjsdul ehnruze0\">12</span><a class=\"user-name css-0 e10qwino0\" href=\"/u/18922972\"><span class=\"css-14dzdfy e1bokax20\"><img src=\"https://d2jtsb989t238a.cloudfront.net/p/18922972/1782643043/small\" alt=\"大園奈美(Sepiacode)\" class=\"thumb-img\" loading=\"lazy\"></span><span class=\"css-qrjx5q ejhaeu10\">大園奈美(Sepiacode)</span></a><span class=\"css-1xxlsgn ewf2cv0\"><span class=\"num\">45,822</span><span class=\"unit\">pt</span></span></li><li class=\"e1jtukx00 css-w1rca4 ex3haug0\"><span class=\"css-cjsdul ehnruze0\">13</span><a class=\"user-name css-0 e10qwino0\" href=\"/u/12466064\"><span class=\"css-14dzdfy e1bokax20\"><img src=\"https://d2jtsb989t238a.cloudfront.net/p/12466064/1782741564/small\" alt=\"尾上美月\" class=\"thumb-img\" loading=\"lazy\"></span><span class=\"css-qrjx5q ejhaeu10\">尾上美月</span></a><span class=\"css-1xxlsgn ewf2cv0\"><span class=\"num\">24,478</span><span class=\"unit\">pt</span></span></li></ul></div>",
  "detailHtml": "<div class=\"content\"><style>*{max-width:100% !important;}*::before{max-width:100% !important;}*::after{max-width:100% !important;};  .cf:after{content:&apos; &apos;;display:block;clear:both;height:0;}.cf{display:inline-block;}.cf{display:block;}body{background:#f8f7f4;font-family:Hiragino Kaku Gothic Pro,Meiryo,MS PGothic,sans-serif;font-size:16px;line-height:1.4;letter-spacing:0.05em;margin:0px;color:#3c3c3c;overflow-y:hidden;overflow-x:hidden;padding:0px 5px;}img{vertical-align:bottom;border:none;outline:none;}a,.text-link{text-decoration:none;outline:none;color:#ef9500;cursor:pointer;}a:hover,.text-link:hover{text-decoration:underline;}input,select,option,textarea{font-family:Hiragino Kaku Gothic Pro,Meiryo,MS PGothic,sans-serif;}.center{text-align:center;}.right{text-align:right;}.button-green{color:#fff;display:block;width:100%;box-sizing:border-box;padding:10px 0 9px 0;margin:0 auto;cursor:pointer;font-size:15px;font-weight:bold;text-align:center;border-radius:3px;-moz-border-radius:3px;-webkit-border-radius:3px;background-color:#65b721;background-image:-webkit-gradient(\n      linear,left top,left bottom,from(#6ac023),to(#65b721)\n    );background-image:-webkit-linear-gradient(top,#6ac023,#65b721);background-image:-moz-linear-gradient(top,#6ac023,#65b721);background-image:-o-linear-gradient(top,#6ac023,#65b721);background-image:linear-gradient(top,#6ac023,#65b721);border:solid 1px #61bc14;text-shadow:0 1px 1px #135e00;box-shadow:0 3px 0 #467f17;}.button-green:hover{text-decoration:none;background:#84d933;}.button-green-s{color:#fff;box-sizing:border-box;cursor:pointer;font-weight:bold;text-align:center;border-radius:3px;-moz-border-radius:3px;-webkit-border-radius:3px;background-color:#65b721;background-image:-webkit-gradient(\n      linear,left top,left bottom,from(#6ac023),to(#65b721)\n    );background-image:-webkit-linear-gradient(top,#6ac023,#65b721);background-image:-moz-linear-gradient(top,#6ac023,#65b721);background-image:-o-linear-gradient(top,#6ac023,#65b721);background-image:linear-gradient(top,#6ac023,#65b721);text-shadow:0 1px 1px #135e00;display:inline-block;font-size:16px;padding:8px 11px 7px 11px;margin:0;width:auto;border:solid 1px #61bc14;box-shadow:0 3px 0 #467f17;}.button-green-s:hover{text-decoration:none;background:#84d933;}.content{background:#fff;margin:0 0 20px 0;padding:0 0 1px 0;box-shadow:0 1px 1px #ccc;}.content p{padding:0 10px;margin:0 0 10px 0;}.content h1{display:none;}.content h2{font-size:16px;background:#f5f5f5;border-left:solid 8px #cece2b;padding:8px 0 8px 8px;}.content h3{padding:0 0 0 5px;margin:0;}.menu{background-color:#333;padding:5px 30px;color:white;width:100%;}</style><p>\n<style>h1 { display: none; }\n</style>\n</p><div class=\"main-content\" style=\"max-width:480px;margin:0 auto;\">\n<!--\n<center>\n<img src=\"https://d2uqarpmf42qy0.cloudfront.net/event/41haba/banner1 (73).png\" width=\"100%\" />\n</center>\n-->\n<!-- 💡タブセクションはじめ -->\n<div class=\"tab-content\">\n<input type=\"radio\" id=\"tab1\" name=\"tab\" checked>\n<label for=\"tab1\">&#x3000;&#x6982;&#x8981;&#x3000;</label>\n<input type=\"radio\" id=\"tab2\" name=\"tab\">\n<label for=\"tab2\">&#x3000;&#x30b9;&#x30b1;&#x30b8;&#x30e5;&#x30fc;&#x30eb; / &#x5be9;&#x67fb;&#x65b9;&#x6cd5;&#x3000;</label><p></p>\n\n<!-- タブセクションおわり💡 -->\n\n<!-- 💡1タブの中身はじめ -->\n\n<div class=\"tab-box\">\n<div id=\"tabView1\" class=\"tabView\">\n<div style=\"background-color:rgba(255,255,255,0.6);color:#735d65;font-size:15px;\">\n<h3 class=\"logo\">&#x30a4;&#x30d9;&#x30f3;&#x30c8;&#x6982;&#x8981;</h3>\n<br>\n<center>\n<img src=\"https://d2uqarpmf42qy0.cloudfront.net/event/41haba/tif2026_logo.png\" width=\"80%\">\n</center>\n\n\n<br>\n<center>\n<p style=\"margin:11px;font-size:16px;\">\n&#x4e16;&#x754c;&#x6700;&#x5927;&#x306e;&#x30a2;&#x30a4;&#x30c9;&#x30eb;&#x30d5;&#x30a7;&#x30b9;<br>\n<b><span style=\"background:linear-gradient(transparent 60%, #ff66cc 0%);\">TOKYO IDOL FESTIVAL 2026</span></b><br>\n7/31(&#x91d1;)&#x3001;8/1(&#x571f;)&#x3001;8/2(&#x65e5;)<br>\n&#x304a;&#x53f0;&#x5834;&#x30fb;&#x9752;&#x6d77;&#x5468;&#x8fba;&#x30a8;&#x30ea;&#x30a2;&#x3067;&#x958b;&#x50ac;&#xff01;\n</p></center>\n\n<center>\n<p style=\"margin:11px;font-size:16px;\">\nTIF2026&#x3068;&#x201d;&#x5927;&#x4eba;&#x53ef;&#x611b;&#x3044;&#x201d;&#x4e16;&#x754c;&#x89b3;&#x3067;&#x3001;&#x6ce8;&#x76ee;&#x3092;&#x96c6;&#x3081;&#x308b;&#x5973;&#x6027;&#x30d5;&#x30a1;&#x30c3;&#x30b7;&#x30e7;&#x30f3;&#x8a8c;&#x300c;andGIRL&#x300d;&#x306e;&#x30b3;&#x30e9;&#x30dc;&#x4f01;&#x753b;&#xff01;<br>\n<br>\n&#x8a8c;&#x9762; / web / SNS&#x7b49;&#x3067;&#x6d3b;&#x8e8d;&#x3059;&#x308b;<br>\n<b><font color=\"#D12B34\">&#x300e;&#x30d3;&#x30e5;&#x30fc;&#x30c6;&#x30a3;&#x30fc;&#x30df;&#x30e5;&#x30fc;&#x30ba;&#x300f;</font></b><br>\n&#x3092;&#x73fe;&#x5f79;&#x5973;&#x6027;&#x30a2;&#x30a4;&#x30c9;&#x30eb;&#x306e;&#x4e2d;&#x304b;&#x3089;1&#x540d;&#x6c7a;&#x5b9a;&#xff01;<br>\n&#x3055;&#x3089;&#x306b;&#x526f;&#x8cde;&#x3068;&#x3057;&#x3066;<b><font color=\"#D12B34\">&#x300e;&#x30c7;&#x30b8;&#x30bf;&#x30eb;&#x5199;&#x771f;&#x96c6;&#x5236;&#x4f5c;&#x6a29;&#x300f;</font></b><br>\n&#x3082;&#x3054;&#x7528;&#x610f;&#x3057;&#x307e;&#x3059;&#xff01;\n</p></center>\n\n\n<center>\n<a class=\"link-btn\" href=\"https://official.idolfes.com/s/tif2026/\" target=\"_blank\" referrerpolicy=\"no-referrer\">TIF2026 &#x516c;&#x5f0f;HP</a>\n</center>\n\n\n<br>\n\n<h3 class=\"logo\">&#x30d3;&#x30e5;&#x30fc;&#x30c6;&#x30a3;&#x30fc;&#x30df;&#x30e5;&#x30fc;&#x30ba;&#x3068;&#x306f;&#xff1f;</h3>\n<center>\n<p style=\"margin:11px;font-size:16px;\">\n<b><font color=\"#D12B34\"><font size=\"4\">&#x300e;&#x30d3;&#x30e5;&#x30fc;&#x30c6;&#x30a3;&#x30fc;&#x30df;&#x30e5;&#x30fc;&#x30ba;&#x300f;</font></font></b>&#x306f;<br>\n&#x4eca;&#x56de;&#x306e;&#x30b3;&#x30e9;&#x30dc;&#x4f01;&#x753b;&#x3067;&#x65b0;&#x305f;&#x306b;&#x8a95;&#x751f;&#x3059;&#x308b;<br>\n<b><font color=\"#D12B34\"><font size=\"4\">&#x300e;&#x7279;&#x5225;&#x79f0;&#x53f7;&#x300f;</font></font></b>&#x3067;&#x3059;&#xff01;\n</p></center>\n\n<div style=\"padding:3px;margin:15px;border:0.5px solid #D12B34;border-radius:10px;\">\n<center>\n<div style=\"margin:10px;color:#fff;background-image:linear-gradient(-90deg,  #D12B34 0%, #D12B34);text-align:center;width:80%;border-radius:30px;padding:3px;\"><b>&#x4e3b;&#x306a;&#x6d3b;&#x52d5;&#x5185;&#x5bb9;&#xff08;&#x4e88;&#x5b9a;&#xff09;</b></div>\n\n<p style=\"margin:2px;font-size:15px;\">\n<b><font color=\"#D12B34\">&#x6d3b;&#x52d5;&#x2460;&#x300e;andGIRL&#x300f;&#x8a8c;&#x9762;</font></b><br>\n<small>\n1&#x5e74;&#x9593;&#x3001;&#x6bce;&#x53f7;&#x300e;andGIRL&#x300f;&#x8a8c;&#x9762;&#x306b;&#x3054;&#x51fa;&#x6f14;&#x3044;&#x305f;&#x3060;&#x304d;&#x307e;&#x3059;&#xff01;<br>\n&#xff08;&#x5b63;&#x520a;&#x8a8c;&#x306e;&#x305f;&#x3081;&#x3001;&#x8a08;4&#x53f7;&#x63b2;&#x8f09;&#x3092;&#x4e88;&#x5b9a;&#xff09;\n</small><br>\n</p><center>\n<img src=\"https://d2uqarpmf42qy0.cloudfront.net/event/41haba/and&#x30a4;&#x30e1;&#x30fc;&#x30b7;&#x3099;.png\" width=\"100%\">\n</center>\n\n<br>\n<b><font color=\"#D12B34\">&#x6d3b;&#x52d5;&#x2461;&#x300e;andGIRL&#x300f;web &amp; SNS</font></b><br>\n<small>\nweb&#x8a18;&#x4e8b;&#x3084;SNS&#x3092;&#x901a;&#x3058;&#x3066;&#x3001;<br>\n&#x30d5;&#x30a1;&#x30c3;&#x30b7;&#x30e7;&#x30f3;&#x3084;&#x7f8e;&#x5bb9;&#x306f;&#x3082;&#x3061;&#x308d;&#x3093;&#x3001;&#x65c5;&#x884c;&#x3001;&#x30b0;&#x30eb;&#x30e1;&#x306a;&#x3069;&#x3001;<br>\n&#x30ea;&#x30a2;&#x30eb;&#x306a;&#x30e9;&#x30a4;&#x30d5;&#x30b9;&#x30bf;&#x30a4;&#x30eb;&#x3084;&#x30c8;&#x30ec;&#x30f3;&#x30c9;&#x3092;<br>\n&#x30ad;&#x30e3;&#x30c3;&#x30c1;&#x3057;&#x3066;&#x307f;&#x3093;&#x306a;&#x306b;&#x30b7;&#x30a7;&#x30a2;&#xff01;</small>\n<br>\n<br>\n</center>\n</div>\n\n\n\n<br>\n<br>\n\n<h3 class=\"logo\">andGIRL</h3>\n<center><img src=\"https://d2uqarpmf42qy0.cloudfront.net/event/21nakaya/IMG_1517%20(1).PNG\" width=\"70%\"></center>\n<p style=\"margin:10px;font-size:15px;\">\n&#x30a2;&#x30e9;&#x30b5;&#x30fc;&#x306b;&#x306a;&#x3063;&#x3066;&#x3082;&#x3001;&#x4ed5;&#x4e8b;&#x304c;&#x3067;&#x304d;&#x3066;&#x3082;&#x3001;&#x7d50;&#x5a5a;&#x3057;&#x3066;&#x3082;&#x3001;&#x300c;&#x30ac;&#x30fc;&#x30eb;&#x300d;&#x306a;&#x5927;&#x4eba;&#x305f;&#x3061;&#x3078;&#xff01;<br>\n&#x53ef;&#x611b;&#x3044;&#x30e2;&#x30ce;&#x304c;&#x5927;&#x597d;&#x304d;&#x3001;&#x81ea;&#x5206;&#x3078;&#x306e;&#x3054;&#x307b;&#x3046;&#x3073;&#x5927;&#x597d;&#x304d;&#x3001;&#x30aa;&#x30b7;&#x30e3;&#x30ec;&#x306b;&#x3082;&#x904a;&#x3073;&#x306b;&#x3082;&#x8caa;&#x6b32;&#x3067;&#x30a2;&#x30af;&#x30c6;&#x30a3;&#x30d6;&#x306a;&#x3001;&#x30ad;&#x30e9;&#x30ad;&#x30e9;&#x3057;&#x305f;&#x5927;&#x4eba;&#x5973;&#x5b50;&#x306e;&#x30e2;&#x30c1;&#x30d9;&#x30fc;&#x30b7;&#x30e7;&#x30f3;&#x3092;&#x4e0a;&#x3052;&#x308b;&#x5973;&#x6027;&#x30e1;&#x30c7;&#x30a3;&#x30a2;&#x3002;<br>\n</p><br>\n\n\n<center>\n<div style=\"filter:invert(33%) sepia(35%) saturate(2483%) hue-rotate(334deg) brightness(94%) contrast(90%);\">\n<a href=\"https://www.andgirl.jp/\" target=\"_blank\" referrerpolicy=\"no-referrer\"><img src=\"https://d2uqarpmf42qy0.cloudfront.net/event/35ishimatsu/&#x5bb6;&#x7d20;&#x6750;2.png\" width=\"13%\"></a>\n<a href=\"https://twitter.com/andgirl_jp\" target=\"_blank\" referrerpolicy=\"no-referrer\"><img src=\"https://d2uqarpmf42qy0.cloudfront.net/event/35ishimatsu/&#x65b0;Twitter&#x4e38;_&#x9ed2;.png\" width=\"13%\"></a>\n<a href=\"https://www.instagram.com/andgirl_jp/?hl=ja\" target=\"_blank\" referrerpolicy=\"no-referrer\"><img src=\"https://d2uqarpmf42qy0.cloudfront.net/event/35ishimatsu/Instagram&#x4e38;_&#x9ed2;.png\" width=\"13%\"></a></div></center><br><br>\n\n<br>\n\n<h3 class=\"logo\">&#x30a8;&#x30f3;&#x30c8;&#x30ea;&#x30fc;&#x30a2;&#x30a4;&#x30c9;&#x30eb;&#xff08;50&#x97f3;&#x9806;&#xff09;</h3>\n<br><table width=\"100%\">\n<tbody><tr><td width=\"50%\">\n\n<center>\n<img src=\"https://d2uqarpmf42qy0.cloudfront.net/event/41haba/&#x706f;&#x7530;&#x306b;&#x3057;&#x3099;_&#x30cf;&#x309a;&#x30e9;&#x30c6;&#x3099;&#x30a3;&#x30fc;&#x30af;.png\" alt=\"&#x753b;&#x50cf;\" onselectstart=\"return false;\" onmousedown=\"return false;\" oncontextmenu=\"return false;\" width=\"95%\">\n<br><br>\n<font size=\"3\"><b>&#x706f;&#x7530;&#x306b;&#x3058;</b></font><br>\n<small>&#x30d1;&#x30e9;&#x30c7;&#x30a3;&#x30fc;&#x30af;</small><br>\n<a href=\"https://x.com/para_niji\" target=\"_blank\" referrerpolicy=\"no-referrer\"><img src=\"https://d2uqarpmf42qy0.cloudfront.net/event/41haba/x_gray.png\" width=\"28%\"></a>\n<a href=\"https://www.tiktok.com/@para_niji\" target=\"_blank\" referrerpolicy=\"no-referrer\"><img src=\"https://d2uqarpmf42qy0.cloudfront.net/event/41haba/tiktok_gray.png\" width=\"28%\"></a>\n<br>\n\n\n</center>\n\n\n</td>\n\n<td width=\"50%\">\n\n<center>\n<img src=\"https://d2uqarpmf42qy0.cloudfront.net/event/41haba/&#x5927;&#x5712;&#x5948;&#x7f8e;_Sepiacode.png\" alt=\"&#x753b;&#x50cf;\" onselectstart=\"return false;\" onmousedown=\"return false;\" oncontextmenu=\"return false;\" width=\"95%\">\n<br><br>\n<font size=\"3\"><b>&#x5927;&#x5712;&#x5948;&#x7f8e;</b></font><br>\n<small>Sepiacode</small><br>\n<a href=\"https://x.com/nami01_22\" target=\"_blank\" referrerpolicy=\"no-referrer\"><img src=\"https://d2uqarpmf42qy0.cloudfront.net/event/41haba/x_gray.png\" width=\"28%\"></a>\n<br>\n\n</center>\n\n</td>\n</tr></tbody></table>\n\n<br><table width=\"100%\">\n<tbody><tr><td width=\"50%\">\n\n<center>\n<img src=\"https://d2uqarpmf42qy0.cloudfront.net/event/41haba/02_&#x5c3e;&#x4e0a;&#x7f8e;&#x6708;_&#x3059;&#x3078;&#x3099;&#x3066;&#x306e;&#x77ac;&#x9593;&#x306f;&#x541b;&#x305f;&#x3099;&#x3063;&#x305f;&#x3002;.png\" alt=\"&#x753b;&#x50cf;\" onselectstart=\"return false;\" onmousedown=\"return false;\" oncontextmenu=\"return false;\" width=\"95%\">\n<br><br>\n<font size=\"3\"><b>&#x5c3e;&#x4e0a;&#x7f8e;&#x6708;</b></font><br>\n<small>&#x3059;&#x3079;&#x3066;&#x306e;&#x77ac;&#x9593;&#x306f;&#x541b;&#x3060;&#x3063;&#x305f;&#x3002;</small><br>\n<a href=\"https://x.com/onoue_mizuki\" target=\"_blank\" referrerpolicy=\"no-referrer\"><img src=\"https://d2uqarpmf42qy0.cloudfront.net/event/41haba/x_gray.png\" width=\"28%\"></a>\n<a href=\"https://www.instagram.com/onoue_mizuki/profilecard/?igsh=MTNqbTh1aXV3ZWJ1Mg%3D%3D\" target=\"_blank\" referrerpolicy=\"no-referrer\"><img src=\"https://d2uqarpmf42qy0.cloudfront.net/event/41haba/instagram_gray.png\" width=\"28%\"></a>\n<a href=\"https://www.tiktok.com/@omizuki_fc\" target=\"_blank\" referrerpolicy=\"no-referrer\"><img src=\"https://d2uqarpmf42qy0.cloudfront.net/event/41haba/tiktok_gray.png\" width=\"28%\"></a>\n<br>\n\n</center>\n\n\n\n</td>\n\n<td width=\"50%\">\n\n<center>\n<img src=\"https://d2uqarpmf42qy0.cloudfront.net/event/41haba/03_&#x8305;&#x91ce;&#x98a8;&#x82b1;_KRD8 .png\" alt=\"&#x753b;&#x50cf;\" onselectstart=\"return false;\" onmousedown=\"return false;\" oncontextmenu=\"return false;\" width=\"95%\">\n<br><br>\n<font size=\"3\"><b>&#x8305;&#x91ce;&#x98a8;&#x82b1;</b></font><br>\n<small>KRD8 </small><br>\n<a href=\"https://x.com/krd8_fuka\" target=\"_blank\" referrerpolicy=\"no-referrer\"><img src=\"https://d2uqarpmf42qy0.cloudfront.net/event/41haba/x_gray.png\" width=\"28%\"></a>\n<a href=\"https://www.tiktok.com/@fuka_kyn?_t=8YStBMzq7oQ&amp;_r=1\" target=\"_blank\" referrerpolicy=\"no-referrer\"><img src=\"https://d2uqarpmf42qy0.cloudfront.net/event/41haba/tiktok_gray.png\" width=\"28%\"></a>\n<br>\n\n</center>\n\n\n</td>\n</tr></tbody></table>\n\n<br><table width=\"100%\">\n<tbody><tr><td width=\"50%\">\n\n<center>\n<img src=\"https://d2uqarpmf42qy0.cloudfront.net/event/41haba/04_&#x304d;&#x3089;&#x308a;_himawari(&#x8239;&#x6a4b;).png\" alt=\"&#x753b;&#x50cf;\" onselectstart=\"return false;\" onmousedown=\"return false;\" oncontextmenu=\"return false;\" width=\"95%\">\n<br><br>\n<font size=\"3\"><b>&#x304d;&#x3089;&#x308a;</b></font><br>\n<small>himawari(&#x8239;&#x6a4b;)</small><br>\n<a href=\"https://x.com/kii_i0ii\" target=\"_blank\" referrerpolicy=\"no-referrer\"><img src=\"https://d2uqarpmf42qy0.cloudfront.net/event/41haba/x_gray.png\" width=\"28%\"></a>\n<a href=\"https://www.tiktok.com/@kii_i0ii?_t=ZS-8xVBF80ATZZ&amp;_r=1\" target=\"_blank\" referrerpolicy=\"no-referrer\"><img src=\"https://d2uqarpmf42qy0.cloudfront.net/event/41haba/tiktok_gray.png\" width=\"28%\"></a>\n<br>\n\n</center>\n\n\n</td>\n\n<td width=\"50%\">\n\n<center>\n<img src=\"https://d2uqarpmf42qy0.cloudfront.net/event/41haba/05_&#x9808;&#x540d;&#x512a;&#x6708;_&#x30eb;&#x30fc;&#x30b7;&#x3099;&#x30e5;&#x30d5;&#x3099;&#x30c3;&#x30af;.png\" alt=\"&#x753b;&#x50cf;\" onselectstart=\"return false;\" onmousedown=\"return false;\" oncontextmenu=\"return false;\" width=\"95%\">\n<br><br>\n<font size=\"3\"><b>&#x9808;&#x540d;&#x512a;&#x6708;</b></font><br>\n<small>&#x30eb;&#x30fc;&#x30b8;&#x30e5;&#x30d6;&#x30c3;&#x30af;</small><br>\n<a href=\"https://x.com/rougebook_suna\" target=\"_blank\" referrerpolicy=\"no-referrer\"><img src=\"https://d2uqarpmf42qy0.cloudfront.net/event/41haba/x_gray.png\" width=\"28%\"></a>\n<br>\n\n</center>\n</td>\n</tr></tbody></table>\n\n<br><table width=\"100%\">\n<tbody><tr><td width=\"50%\">\n\n<center>\n<img src=\"https://d2uqarpmf42qy0.cloudfront.net/event/41haba/06_&#x4e2d;&#x6751;&#x65e5;&#x83dc;_AQUAPLANET.png\" alt=\"&#x753b;&#x50cf;\" onselectstart=\"return false;\" onmousedown=\"return false;\" oncontextmenu=\"return false;\" width=\"95%\">\n<br><br>\n<font size=\"3\"><b>&#x4e2d;&#x6751;&#x65e5;&#x83dc;</b></font><br>\n<small>AQUAPLANET</small><br>\n<a href=\"https://x.com/Hina1_AQUA\" target=\"_blank\" referrerpolicy=\"no-referrer\"><img src=\"https://d2uqarpmf42qy0.cloudfront.net/event/41haba/x_gray.png\" width=\"28%\"></a>\n<a href=\"https://www.instagram.com/__nakamurahina\" target=\"_blank\" referrerpolicy=\"no-referrer\"><img src=\"https://d2uqarpmf42qy0.cloudfront.net/event/41haba/instagram_gray.png\" width=\"28%\"></a>\n<a href=\"https://www.tiktok.com/@ohina17\" target=\"_blank\" referrerpolicy=\"no-referrer\"><img src=\"https://d2uqarpmf42qy0.cloudfront.net/event/41haba/tiktok_gray.png\" width=\"28%\"></a>\n<br>\n\n</center>\n\n</td>\n\n<td width=\"50%\">\n\n<center>\n<img src=\"https://d2uqarpmf42qy0.cloudfront.net/event/41haba/07_&#x7fbd;&#x7530;&#x5fc3;&#x54b2;_Lumie&#x301;toile.png\" alt=\"&#x753b;&#x50cf;\" onselectstart=\"return false;\" onmousedown=\"return false;\" oncontextmenu=\"return false;\" width=\"95%\">\n<br><br>\n<font size=\"3\"><b>&#x7fbd;&#x7530;&#x5fc3;&#x54b2;</b></font><br>\n<small>Lumi&#xe9;toile</small><br>\n<a href=\"https://x.com/Lumieto_misaki\" target=\"_blank\" referrerpolicy=\"no-referrer\"><img src=\"https://d2uqarpmf42qy0.cloudfront.net/event/41haba/x_gray.png\" width=\"28%\"></a>\n<a href=\"https://www.instagram.com/Lumieto_misaki\" target=\"_blank\" referrerpolicy=\"no-referrer\"><img src=\"https://d2uqarpmf42qy0.cloudfront.net/event/41haba/instagram_gray.png\" width=\"28%\"></a>\n<a href=\"https://www.tiktok.com/@Lumieto_misaki\" target=\"_blank\" referrerpolicy=\"no-referrer\"><img src=\"https://d2uqarpmf42qy0.cloudfront.net/event/41haba/tiktok_gray.png\" width=\"28%\"></a>\n<br>\n\n</center>\n\n\n</td>\n</tr></tbody></table>\n\n<br><table width=\"100%\">\n<tbody><tr><td width=\"50%\">\n\n<center>\n<img src=\"https://d2uqarpmf42qy0.cloudfront.net/event/41haba/08_&#x5175;&#x982d;&#x7f8e;&#x6ce2;_&#x30a2;&#x30c3;&#x30d5;&#x309a;&#x30a2;&#x30c3;&#x30d5;&#x309a;&#x30ab;&#x3099;&#x30fc;&#x30eb;&#x30b9;&#x3099;&#xff08;2&#xff09;.png\" alt=\"&#x753b;&#x50cf;\" onselectstart=\"return false;\" onmousedown=\"return false;\" oncontextmenu=\"return false;\" width=\"95%\">\n<br><br>\n<font size=\"3\"><b>&#x5175;&#x982d;&#x7f8e;&#x6ce2;</b></font><br>\n<small>&#x30a2;&#x30c3;&#x30d7;&#x30a2;&#x30c3;&#x30d7;&#x30ac;&#x30fc;&#x30eb;&#x30ba;&#xff08;2&#xff09;</small><br>\n<a href=\"https://x.com/uug2_minami\" target=\"_blank\" referrerpolicy=\"no-referrer\"><img src=\"https://d2uqarpmf42qy0.cloudfront.net/event/41haba/x_gray.png\" width=\"28%\"></a>\n<a href=\"https://www.instagram.com/minami_hyodo_uug2ki/\" target=\"_blank\" referrerpolicy=\"no-referrer\"><img src=\"https://d2uqarpmf42qy0.cloudfront.net/event/41haba/instagram_gray.png\" width=\"28%\"></a>\n<a href=\"https://www.tiktok.com/@hyodo_minami\" target=\"_blank\" referrerpolicy=\"no-referrer\"><img src=\"https://d2uqarpmf42qy0.cloudfront.net/event/41haba/tiktok_gray.png\" width=\"28%\"></a>\n<br>\n\n</center>\n\n</td>\n\n<td width=\"50%\">\n\n<center>\n<img src=\"https://d2uqarpmf42qy0.cloudfront.net/event/41haba/09_&#x661f;&#x91ce;&#x3055;&#x3086;_&#x30ce;&#x30d8;&#x3099;&#x30eb;&#x30ce;&#x30a2;.png\" alt=\"&#x753b;&#x50cf;\" onselectstart=\"return false;\" onmousedown=\"return false;\" oncontextmenu=\"return false;\" width=\"95%\">\n<br><br>\n<font size=\"3\"><b>&#x661f;&#x91ce;&#x3055;&#x3086;</b></font><br>\n<small>&#x30ce;&#x30d9;&#x30eb;&#x30ce;&#x30a2;</small><br>\n<a href=\"https://x.com/novelnoah_sayu\" target=\"_blank\" referrerpolicy=\"no-referrer\"><img src=\"https://d2uqarpmf42qy0.cloudfront.net/event/41haba/x_gray.png\" width=\"28%\"></a>\n<br>\n\n</center>\n\n</td>\n</tr></tbody></table>\n\n<br><table width=\"100%\">\n<tbody><tr><td width=\"50%\">\n\n<center>\n<img src=\"https://d2uqarpmf42qy0.cloudfront.net/event/41haba/10_&#x6faa;&#x5948;&#x3086;&#x3093;_myojou.png\" alt=\"&#x753b;&#x50cf;\" onselectstart=\"return false;\" onmousedown=\"return false;\" oncontextmenu=\"return false;\" width=\"95%\">\n<br><br>\n<font size=\"3\"><b>&#x6faa;&#x5948;&#x3086;&#x3093;</b></font><br>\n<small>myojou</small><br>\n<a href=\"https://x.com/myojou_yun\" target=\"_blank\" referrerpolicy=\"no-referrer\"><img src=\"https://d2uqarpmf42qy0.cloudfront.net/event/41haba/x_gray.png\" width=\"28%\"></a>\n<br>\n\n</center>\n\n\n</td>\n\n<td width=\"50%\">\n\n<center>\n<img src=\"https://d2uqarpmf42qy0.cloudfront.net/event/41haba/11_&#x5bae;&#x8107;&#x306f;&#x308b;_&#x30d5;&#x30a1;&#x30fc;&#x30b9;&#x30c8;&#x30d5;&#x309a;&#x30ec;&#x30a4;&#x30ea;&#x30b9;&#x30c8;.png\" alt=\"&#x753b;&#x50cf;\" onselectstart=\"return false;\" onmousedown=\"return false;\" oncontextmenu=\"return false;\" width=\"95%\">\n<br><br>\n<font size=\"3\"><b>&#x5bae;&#x8107;&#x306f;&#x308b;</b></font><br>\n<small>&#x30d5;&#x30a1;&#x30fc;&#x30b9;&#x30c8;&#x30d7;&#x30ec;&#x30a4;&#x30ea;&#x30b9;&#x30c8;</small><br>\n<a href=\"https://x.com/FP_haru_\" target=\"_blank\" referrerpolicy=\"no-referrer\"><img src=\"https://d2uqarpmf42qy0.cloudfront.net/event/41haba/x_gray.png\" width=\"28%\"></a>\n<a href=\"https://www.instagram.com/_harumiyawaki?igsh=MTBxcXFjb2t5N3QxZw%3D%3D&amp;utm_source=qr\" target=\"_blank\" referrerpolicy=\"no-referrer\"><img src=\"https://d2uqarpmf42qy0.cloudfront.net/event/41haba/instagram_gray.png\" width=\"28%\"></a>\n<br>\n\n</center>\n\n</td>\n</tr></tbody></table>\n\n<br><table width=\"100%\">\n<tbody><tr><td width=\"50%\">\n\n<center>\n<img src=\"https://d2uqarpmf42qy0.cloudfront.net/event/41haba/12_YUYU_MAGICAL SPEC.png\" alt=\"&#x753b;&#x50cf;\" onselectstart=\"return false;\" onmousedown=\"return false;\" oncontextmenu=\"return false;\" width=\"95%\">\n<br><br>\n<font size=\"3\"><b>YUYU</b></font><br>\n<small>MAGICAL SPEC</small><br>\n<a href=\"https://x.com/yuyu_magispe\" target=\"_blank\" referrerpolicy=\"no-referrer\"><img src=\"https://d2uqarpmf42qy0.cloudfront.net/event/41haba/x_gray.png\" width=\"28%\"></a>\n<a href=\"https://www.instagram.com/yuyu_magispe/\" target=\"_blank\" referrerpolicy=\"no-referrer\"><img src=\"https://d2uqarpmf42qy0.cloudfront.net/event/41haba/instagram_gray.png\" width=\"28%\"></a>\n<a href=\"https://www.tiktok.com/@yuyuchi1123\" target=\"_blank\" referrerpolicy=\"no-referrer\"><img src=\"https://d2uqarpmf42qy0.cloudfront.net/event/41haba/tiktok_gray.png\" width=\"28%\"></a>\n<br>\n\n\n</center>\n\n\n\n</td>\n\n<td width=\"50%\">\n\n</td>\n</tr></tbody></table>\n\n<br>\n<br>\n\n\n\n<a href=\"https://mixch.tv/p/qjtg97sp\" target=\"_blank\" referrerpolicy=\"no-referrer\"><center><img src=\"https://d2uqarpmf42qy0.cloudfront.net/event/koizumi/1811_kokoroe.png\" width=\"70%\"></center></a>\n<br>\n\n<div style=\"margin:10px;border:#D12B34 solid 1px;display:block;padding:.2em .3em;\">\n<h3 style=\"border-left:#D12B34 solid 6px;padding:.3em.3em.3em.8em;\">&#x5be9;&#x67fb;&#x306b;&#x3064;&#x3044;&#x3066;</h3>\n</div>\n<p style=\"margin:10px;font-size:15px;\">\n&#x25cf;&#x30e9;&#x30a4;&#x30d6;&#x914d;&#x4fe1;&#x30fb;&#x52d5;&#x753b;&#x6295;&#x7a3f;&#x3092;&#x3059;&#x308b;&#x969b;&#x306f;&#x5fc5;&#x305a;<b><font color=\"#D12B34\">[TIF2026&#xd7;andGIRL &#x30d3;&#x30e5;&#x30fc;&#x30c6;&#x30a3;&#x30fc;&#x30df;&#x30e5;&#x30fc;&#x30ba;&#x30aa;&#x30fc;&#x30c7;&#x30a3;&#x30b7;&#x30e7;&#x30f3;]&#x306e;&#x30a4;&#x30d9;&#x30f3;&#x30c8;&#x9078;&#x629e;</font></b>&#x3092;&#x304a;&#x9858;&#x3044;&#x3057;&#x307e;&#x3059;&#x3002;&#x6b63;&#x3057;&#x304f;&#x9078;&#x629e;&#x3092;&#x3057;&#x3066;&#x3044;&#x306a;&#x3044;&#x5834;&#x5408;&#x306f;&#x7372;&#x5f97;&#x3057;&#x305f;&#x30df;&#x30af;&#x30c1;&#x30e3;&#x30dd;&#x30a4;&#x30f3;&#x30c8;&#x304c;&#x30e9;&#x30f3;&#x30ad;&#x30f3;&#x30b0;&#x306b;&#x53cd;&#x6620;&#x3055;&#x308c;&#x307e;&#x305b;&#x3093;&#x306e;&#x3067;&#x3054;&#x6ce8;&#x610f;&#x304f;&#x3060;&#x3055;&#x3044;&#x3002;&#x307e;&#x305f;&#x3001;&#x8aa4;&#x3063;&#x3066;&#x30a4;&#x30d9;&#x30f3;&#x30c8;&#x9078;&#x629e;&#x3057;&#x305f;&#x969b;&#x306b;&#x30dd;&#x30a4;&#x30f3;&#x30c8;&#x3092;&#x5bfe;&#x8c61;&#x30a4;&#x30d9;&#x30f3;&#x30c8;&#x306b;&#x53cd;&#x6620;&#x3059;&#x308b;&#x3053;&#x3068;&#x306f;&#x3067;&#x304d;&#x304b;&#x306d;&#x307e;&#x3059;&#x306e;&#x3067;&#x4e88;&#x3081;&#x3054;&#x4e86;&#x627f;&#x304f;&#x3060;&#x3055;&#x3044;&#x3002;<br>\n<br>\n&#x25cf;&#x5f53;&#x8a72;&#x30da;&#x30fc;&#x30b8;&#x306e;&#x5be9;&#x67fb;&#x9805;&#x76ee;&#x306b;&#x6cbf;&#x3063;&#x3066;&#x53d7;&#x8cde;&#x8005;&#x304c;&#x6c7a;&#x5b9a;&#x3044;&#x305f;&#x3057;&#x307e;&#x3059;&#x3002;&#x306a;&#x304a;&#x3001;&#x5be9;&#x67fb;&#x306e;&#x904e;&#x7a0b;&#x3084;&#x53d7;&#x8cde;&#x8005;&#x306e;&#x6c7a;&#x5b9a;&#x306b;&#x81f3;&#x3063;&#x305f;&#x7406;&#x7531;&#x7b49;&#x306b;&#x3064;&#x304d;&#x307e;&#x3057;&#x3066;&#x306f;&#x304a;&#x7b54;&#x3048;&#x51fa;&#x6765;&#x307e;&#x305b;&#x3093;&#x306e;&#x3067;&#x3042;&#x3089;&#x304b;&#x3058;&#x3081;&#x3054;&#x4e86;&#x627f;&#x304f;&#x3060;&#x3055;&#x3044;&#x3002;<br>\n<br>\n&#x25cf;&#x7372;&#x5f97;&#x3057;&#x305f;&#x30dd;&#x30a4;&#x30f3;&#x30c8;&#x304c;&#x540c;&#x4e00;&#x306e;&#x5834;&#x5408;&#x306f;&#x3001;&#x4e0b;&#x8a18;&#x306e;&#x6761;&#x4ef6;&#x306b;&#x5f93;&#x3063;&#x3066;&#x9806;&#x4f4d;&#x3092;&#x6c7a;&#x5b9a;&#x3057;&#x307e;&#x3059;&#x3002;((1)&#x304b;&#x3089;&#x6761;&#x4ef6;&#x3092;&#x9069;&#x7528;&#x3057;&#x3001;&#x9806;&#x4f4d;&#x304c;&#x6c7a;&#x5b9a;&#x3057;&#x306a;&#x3044;&#x5834;&#x5408;&#x306f;&#x305d;&#x306e;&#x6b21;&#x306e;&#x6761;&#x4ef6;&#x3092;&#x9069;&#x7528;&#x3057;&#x3066;&#x6c7a;&#x5b9a;&#x3057;&#x3001;&#x4ee5;&#x4e0b;&#x540c;&#x69d8;&#x306e;&#x51e6;&#x7406;&#x3092;&#x3057;&#x307e;&#x3059;&#x3002;)<br>\n<br>\n<font size=\"3\">\n&#x3000;(1) &#x5bfe;&#x8c61;&#x3068;&#x306a;&#x308b;&#x30a4;&#x30d9;&#x30f3;&#x30c8;&#x3092;&#x9078;&#x629e;&#x3057;&#x3066;&#x30e9;&#x30a4;&#x30d6;&#x914d;&#x4fe1;&#x3092;&#x3057;&#x305f;&#x300c;&#x914d;&#x4fe1;&#x6642;&#x9593;&#x300d;&#x306e;&#x5408;&#x8a08;&#x304c;&#x591a;&#x3044;&#x30e6;&#x30fc;&#x30b6;&#x30fc;&#x3092;&#x4e0a;&#x4f4d;&#x3068;&#x3057;&#x307e;&#x3059;&#x3002;<br>\n&#x3000;(2) &#x5bfe;&#x8c61;&#x3068;&#x306a;&#x308b;&#x30a4;&#x30d9;&#x30f3;&#x30c8;&#x3092;&#x9078;&#x629e;&#x3057;&#x3066;&#x30e9;&#x30a4;&#x30d6;&#x914d;&#x4fe1;&#x3092;&#x3057;&#x305f;&#x300c;&#x914d;&#x4fe1;&#x56de;&#x6570;&#x300d;&#x306e;&#x5408;&#x8a08;&#x304c;&#x591a;&#x3044;&#x30e6;&#x30fc;&#x30b6;&#x30fc;&#x3092;&#x4e0a;&#x4f4d;&#x3068;&#x3057;&#x307e;&#x3059;&#x3002;<br>\n&#x3000;(3) &#x5bfe;&#x8c61;&#x3068;&#x306a;&#x308b;&#x30a4;&#x30d9;&#x30f3;&#x30c8;&#x3092;&#x9078;&#x629e;&#x3057;&#x3066;&#x884c;&#x3063;&#x305f;&#x30e9;&#x30a4;&#x30d6;&#x914d;&#x4fe1;&#x30fb;&#x6295;&#x7a3f;&#x52d5;&#x753b;&#x306b;&#x5bfe;&#x3057;&#x3066;&#x53d7;&#x3051;&#x53d6;&#x3063;&#x305f;&#x300c;&#x30b3;&#x30e1;&#x30f3;&#x30c8;&#x6570;&#x300d;&#x306e;&#x5408;&#x8a08;&#x304c;&#x591a;&#x3044;&#x30e6;&#x30fc;&#x30b6;&#x30fc;&#x3092;&#x4e0a;&#x4f4d;&#x3068;&#x3057;&#x307e;&#x3059;&#x3002;<br>\n&#x3000;(4) &#x5bfe;&#x8c61;&#x3068;&#x306a;&#x308b;&#x30a4;&#x30d9;&#x30f3;&#x30c8;&#x3078;&#x306e;&#x5fdc;&#x52df;&#x7533;&#x3057;&#x8fbc;&#x307f;&#x304c;&#x65e9;&#x304b;&#x3063;&#x305f;&#x30e6;&#x30fc;&#x30b6;&#x30fc;&#x3092;&#x4e0a;&#x4f4d;&#x3068;&#x3057;&#x307e;&#x3059;&#x3002;<br>\n&#x3000;(5) &#x3082;&#x3057;(1)&#xff5e;(5)&#x5168;&#x3066;&#x304c;&#x540c;&#x3058;&#x5834;&#x5408;&#x306f;&#x30df;&#x30af;&#x30c1;&#x30e3;&#x306e;&#x300c;&#x30e6;&#x30fc;&#x30b6;&#x30fc;ID&#x306e;&#x6570;&#x5b57;&#x304c;&#x5c0f;&#x3055;&#x3044;&#x300d;&#x30e6;&#x30fc;&#x30b6;&#x30fc;&#x3092;&#x4e0a;&#x4f4d;&#x3068;&#x3057;&#x307e;&#x3059;&#x3002;<br>\n</font>\n<br><br>\n&#x203b;&#x4e0b;&#x8a18;&#x306e;&#x6ce8;&#x610f;&#x4e8b;&#x9805;&#x3082;&#x5fc5;&#x305a;&#x304a;&#x8aad;&#x307f;&#x304f;&#x3060;&#x3055;&#x3044;&#x3002;</p>\n\n<div style=\"margin:10px;border:#D12B34 solid 1px;display:block;padding:.2em .3em;\">\n<h3 style=\"border-left:#D12B34 solid 6px;padding:.3em.3em.3em.8em;\">&#x30a2;&#x30a4;&#x30c6;&#x30e0;&#x9001;&#x4fe1;&#x306b;&#x95a2;&#x3059;&#x308b;&#x6ce8;&#x610f;&#x70b9;</h3>\n</div>\n<p style=\"margin:10px;font-size:15px;\">\n&#x25cf;&#x30e9;&#x30a4;&#x30d6;&#x914d;&#x4fe1;&#x3067;&#x3001;&#x30a4;&#x30d9;&#x30f3;&#x30c8;&#x7d42;&#x4e86;&#x9593;&#x969b;&#x306a;&#x3069;&#x540c;&#x6642;&#x9593;&#x5e2f;&#x306b;&#x5927;&#x91cf;&#x306e;&#x30a2;&#x30a4;&#x30c6;&#x30e0;&#x3092;&#x6295;&#x3052;&#x308b;&#x3068;&#x3001;&#x591a;&#x6570;&#x306e;&#x30a2;&#x30a4;&#x30c6;&#x30e0;&#x30ea;&#x30af;&#x30a8;&#x30b9;&#x30c8;&#x306b;&#x3088;&#x308a;&#x30b3;&#x30a4;&#x30f3;&#x6d88;&#x8cbb;&#x306b;&#x9045;&#x5ef6;&#x304c;&#x751f;&#x3058;&#x308b;&#x53ef;&#x80fd;&#x6027;&#x304c;&#x3054;&#x3056;&#x3044;&#x307e;&#x3059;&#x3002;&#x30e0;&#x30fc;&#x30d3;&#x30fc;&#x3067;&#x306f;&#x9045;&#x5ef6;&#x304c;&#x751f;&#x3058;&#x308b;&#x3053;&#x3068;&#x306f;&#x306a;&#x3044;&#x306e;&#x3067;&#x3001;&#x30e0;&#x30fc;&#x30d3;&#x30fc;&#x30a4;&#x30d9;&#x30f3;&#x30c8;&#x306e;&#x5834;&#x5408;&#x306f;&#x6295;&#x7a3f;&#x52d5;&#x753b;&#x3078;&#x306e;&#x7a4d;&#x6975;&#x7684;&#x306a;&#x9001;&#x4fe1;&#x3092;&#x3054;&#x691c;&#x8a0e;&#x304f;&#x3060;&#x3055;&#x3044;&#x3002;<br>\n&#x25cf;&#x30e9;&#x30a4;&#x30d6;&#x914d;&#x4fe1;&#x306e;&#x5834;&#x5408;&#x3001;&#x30a4;&#x30d9;&#x30f3;&#x30c8;&#x671f;&#x9593;&#x4e2d;&#x306b;&#x30e9;&#x30a4;&#x30d0;&#x30fc;&#x306e;&#x7aef;&#x672b;&#x5074;&#x3067;&#x30a2;&#x30a4;&#x30c6;&#x30e0;&#x306e;&#x30a2;&#x30cb;&#x30e1;&#x30fc;&#x30b7;&#x30e7;&#x30f3;&#x518d;&#x751f;&#x304c;&#x59cb;&#x307e;&#x3063;&#x305f;&#x30a2;&#x30a4;&#x30c6;&#x30e0;&#x306f;&#x30a4;&#x30d9;&#x30f3;&#x30c8;&#x306e;&#x30dd;&#x30a4;&#x30f3;&#x30c8;&#x306b;&#x52a0;&#x7b97;&#x3055;&#x308c;&#x307e;&#x3059;&#x3002;&#x30a4;&#x30d9;&#x30f3;&#x30c8;&#x671f;&#x9593;&#x4e2d;&#x306b;&#x518d;&#x751f;&#x5931;&#x6557;&#x3057;&#x305f;&#x30a2;&#x30a4;&#x30c6;&#x30e0;&#x3084;&#x30a4;&#x30d9;&#x30f3;&#x30c8;&#x671f;&#x9593;&#x3092;&#x3059;&#x304e;&#x3066;&#x304b;&#x3089;&#x518d;&#x751f;&#x3055;&#x308c;&#x305f;&#x30a2;&#x30a4;&#x30c6;&#x30e0;&#x306f;&#x3001;&#x30a4;&#x30d9;&#x30f3;&#x30c8;&#x306e;&#x30dd;&#x30a4;&#x30f3;&#x30c8;&#x306b;&#x52a0;&#x7b97;&#x3055;&#x308c;&#x307e;&#x305b;&#x3093;&#x3002;<br>\n&#x25cf;&#x306a;&#x304a;&#x3001;&#x4e0a;&#x8a18;&#x306e;&#x4e8b;&#x8c61;&#x304c;&#x767a;&#x751f;&#x3057;&#x305f;&#x5834;&#x5408;&#x306b;&#x304a;&#x3044;&#x3066;&#x3082;&#x3001;&#x30a4;&#x30d9;&#x30f3;&#x30c8;&#x3078;&#x306e;&#x30dd;&#x30a4;&#x30f3;&#x30c8;&#x53cd;&#x6620;&#x3084;&#x30b3;&#x30a4;&#x30f3;&#x306e;&#x8fd4;&#x5374;&#x306a;&#x3069;&#x306e;&#x3054;&#x5bfe;&#x5fdc;&#x306f;&#x51fa;&#x6765;&#x304b;&#x306d;&#x307e;&#x3059;&#x306e;&#x3067;&#x3054;&#x4e86;&#x627f;&#x304f;&#x3060;&#x3055;&#x3044;&#x307e;&#x305b;&#x3002;<br>\n&#x305d;&#x306e;&#x305f;&#x3081;&#x3001;&#x30e9;&#x30a4;&#x30d6;&#x914d;&#x4fe1;&#x3067;&#x306f;&#x3067;&#x304d;&#x308b;&#x3060;&#x3051;&#x4e00;&#x6c17;&#x306b;&#x5927;&#x91cf;&#x306b;&#x9001;&#x308b;&#x306e;&#x3067;&#x306f;&#x306a;&#x304f;&#x3001;&#x5b9a;&#x671f;&#x7684;&#x306b;&#x30a2;&#x30a4;&#x30c6;&#x30e0;&#x3092;&#x9001;&#x308b;&#x304b;&#x30e0;&#x30fc;&#x30d3;&#x30fc;&#x3078;&#x306e;&#x30a2;&#x30a4;&#x30c6;&#x30e0;&#x9001;&#x4fe1;&#x3092;&#x63a8;&#x5968;&#x3044;&#x305f;&#x3057;&#x307e;&#x3059;&#x3002;<br>\n</p>\n\n<div style=\"margin:10px;border:#D12B34 solid 1px;display:block;padding:.2em .3em;\">\n<h3 style=\"border-left:#D12B34 solid 6px;padding:.3em.3em.3em.8em;\">&#x5fdc;&#x52df;&#x898f;&#x7d04;</h3>\n</div>\n<p style=\"margin:10px;font-size:15px;\">\n&#x672c;&#x30ad;&#x30e3;&#x30f3;&#x30da;&#x30fc;&#x30f3;&#x306b;&#x5fdc;&#x52df;&#x3044;&#x305f;&#x3060;&#x3051;&#x308b;&#x65b9;&#xff08;&#x4ee5;&#x4e0b;&#x3001;&#x300c;&#x5fdc;&#x52df;&#x8005;&#x300d;&#x3068;&#x3044;&#x3044;&#x307e;&#x3059;&#x3002;&#xff09;&#x306f;&#x3001;&#x4ee5;&#x4e0b;&#x3092;&#x3088;&#x304f;&#x304a;&#x8aad;&#x307f;&#x3044;&#x305f;&#x3060;&#x304d;&#x3001;&#x540c;&#x610f;&#x306e;&#x4e0a;&#x3054;&#x5fdc;&#x52df;&#x304f;&#x3060;&#x3055;&#x3044;&#x3002;<br><br>\n&#x30df;&#x30af;&#x30c1;&#x30e3;&#x306b;&#x3066;&#x3001;&#x300c;&#x30a4;&#x30d9;&#x30f3;&#x30c8;&#x306b;&#x53c2;&#x52a0;&#x3059;&#x308b;&#x300d;&#x3092;&#x30bf;&#x30c3;&#x30d7;&#x3057;&#x305f;&#x6642;&#x70b9;&#x3067;&#x672c;&#x898f;&#x7d04;&#x306b;&#x540c;&#x610f;&#x3057;&#x305f;&#x3082;&#x306e;&#x3068;&#x307f;&#x306a;&#x3057;&#x307e;&#x3059;&#x3002;&#x4e07;&#x304c;&#x4e00;&#x3054;&#x540c;&#x610f;&#x3044;&#x305f;&#x3060;&#x3051;&#x306a;&#x3044;&#x5834;&#x5408;&#x306f;&#x5fdc;&#x52df;&#x3092;&#x4e2d;&#x6b62;&#x3057;&#x3066;&#x304f;&#x3060;&#x3055;&#x3044;&#x3002;<br>\n&#x672c;&#x898f;&#x7d04;&#x306e;&#x5185;&#x5bb9;&#x306f;&#x3001;&#x4e8b;&#x524d;&#x306e;&#x544a;&#x77e5;&#x306a;&#x304f;&#x5909;&#x66f4;&#x3055;&#x308c;&#x308b;&#x5834;&#x5408;&#x304c;&#x3042;&#x308a;&#x307e;&#x3059;&#x306e;&#x3067;&#x3001;&#x4e88;&#x3081;&#x3054;&#x4e86;&#x627f;&#x304f;&#x3060;&#x3055;&#x3044;&#x3002;<br>\n</p>\n<div style=\"font-size:16px;padding:.75em 0;border-top:1px solid #D12B34;border-bottom:1px solid #D12B34;\">\n&#x3000;&#x25aa;&#xfe0f;&#x52d5;&#x753b;&#x6295;&#x7a3f;&#x30fb;&#x30e9;&#x30a4;&#x30d6;&#x914d;&#x4fe1;&#x3067;&#x306e;&#x6ce8;&#x610f;&#x4e8b;&#x9805;\n</div>\n<p style=\"margin:10px;font-size:15px;\">\n&#x25cf;&#x64ae;&#x5f71;&#x30fb;&#x30e9;&#x30a4;&#x30d6;&#x914d;&#x4fe1;&#x304c;&#x7981;&#x6b62;&#x3055;&#x308c;&#x3066;&#x3044;&#x308b;&#x5834;&#x6240;&#x307e;&#x305f;&#x306f;&#x5371;&#x967a;&#x306a;&#x5834;&#x6240;&#x3067;&#x306e;&#x64ae;&#x5f71;&#x3084;&#x30e9;&#x30a4;&#x30d6;&#x914d;&#x4fe1;&#x306f;&#x304a;&#x63a7;&#x3048;&#x4e0b;&#x3055;&#x3044;&#x3002;<br>\n&#x25cf;&#x697d;&#x66f2;&#x3092;&#x4f7f;&#x7528;&#x3059;&#x308b;&#x5834;&#x5408;&#x306f;&#x8457;&#x4f5c;&#x6a29;&#x8005;&#x304b;&#x3089;&#x697d;&#x66f2;&#x5229;&#x7528;&#x306e;&#x8a31;&#x53ef;&#x304c;&#x304a;&#x308a;&#x3066;&#x3044;&#x308b;&#x3082;&#x306e;&#x3092;&#x304a;&#x4f7f;&#x3044;&#x304f;&#x3060;&#x3055;&#x3044;&#x3002;<br>\n&#x25cf;&#x5927;&#x58f0;&#x3092;&#x51fa;&#x3059;&#x30fb;&#x5927;&#x97f3;&#x91cf;&#x3067;&#x97f3;&#x697d;&#x3092;&#x6d41;&#x3059;&#x3001;&#x9053;&#x3092;&#x585e;&#x3050;&#x306a;&#x3069;&#x3001;&#x4eba;&#x306e;&#x8ff7;&#x60d1;&#x306b;&#x306a;&#x308b;&#x884c;&#x70ba;&#x306f;&#x63a7;&#x3048;&#x3066;&#x3001;&#x64ae;&#x5f71;&#x3084;&#x30e9;&#x30a4;&#x30d6;&#x914d;&#x4fe1;&#x3092;&#x5b9f;&#x65bd;&#x3057;&#x3066;&#x304f;&#x3060;&#x3055;&#x3044;&#x3002;<br>\n</p>\n<p style=\"margin:10px;font-size:15px;\">\n&#x25cf;&#x5fdc;&#x52df;&#x8005;&#x3068;&#x4e00;&#x7dd2;&#x306b;&#x6295;&#x7a3f;&#x52d5;&#x753b;&#x30fb;&#x30e9;&#x30a4;&#x30d6;&#x914d;&#x4fe1;&#x306b;&#x5199;&#x3063;&#x3066;&#x3044;&#x308b;&#x65b9;&#x304c;&#x3044;&#x3089;&#x3063;&#x3057;&#x3083;&#x308b;&#x5834;&#x5408;&#x3084;&#x3001;&#x7b2c;&#x4e09;&#x8005;&#x306e;&#x77e5;&#x7684;&#x8ca1;&#x7523;&#x6a29;&#x304c;&#x542b;&#x307e;&#x308c;&#x308b;&#x5834;&#x5408;&#x3001;&#x5fc5;&#x305a;&#x6295;&#x7a3f;&#x3084;&#x30e9;&#x30a4;&#x30d6;&#x914d;&#x4fe1;&#x524d;&#x306b;&#x6a29;&#x5229;&#x8005;&#x304b;&#x3089;&#x4f7f;&#x7528;&#x8a31;&#x8afe;&#x3092;&#x5f97;&#x3066;&#x304f;&#x3060;&#x3055;&#x3044;&#x3002;<br>\n&#x307e;&#x305f;&#x3001;&#x5fdc;&#x52df;&#x8005;&#x306f;&#x6295;&#x7a3f;&#x52d5;&#x753b;&#x30fb;&#x30e9;&#x30a4;&#x30d6;&#x914d;&#x4fe1;&#x306b;&#x3064;&#x3044;&#x3066;&#x81ea;&#x3089;&#x304c;&#x6295;&#x7a3f;&#x30fb;&#x30e9;&#x30a4;&#x30d6;&#x914d;&#x4fe1;&#x3059;&#x308b;&#x3053;&#x3068;&#x306b;&#x3064;&#x3044;&#x3066;&#x306e;&#x9069;&#x6cd5;&#x306a;&#x6a29;&#x5229;&#x3092;&#x6709;&#x3057;&#x3066;&#x3044;&#x308b;&#x3053;&#x3068;&#x53ca;&#x3073;&#x7b2c;&#x4e09;&#x8005;&#x306e;&#x4e00;&#x5207;&#x306e;&#x6a29;&#x5229;&#x3092;&#x4fb5;&#x5bb3;&#x3057;&#x3066;&#x3044;&#x306a;&#x3044;&#x3053;&#x3068;&#x306b;&#x3064;&#x3044;&#x3066;&#x5f53;&#x793e;&#x306b;&#x5bfe;&#x3057;&#x8868;&#x660e;&#x3057;&#x3001;&#x4fdd;&#x8a3c;&#x3059;&#x308b;&#x3082;&#x306e;&#x3068;&#x3057;&#x307e;&#x3059;&#x3002;&#x4e07;&#x304c;&#x4e00;&#x3001;&#x7b2c;&#x4e09;&#x8005;&#x304b;&#x3089;&#x306e;&#x6a29;&#x5229;&#x4fb5;&#x5bb3;&#x7b49;&#x306e;&#x7533;&#x3057;&#x7acb;&#x3066;&#x304c;&#x3042;&#x3063;&#x305f;&#x5834;&#x5408;&#x306b;&#x306f;&#x3001;&#x6295;&#x7a3f;&#x8005;&#x3084;&#x914d;&#x4fe1;&#x8005;&#x3054;&#x81ea;&#x8eab;&#x306e;&#x8cac;&#x4efb;&#x3092;&#x3082;&#x3063;&#x3066;&#x89e3;&#x6c7a;&#x3057;&#x3066;&#x3044;&#x305f;&#x3060;&#x304d;&#x307e;&#x3059;&#x306e;&#x3067;&#x3001;&#x4e88;&#x3081;&#x3054;&#x4e86;&#x627f;&#x304f;&#x3060;&#x3055;&#x3044;&#x3002;<br>\n&#x25cf;&#x30df;&#x30af;&#x30c1;&#x30e3;&#x4ee5;&#x5916;&#x306e;&#x30d7;&#x30e9;&#x30c3;&#x30c8;&#x30d5;&#x30a9;&#x30fc;&#x30e0;&#x3067;&#x4f5c;&#x6210;&#x3057;&#x305f;&#x52d5;&#x753b;&#x3092;&#x30df;&#x30af;&#x30c1;&#x30e3;&#x3067;&#x30a2;&#x30c3;&#x30d7;&#x30ed;&#x30fc;&#x30c9;&#x3059;&#x308b;&#x5834;&#x5408;&#x3001;&#x5f53;&#x8a72;&#x30d7;&#x30e9;&#x30c3;&#x30c8;&#x30d5;&#x30a9;&#x30fc;&#x30e0;&#x306e;&#x5229;&#x7528;&#x898f;&#x7d04;&#x306b;&#x6cbf;&#x3063;&#x3066;&#x6295;&#x7a3f;&#x3057;&#x3066;&#x304f;&#x3060;&#x3055;&#x3044;&#x3002;<br>\n&#x25cf;&#x672a;&#x6210;&#x5e74;&#x306e;&#x65b9;&#x306f;&#x4fdd;&#x8b77;&#x8005;&#x306e;&#x540c;&#x610f;&#x3092;&#x5f97;&#x305f;&#x4e0a;&#x3067;&#x3054;&#x5fdc;&#x52df;&#x304f;&#x3060;&#x3055;&#x3044;&#x3002;&#x307e;&#x305f;&#x3001;&#x5fc5;&#x8981;&#x306b;&#x5fdc;&#x3058;&#x3066;&#x3001;&#x5728;&#x7c4d;&#x3059;&#x308b;&#x5b66;&#x6821;&#x307e;&#x305f;&#x306f;&#x6240;&#x5c5e;&#x3059;&#x308b;&#x90e8;&#x6d3b;&#x52d5;&#x304c;&#x52a0;&#x76df;&#x3059;&#x308b;&#x9023;&#x76df;&#x7b49;&#x3078;&#x78ba;&#x8a8d;&#x3092;&#x3068;&#x3063;&#x305f;&#x3046;&#x3048;&#x3067;&#x5fdc;&#x52df;&#x3057;&#x3066;&#x304f;&#x3060;&#x3055;&#x3044;&#x3002;<br>\n&#x25cf;&#x4e8b;&#x52d9;&#x6240;&#x3001;&#x5287;&#x56e3;&#x3001;&#x305d;&#x306e;&#x4ed6;&#x306e;&#x56e3;&#x4f53;&#xff08;&#x4ee5;&#x4e0b;&#x300c;&#x4e8b;&#x52d9;&#x6240;&#x7b49;&#x300d;&#x3068;&#x3044;&#x3044;&#x307e;&#x3059;&#xff09;&#x306b;&#x6240;&#x5c5e;&#x3055;&#x308c;&#x3066;&#x3044;&#x308b;&#x65b9;&#x306f;&#x3001;&#x3054;&#x81ea;&#x8eab;&#x306e;&#x8cac;&#x4efb;&#x3067;&#x4e8b;&#x52d9;&#x6240;&#x7b49;&#x306b;&#x672c;&#x30ad;&#x30e3;&#x30f3;&#x30da;&#x30fc;&#x30f3;&#x3078;&#x306e;&#x5fdc;&#x52df;&#x306e;&#x53ef;&#x5426;&#x306b;&#x3064;&#x304d;&#x3054;&#x78ba;&#x8a8d;&#x304f;&#x3060;&#x3055;&#x3044;&#x3002;<br>\n&#x25cf;&#x30b3;&#x30f3;&#x30c6;&#x30b9;&#x30c8;&#x306a;&#x3069;&#x306e;&#x65b0;&#x3057;&#x3044;&#x624d;&#x80fd;&#x306e;&#x767a;&#x6398;&#x3092;&#x76ee;&#x7684;&#x3068;&#x3057;&#x305f;&#x3082;&#x306e;&#x3084;&#x3001;&#x4e8b;&#x52d9;&#x6240;&#x6240;&#x5c5e;&#x8005;&#x3084;&#x65b0;&#x30b0;&#x30eb;&#x30fc;&#x30d7;&#x30e1;&#x30f3;&#x30d0;&#x30fc;&#x306e;&#x9078;&#x5b9a;&#x3092;&#x76ee;&#x7684;&#x3068;&#x3057;&#x305f;&#x4e00;&#x822c;&#x7684;&#x306a;&#x300c;&#x30aa;&#x30fc;&#x30c7;&#x30a3;&#x30b7;&#x30e7;&#x30f3;&#x300d;&#x306b;&#x95a2;&#x3059;&#x308b;&#x30a4;&#x30d9;&#x30f3;&#x30c8;&#x306b;&#x306f;&#x3001;&#x30ad;&#x30e3;&#x30c3;&#x30b7;&#x30e5;&#x30d0;&#x30c3;&#x30af;&#x306e;&#x304a;&#x652f;&#x6255;&#x3044;&#x306f;&#x3054;&#x3056;&#x3044;&#x307e;&#x305b;&#x3093;&#x3002;&#x306a;&#x304a;&#x3001;&#x4e00;&#x90e8;&#x5bfe;&#x8c61;&#x5916;&#x306e;&#x3082;&#x306e;&#x3082;&#x3054;&#x3056;&#x3044;&#x307e;&#x3059;&#x306e;&#x3067;&#x3001;&#x3054;&#x4e0d;&#x660e;&#x306a;&#x5834;&#x5408;&#x306f;&#x304a;&#x554f;&#x3044;&#x5408;&#x308f;&#x305b;&#x304f;&#x3060;&#x3055;&#x3044;&#x3002;<br>\n&#x25cf;&#x4e0a;&#x8a18;&#x5404;&#x9805;&#x3078;&#x306e;&#x9055;&#x53cd;&#x3084;&#x6975;&#x7aef;&#x306b;&#x4ed6;&#x4eba;&#x306b;&#x4e0d;&#x5feb;&#x611f;&#x3092;&#x4e0e;&#x3048;&#x308b;&#x3088;&#x3046;&#x306a;&#x8a00;&#x52d5;&#x3084;&#x3001;&#x6cd5;&#x5f8b;&#x306b;&#x62b5;&#x89e6;&#x3059;&#x308b;&#x5185;&#x5bb9;&#x3001;&#x30df;&#x30af;&#x30c1;&#x30e3;&#x306e;&#x5229;&#x7528;&#x898f;&#x7d04;&#x306b;&#x9055;&#x53cd;&#x3057;&#x305f;&#x5185;&#x5bb9;&#x3001;&#x904b;&#x55b6;&#x4e8b;&#x52d9;&#x5c40;&#x304c;&#x4e0d;&#x9069;&#x5207;&#x3068;&#x5224;&#x65ad;&#x3057;&#x305f;&#x52d5;&#x753b;&#x3084;&#x30e9;&#x30a4;&#x30d6;&#x914d;&#x4fe1;&#x306b;&#x3064;&#x3044;&#x3066;&#x306f;&#x524a;&#x9664;&#x3001;&#x3082;&#x3057;&#x304f;&#x306f;&#x30ad;&#x30e3;&#x30c3;&#x30b7;&#x30e5;&#x30d0;&#x30c3;&#x30af;&#x3084;&#x5be9;&#x67fb;&#x3001;&#x53d7;&#x8cde;&#x306e;&#x5bfe;&#x8c61;&#x5916;&#x3068;&#x3059;&#x308b;&#x53ef;&#x80fd;&#x6027;&#x304c;&#x3054;&#x3056;&#x3044;&#x307e;&#x3059;&#x306e;&#x3067;&#x3054;&#x4e86;&#x627f;&#x304f;&#x3060;&#x3055;&#x3044;&#x3002;<br>\n&#x25cf;&#x672c;&#x5fdc;&#x52df;&#x898f;&#x7d04;&#x306b;&#x5b9a;&#x3081;&#x308b;&#x4e8b;&#x9805;&#x306e;&#x307b;&#x304b;&#x3001;&#x30df;&#x30af;&#x30c1;&#x30e3;&#x5229;&#x7528;&#x898f;&#x7d04;&#x53ca;&#x3073;&#x30d7;&#x30e9;&#x30a4;&#x30d0;&#x30b7;&#x30fc;&#x30dd;&#x30ea;&#x30b7;&#x30fc;&#x304c;&#x9069;&#x7528;&#x3055;&#x308c;&#x307e;&#x3059;&#x306e;&#x3067;&#x3001;&#x78ba;&#x8a8d;&#x306e;&#x4e0a;&#x3001;&#x3054;&#x5fdc;&#x52df;&#x304f;&#x3060;&#x3055;&#x3044;&#x3002;<br>\n</p>\n\n<div style=\"font-size:16px;padding:.75em 0;border-top:1px solid #D12B34;border-bottom:1px solid #D12B34;\">\n&#x3000;&#x25aa;&#xfe0f;&#x8cde;&#x54c1;&#x30fb;&#x53d7;&#x8cde;&#x306b;&#x3064;&#x3044;&#x3066;\n</div>\n<p style=\"margin:10px;font-size:15px;\">\n&#x25cf;&#x53d7;&#x8cde;&#x8005;&#x3068;&#x9023;&#x7d61;&#x304c;&#x3064;&#x304b;&#x306a;&#x3044;&#x5834;&#x5408;&#x3001;&#x8cde;&#x54c1;&#x53d7;&#x9818;&#x306e;&#x610f;&#x601d;&#x304c;&#x78ba;&#x8a8d;&#x3067;&#x304d;&#x306a;&#x3044;&#x5834;&#x5408;&#x3001;&#x6307;&#x5b9a;&#x3055;&#x308c;&#x305f;&#x671f;&#x65e5;&#x307e;&#x3067;&#x306b;&#x9023;&#x7d61;&#x5148;&#x3092;&#x3054;&#x8fd4;&#x4fe1;&#x3044;&#x305f;&#x3060;&#x3051;&#x306a;&#x3044;&#x5834;&#x5408;&#x7b49;&#x306b;&#x306f;&#x3001;&#x53d7;&#x8cde;&#x3092;&#x8f9e;&#x9000;&#x3055;&#x308c;&#x305f;&#x3082;&#x306e;&#x3068;&#x307f;&#x306a;&#x3057;&#x3001;&#x53d7;&#x8cde;&#x3092;&#x7121;&#x52b9;&#x3068;&#x3055;&#x305b;&#x3066;&#x3044;&#x305f;&#x3060;&#x304d;&#x307e;&#x3059;&#x3002;&#x4e88;&#x3081;&#x3054;&#x4e86;&#x627f;&#x304f;&#x3060;&#x3055;&#x3044;&#x3002;<br>\n&#x25cf;&#x53d7;&#x8cde;&#x306e;&#x6a29;&#x5229;&#x306f;&#x53d7;&#x8cde;&#x8005;&#x3054;&#x672c;&#x4eba;&#x306e;&#x3082;&#x306e;&#x3067;&#x3042;&#x3063;&#x3066;&#x3001;&#x7b2c;&#x4e09;&#x8005;&#x3078;&#x8b72;&#x6e21;&#x30fb;&#x63db;&#x91d1;&#x7b49;&#x3059;&#x308b;&#x3053;&#x3068;&#x306f;&#x3067;&#x304d;&#x307e;&#x305b;&#x3093;&#x3002;&#x307e;&#x305f;&#x3001;&#x53d7;&#x9818;&#x3057;&#x305f;&#x8cde;&#x54c1;&#x306e;&#x7d1b;&#x5931;&#x7b49;&#x306b;&#x3088;&#x308b;&#x518d;&#x9001;&#x4ed8;&#x3001;&#x53d7;&#x8cde;&#x8005;&#x306e;&#x4e8b;&#x60c5;&#x306b;&#x3088;&#x308b;&#x5909;&#x66f4;&#x3001;&#x305d;&#x306e;&#x4ed6;&#x30af;&#x30ec;&#x30fc;&#x30e0;&#x7b49;&#x306b;&#x306f;&#x4e00;&#x5207;&#x5fdc;&#x3058;&#x308b;&#x3053;&#x3068;&#x304c;&#x3067;&#x304d;&#x307e;&#x305b;&#x3093;&#x3002;<br>\n&#x25cf;&#x5f53;&#x793e;&#x306f;&#x3001;&#x8cde;&#x54c1;&#x306e;&#x54c1;&#x8cea;&#x53ca;&#x3073;&#x3001;&#x76ee;&#x7684;&#x9069;&#x5408;&#x6027;&#x306b;&#x3064;&#x3044;&#x3066;&#x4f55;&#x3089;&#x4fdd;&#x8a3c;&#x3059;&#x308b;&#x3053;&#x3068;&#x306f;&#x3067;&#x304d;&#x304b;&#x306d;&#x307e;&#x3059;&#x3002;&#x8cde;&#x54c1;&#x306e;&#x4f7f;&#x7528;&#x306b;&#x5f53;&#x305f;&#x3063;&#x3066;&#x306f;&#x3001;&#x8cde;&#x54c1;&#x306b;&#x8a18;&#x8f09;&#x306e;&#x6ce8;&#x610f;&#x4e8b;&#x9805;&#x3092;&#x3054;&#x78ba;&#x8a8d;&#x306e;&#x4e0a;&#x3001;&#x3054;&#x4f7f;&#x7528;&#x304f;&#x3060;&#x3055;&#x3044;&#x3002;&#x53d7;&#x8cde;&#x3055;&#x308c;&#x305f;&#x8cde;&#x54c1;&#x306e;&#x4f7f;&#x7528;&#x4e2d;&#x306b;&#x751f;&#x3058;&#x305f;&#x4e8b;&#x6545;&#x7b49;&#x306e;&#x30c8;&#x30e9;&#x30d6;&#x30eb;&#x306b;&#x3064;&#x3044;&#x3066;&#x306e;&#x8cac;&#x4efb;&#x306f;&#x3001;&#x5f53;&#x793e;&#x3067;&#x306f;&#x8ca0;&#x3044;&#x304b;&#x306d;&#x307e;&#x3059;&#x3002;<br>\n&#x25cf;&#x8cde;&#x54c1;&#x63d0;&#x4f9b;&#x5143;&#x306e;&#x4f55;&#x3089;&#x304b;&#x306e;&#x4e8b;&#x7531;&#x306b;&#x3088;&#x308a;&#x7279;&#x5178;&#x4e0d;&#x5c65;&#x884c;&#x3068;&#x306a;&#x308b;&#x4e8b;&#x6848;&#x304c;&#x751f;&#x3058;&#x305f;&#x5834;&#x5408;&#x306f;&#x3001;&#x4ee3;&#x66ff;&#x8cde;&#x54c1;&#x306b;&#x3088;&#x308b;&#x88dc;&#x586b;&#x306a;&#x3069;&#x3067;&#x5bfe;&#x5fdc;&#x3059;&#x308b;&#x3053;&#x3068;&#x304c;&#x3054;&#x3056;&#x3044;&#x307e;&#x3059;&#x306e;&#x3067;&#x3054;&#x4e86;&#x627f;&#x304f;&#x3060;&#x3055;&#x3044;&#x307e;&#x305b;&#x3002;<br>\n</p>\n\n<div style=\"font-size:16px;padding:.75em 0;border-top:1px solid #D12B34;border-bottom:1px solid #D12B34;\">\n&#x3000;&#x25aa;&#xfe0f;&#x7981;&#x6b62;&#x4e8b;&#x9805;\n</div>\n<p style=\"margin:10px;font-size:15px;\">\n&#x672c;&#x30ad;&#x30e3;&#x30f3;&#x30da;&#x30fc;&#x30f3;&#x3078;&#x306e;&#x5fdc;&#x52df;&#x306b;&#x969b;&#x3057;&#x3001;&#x4ee5;&#x4e0b;&#x306e;&#x884c;&#x70ba;&#x3092;&#x7981;&#x6b62;&#x3057;&#x307e;&#x3059;&#x3002;&#x5f53;&#x793e;&#x306f;&#x3001;&#x5fdc;&#x52df;&#x8005;&#x304c;&#x4ee5;&#x4e0b;&#x306b;&#x8a72;&#x5f53;&#x3059;&#x308b;&#x884c;&#x70ba;&#x3092;&#x884c;&#x3063;&#x305f;&#x3068;&#x5224;&#x65ad;&#x3057;&#x305f;&#x5834;&#x5408;&#x306f;&#x3001;&#x5fdc;&#x52df;&#x8005;&#x3078;&#x306e;&#x4e8b;&#x524d;&#x901a;&#x544a;&#x306a;&#x304f;&#x3001;&#x5bfe;&#x8c61;&#x6295;&#x7a3f;&#x3092;&#x63b2;&#x8f09;&#x3057;&#x306a;&#x3044;&#x3001;&#x63b2;&#x8f09;&#x5f8c;&#x524a;&#x9664;&#x3059;&#x308b;&#x3001;&#x5fdc;&#x52df;&#x30fb;&#x53d7;&#x8cde;&#x3092;&#x7121;&#x52b9;&#x3068;&#x3059;&#x308b;&#x306a;&#x3069;&#x306e;&#x5bfe;&#x5fdc;&#x3092;&#x3068;&#x308b;&#x5834;&#x5408;&#x304c;&#x3042;&#x308a;&#x307e;&#x3059;&#x3002;<br>\n<br>\n&#x30fb;&#x672c;&#x898f;&#x7d04;&#x307e;&#x305f;&#x306f;&#x6cd5;&#x4ee4;&#x306b;&#x9055;&#x53cd;&#x3059;&#x308b;&#x884c;&#x70ba;<br>\n&#x30fb;&#x672c;&#x30ad;&#x30e3;&#x30f3;&#x30da;&#x30fc;&#x30f3;&#x306e;&#x904b;&#x55b6;&#x3092;&#x59a8;&#x3052;&#x308b;&#x884c;&#x70ba;<br>\n&#x30fb;&#x4ed6;&#x4eba;&#x306b;&#x8ff7;&#x60d1;&#x3001;&#x4e0d;&#x5229;&#x76ca;&#x3001;&#x640d;&#x5bb3;&#x307e;&#x305f;&#x306f;&#x4e0d;&#x5feb;&#x611f;&#x3092;&#x4e0e;&#x3048;&#x308b;&#x884c;&#x70ba;<br>\n&#x30fb;&#x4ed6;&#x4eba;&#x3092;&#x8ab9;&#x8b17;&#x4e2d;&#x50b7;&#x3057;&#x3001;&#x307e;&#x305f;&#x306f;&#x305d;&#x306e;&#x540d;&#x8a89;&#x82e5;&#x3057;&#x304f;&#x306f;&#x4fe1;&#x7528;&#x3092;&#x6bc0;&#x640d;&#x3059;&#x308b;&#x884c;&#x70ba;<br>\n&#x30fb;&#x7b2c;&#x4e09;&#x8005;&#x306e;&#x8457;&#x4f5c;&#x6a29;&#x305d;&#x306e;&#x4ed6;&#x306e;&#x77e5;&#x7684;&#x8ca1;&#x7523;&#x6a29;&#x3092;&#x4fb5;&#x5bb3;&#x3059;&#x308b;&#x884c;&#x70ba;<br>\n&#x30fb;&#x4ed6;&#x4eba;&#x306e;&#x8ca1;&#x7523;&#x3001;&#x30d7;&#x30e9;&#x30a4;&#x30d0;&#x30b7;&#x30fc;&#x82e5;&#x3057;&#x304f;&#x306f;&#x8096;&#x50cf;&#x6a29;&#x3092;&#x4fb5;&#x5bb3;&#x3059;&#x308b;&#x884c;&#x70ba;<br>\n&#x30fb;&#x308f;&#x3044;&#x305b;&#x3064;&#x3001;&#x5150;&#x7ae5;&#x30dd;&#x30eb;&#x30ce;&#x53ca;&#x3073;&#x5150;&#x7ae5;&#x306e;&#x6027;&#x7684;&#x643e;&#x53d6;&#x3092;&#x52a9;&#x9577;&#x3059;&#x308b;&#x30c7;&#x30fc;&#x30bf;&#x3092;&#x6295;&#x7a3f;&#x3059;&#x308b;&#x884c;&#x70ba;<br>\n&#x30fb;&#x55b6;&#x5229;&#x3092;&#x76ee;&#x7684;&#x3068;&#x3057;&#x305f;&#x60c5;&#x5831;&#x63d0;&#x4f9b;&#x3001;&#x5e83;&#x544a;&#x5ba3;&#x4f1d;&#x3082;&#x3057;&#x304f;&#x306f;&#x52e7;&#x8a98;&#x884c;&#x70ba;<br>\n&#x30fb;&#x516c;&#x5e8f;&#x826f;&#x4fd7;&#x306b;&#x53cd;&#x3059;&#x308b;&#x884c;&#x70ba;<br>\n&#x30fb;&#x30df;&#x30af;&#x30c1;&#x30e3;&#x306e;&#x5229;&#x7528;&#x898f;&#x7d04;&#x306b;&#x9055;&#x53cd;&#x3059;&#x308b;&#x884c;&#x70ba;<br>\n&#x30fb;&#x305d;&#x306e;&#x4ed6;&#x3001;&#x524d;&#x5404;&#x53f7;&#x306b;&#x985e;&#x3059;&#x308b;&#x884c;&#x70ba;<br>\n</p>\n\n<div style=\"font-size:16px;padding:.75em 0;border-top:1px solid #D12B34;border-bottom:1px solid #D12B34;\">\n&#x3000;&#x25aa;&#xfe0f;&#x514d;&#x8cac;&#x30fb;&#x305d;&#x306e;&#x4ed6;\n</div>\n<p style=\"margin:10px;font-size:15px;\">\n&#x672c;&#x30ad;&#x30e3;&#x30f3;&#x30da;&#x30fc;&#x30f3;&#x306f;&#x3001;&#x7d30;&#x5fc3;&#x306e;&#x6ce8;&#x610f;&#x3092;&#x6255;&#x3063;&#x3066;&#x904b;&#x55b6;&#x3092;&#x3057;&#x3066;&#x3044;&#x307e;&#x3059;&#x304c;&#x3001;&#x63d0;&#x4f9b;&#x3059;&#x308b;&#x60c5;&#x5831;&#x3001;&#x30d7;&#x30ed;&#x30b0;&#x30e9;&#x30e0;&#x3001;&#x5404;&#x7a2e;&#x30b5;&#x30fc;&#x30d3;&#x30b9;&#x3001;&#x305d;&#x306e;&#x4ed6;&#x672c;&#x30ad;&#x30e3;&#x30f3;&#x30da;&#x30fc;&#x30f3;&#x306b;&#x95a2;&#x3059;&#x308b;&#x3059;&#x3079;&#x3066;&#x306e;&#x4e8b;&#x9805;&#x306b;&#x3064;&#x3044;&#x3066;&#x3001;&#x305d;&#x306e;&#x5b8c;&#x5168;&#x6027;&#x3001;&#x6b63;&#x78ba;&#x6027;&#x3001;&#x5b89;&#x5168;&#x6027;&#x3001;&#x6709;&#x7528;&#x6027;&#x7b49;&#x306b;&#x3064;&#x3044;&#x3066;&#x3001;&#x3044;&#x304b;&#x306a;&#x308b;&#x4fdd;&#x8a3c;&#x3082;&#x3059;&#x308b;&#x3082;&#x306e;&#x3067;&#x306f;&#x3042;&#x308a;&#x307e;&#x305b;&#x3093;&#x3002;&#x307e;&#x305f;&#x3001;&#x5229;&#x7528;&#x8005;&#x307e;&#x305f;&#x306f;&#x7b2c;&#x4e09;&#x8005;&#x304c;&#x88ab;&#x3063;&#x305f;&#x4ee5;&#x4e0b;&#x306e;&#x4e8b;&#x4f8b;&#x3092;&#x542b;&#x3080;&#x640d;&#x5bb3;&#x306b;&#x3064;&#x3044;&#x3066;&#x306f;&#x3001;&#x5f53;&#x793e;&#x306f;&#x8cac;&#x4efb;&#x3092;&#x8ca0;&#x3044;&#x304b;&#x306d;&#x307e;&#x3059;&#x3002;<br>\n<br>\n1.&#x672c;&#x30ad;&#x30e3;&#x30f3;&#x30da;&#x30fc;&#x30f3;&#x3078;&#x306e;&#x5fdc;&#x52df;&#x306b;&#x969b;&#x3057;&#x3066;&#x3001;&#x30bd;&#x30d5;&#x30c8;&#x30a6;&#x30a7;&#x30a2;&#x30fb;&#x30cf;&#x30fc;&#x30c9;&#x30a6;&#x30a7;&#x30a2;&#x4e0a;&#x306e;&#x4e8b;&#x6545;&#x3001;&#x706b;&#x707d;&#x3001;&#x505c;&#x96fb;&#x3001;&#x901a;&#x4fe1;&#x74b0;&#x5883;&#x306e;&#x60aa;&#x5316;&#x3001;&#x5730;&#x9707;&#x3001;&#x4e8b;&#x5909;&#x7b49;&#x306e;&#x975e;&#x5e38;&#x4e8b;&#x614b;&#x304c;&#x767a;&#x751f;&#x3057;&#x305f;&#x5834;&#x5408;&#x3002;<br>\n2.&#x672c;&#x30ad;&#x30e3;&#x30f3;&#x30da;&#x30fc;&#x30f3;&#x306b;&#x304a;&#x3051;&#x308b;&#x30b7;&#x30b9;&#x30c6;&#x30e0;&#x306e;&#x4fdd;&#x5b88;&#x3092;&#x5b9a;&#x671f;&#x7684;&#x3042;&#x308b;&#x3044;&#x306f;&#x7dca;&#x6025;&#x306b;&#x884c;&#x3046;&#x5834;&#x5408;&#x3002;<br>\n3.&#x5229;&#x7528;&#x8005;&#x9593;&#x307e;&#x305f;&#x306f;&#x5229;&#x7528;&#x8005;&#x3068;&#x7b2c;&#x4e09;&#x8005;&#x306e;&#x9593;&#x306b;&#x304a;&#x3051;&#x308b;&#x30c8;&#x30e9;&#x30d6;&#x30eb;&#x7b49;&#x304c;&#x751f;&#x3058;&#x305f;&#x5834;&#x5408;&#x3002;<br>\n4.&#x7b2c;&#x4e09;&#x8005;&#x306b;&#x3088;&#x308b;&#x672c;&#x30ad;&#x30e3;&#x30f3;&#x30da;&#x30fc;&#x30f3;&#x306e;&#x30b5;&#x30fc;&#x30d3;&#x30b9;&#x306e;&#x59a8;&#x5bb3;&#x3001;&#x60c5;&#x5831;&#x6539;&#x5909;&#x306a;&#x3069;&#x306b;&#x3088;&#x308a;&#x30b5;&#x30fc;&#x30d3;&#x30b9;&#x304c;&#x4e2d;&#x65ad;&#x3082;&#x3057;&#x304f;&#x306f;&#x9045;&#x5ef6;&#x3057;&#x3001;&#x4f55;&#x3089;&#x304b;&#x306e;&#x6b20;&#x9665;&#x304c;&#x751f;&#x3058;&#x305f;&#x5834;&#x5408;&#x3002;<br>\n5.&#x5f53;&#x793e;&#x304c;&#x63a8;&#x5968;&#x3059;&#x308b;&#x74b0;&#x5883;&#x4ee5;&#x5916;&#x304b;&#x3089;&#x672c;&#x30ad;&#x30e3;&#x30f3;&#x30da;&#x30fc;&#x30f3;&#x306b;&#x5fdc;&#x52df;&#x3057;&#x305f;&#x305f;&#x3081;&#x306b;&#x60c5;&#x5831;&#x3092;&#x5b8c;&#x5168;&#x306b;&#x53d6;&#x5f97;&#x3067;&#x304d;&#x306a;&#x3044;&#x5834;&#x5408;&#x3002;<br>\n6.&#x6545;&#x610f;&#x307e;&#x305f;&#x306f;&#x91cd;&#x904e;&#x5931;&#x306a;&#x304f;&#x3057;&#x3066;&#x672c;&#x30ad;&#x30e3;&#x30f3;&#x30da;&#x30fc;&#x30f3;&#x304c;&#x63d0;&#x4f9b;&#x3059;&#x308b;&#x60c5;&#x5831;&#x304c;&#x8aa4;&#x9001;&#x4fe1;&#x3055;&#x308c;&#x308b;&#x304b;&#x3001;&#x3082;&#x3057;&#x304f;&#x306f;&#x6b20;&#x9665;&#x304c;&#x3042;&#x3063;&#x305f;&#x5834;&#x5408;&#x3002;<br>\n<br>\n&#x5f53;&#x793e;&#x306f;&#x3001;&#x672c;&#x30ad;&#x30e3;&#x30f3;&#x30da;&#x30fc;&#x30f3;&#x306e;&#x5fdc;&#x52df;&#x306b;&#x3088;&#x308a;&#x5fdc;&#x52df;&#x8005;&#x306b;&#x751f;&#x3058;&#x305f;&#x4e00;&#x5207;&#x306e;&#x30c8;&#x30e9;&#x30d6;&#x30eb;&#x30fb;&#x640d;&#x5bb3;&#xff08;&#x76f4;&#x63a5;&#x30fb;&#x9593;&#x63a5;&#x3092;&#x554f;&#x3044;&#x307e;&#x305b;&#x3093;&#xff09;&#x306b;&#x3064;&#x3044;&#x3066;&#x3001;&#x5982;&#x4f55;&#x306a;&#x308b;&#x8cac;&#x4efb;&#x3082;&#x8ca0;&#x3044;&#x307e;&#x305b;&#x3093;&#x3002;<br>\n&#x672c;&#x30ad;&#x30e3;&#x30f3;&#x30da;&#x30fc;&#x30f3;&#x306e;&#x5fdc;&#x52df;&#x306b;&#x304b;&#x304b;&#x308b;&#x30a4;&#x30f3;&#x30bf;&#x30fc;&#x30cd;&#x30c3;&#x30c8;&#x63a5;&#x7d9a;&#x6599;&#x53ca;&#x3073;&#x901a;&#x4fe1;&#x8cbb;&#x306f;&#x5fdc;&#x52df;&#x8005;&#x306e;&#x3054;&#x8ca0;&#x62c5;&#x3068;&#x306a;&#x308a;&#x307e;&#x3059;&#x3002;<br>\n&#x672c;&#x30ad;&#x30e3;&#x30f3;&#x30da;&#x30fc;&#x30f3;&#x306f;&#x3001;&#x30df;&#x30af;&#x30c1;&#x30e3;&#x3092;&#x63d0;&#x4f9b;&#x3057;&#x3066;&#x3044;&#x308b;&#x5f53;&#x793e;&#xff08;&#x682a;&#x5f0f;&#x4f1a;&#x793e;Donuts&#xff09;&#x304c;&#x904b;&#x55b6;&#x3057;&#x3066;&#x3044;&#x308b;&#x3082;&#x306e;&#x3067;&#x3042;&#x308a;&#x3001;Apple&#x793e;&#x306b;&#x3088;&#x3063;&#x3066;&#x63d0;&#x4f9b;&#x3055;&#x308c;&#x3066;&#x3044;&#x308b;&#x3082;&#x306e;&#x3067;&#x306f;&#x3054;&#x3056;&#x3044;&#x307e;&#x305b;&#x3093;&#x3002;<br>\n</p>\n\n<div style=\"font-size:16px;padding:.75em 0;border-top:1px solid #D12B34;border-bottom:1px solid #D12B34;\">\n&#x3000;&#x25aa;&#xfe0f;&#x500b;&#x4eba;&#x60c5;&#x5831;&#x306e;&#x53d6;&#x308a;&#x6271;&#x3044;&#x306b;&#x3064;&#x3044;&#x3066;\n</div>\n<p style=\"margin:10px;font-size:15px;\">\n&#x4f4f;&#x6240;&#x3001;&#x96fb;&#x8a71;&#x756a;&#x53f7;&#x3001;&#x6c0f;&#x540d;&#x3001;&#x6027;&#x5225;&#x3001;&#x5e74;&#x9f62;&#x3001;&#x30df;&#x30af;&#x30c1;&#x30e3;&#x30a2;&#x30ab;&#x30a6;&#x30f3;&#x30c8;URL&#x306e;&#x60c5;&#x5831;&#xff08;&#x4ee5;&#x4e0b;&#x300c;&#x500b;&#x4eba;&#x60c5;&#x5831;&#x300d;&#x3068;&#x3044;&#x3044;&#x307e;&#x3059;&#x3002;&#xff09;&#x306f;&#x3001;&#x682a;&#x5f0f;&#x4f1a;&#x793e;Donuts&#x304c;&#x7ba1;&#x7406;&#x3057;&#x307e;&#x3059;&#xff08;&#x7ba1;&#x7406;&#x8cac;&#x4efb;&#x8005;&#xff1a;&#x30df;&#x30af;&#x30c1;&#x30e3;&#x30b0;&#x30eb;&#x30fc;&#x30d7;&#x30ea;&#x30fc;&#x30c0;&#x30fc;&#xff09;&#x3002;&#x304a;&#x5ba2;&#x69d8;&#x306e;&#x500b;&#x4eba;&#x60c5;&#x5831;&#x306f;&#x3001;&#x672c;&#x30ad;&#x30e3;&#x30f3;&#x30da;&#x30fc;&#x30f3;&#x306e;&#x5f53;&#x9078;&#x8005;&#x3078;&#x306e;&#x9023;&#x7d61;&#x30fb;&#x8cde;&#x54c1;&#x306e;&#x9001;&#x4ed8;&#x7b49;&#x306e;&#x76ee;&#x7684;&#x3067;&#x5229;&#x7528;&#x3057;&#x3001;&#x305d;&#x308c;&#x4ee5;&#x5916;&#x306e;&#x76ee;&#x7684;&#x3067;&#x306f;&#x4f7f;&#x7528;&#x81f4;&#x3057;&#x307e;&#x305b;&#x3093;&#x3002;&#x307e;&#x305f;&#x3001;&#x304a;&#x5ba2;&#x69d8;&#x306e;&#x500b;&#x4eba;&#x60c5;&#x5831;&#x3092;&#x304a;&#x5ba2;&#x69d8;&#x306e;&#x540c;&#x610f;&#x306a;&#x3057;&#x306b;&#x696d;&#x52d9;&#x59d4;&#x8a17;&#x5148;&#x4ee5;&#x5916;&#x306e;&#x7b2c;&#x4e09;&#x8005;&#x306b;&#x958b;&#x793a;&#x30fb;&#x63d0;&#x4f9b;&#x3059;&#x308b;&#x3053;&#x3068;&#x306f;&#x3042;&#x308a;&#x307e;&#x305b;&#x3093;&#xff08;&#x6cd5;&#x4ee4;&#x7b49;&#x306b;&#x3088;&#x308a;&#x958b;&#x793a;&#x3092;&#x6c42;&#x3081;&#x3089;&#x308c;&#x305f;&#x5834;&#x5408;&#x3092;&#x9664;&#x304d;&#x307e;&#x3059;&#x3002;&#xff09;&#x3002;<br>\n&#x307e;&#x305f;&#x3001;&#x500b;&#x4eba;&#x60c5;&#x5831;&#x958b;&#x793a;&#x3001;&#x8a02;&#x6b63;&#x7b49;&#x306e;&#x304a;&#x554f;&#x3044;&#x5408;&#x308f;&#x305b;&#x306f;&#x3001;&#x30df;&#x30af;&#x30c1;&#x30e3;&#x904b;&#x55b6;&#x4e8b;&#x52d9;&#x5c40;&#xff08;mixch-support@donuts.ne.jp&#xff09;&#x307e;&#x3067;&#x304a;&#x9858;&#x3044;&#x81f4;&#x3057;&#x307e;&#x3059;&#x3002;<br>\n</p>\n\n<div style=\"font-size:16px;padding:.75em 0;border-top:1px solid #D12B34;border-bottom:1px solid #D12B34;\">\n&#x3000;&#x25aa;&#xfe0f;&#x30ad;&#x30e3;&#x30f3;&#x30da;&#x30fc;&#x30f3;&#x306b;&#x95a2;&#x3059;&#x308b;&#x304a;&#x554f;&#x3044;&#x5408;&#x308f;&#x305b;&#x7a93;&#x53e3;\n</div>\n<p style=\"margin:10px;font-size:15px;\">\n[&#x30df;&#x30af;&#x30c1;&#x30e3;&#x30b9;&#x30dd;&#x30f3;&#x30b5;&#x30fc;&#x4e8b;&#x52d9;&#x5c40;]<br>\nmixch-support@donuts.ne.jp<br>\n</p>\n\n<center><img src=\"https://d2uqarpmf42qy0.cloudfront.net/event/NIKU/mixch_LOGO.png\" width=\"20%\"></center>\n<br><br>\n</div>\n</div>\n\n<!-- 1タブの中身おわり💡 -->\n\n<!-- 💡2タブの中身はじめ -->\n\n<div id=\"tabView2\" class=\"tabView\">\n<div style=\"background-color:rgba(255,255,255,0.6);color:#735d65;font-size:15px;\">\n\n<h3 class=\"logo\">&#x30aa;&#x30fc;&#x30c7;&#x30a3;&#x30b7;&#x30e7;&#x30f3;&#x30b9;&#x30b1;&#x30b8;&#x30e5;&#x30fc;&#x30eb;</h3>\n<p style=\"margin:10px;font-size:15px;\">\n<b>&#x25c6;&#x30df;&#x30af;&#x30c1;&#x30e3;&#x30dd;&#x30a4;&#x30f3;&#x30c8;&#x5be9;&#x67fb; / &#x52d5;&#x753b;Like&#x5be9;&#x67fb;</b>\n<br>\n&#x3000;6&#x6708;29&#x65e5;(&#x6708;) 12:00:00 &#x301c; 7&#x6708;8&#x65e5;(&#x6c34;) 21:59:59<br>\n<br>\n\n<b>&#x25c6;&#x9762;&#x63a5;&#x5be9;&#x67fb;</b>\n<br>\n&#x3000;7&#x6708;10&#x65e5;(&#x91d1;)&#x301c;7&#x6708;17&#x65e5;(&#x91d1;)&#x306e;&#x3044;&#x305a;&#x308c;&#x304b;&#x4e88;&#x5b9a;<br>\n<br>\n\n<b>&#x25c6;&#x30b0;&#x30e9;&#x30f3;&#x30d7;&#x30ea;/&#x6e96;&#x30b0;&#x30e9;&#x30f3;&#x30d7;&#x30ea;&#x767a;&#x8868;</b>\n<br>\n&#x3000;7&#x6708;18&#x65e5;(&#x571f;) &#x4e88;&#x5b9a;<br>\n<br>\n\n<b>&#x25c6;&#x304a;&#x62ab;&#x9732;&#x76ee;&#x30b9;&#x30c6;&#x30fc;&#x30b8;</b>\n<br>\n&#x3000;2026&#x5e74;7&#x6708;31&#x65e5;(&#x91d1;) @TIF2026<br>\n\n</p><p style=\"margin:10px;font-size:15px;\">\n&#x203b;&#x30b9;&#x30b1;&#x30b8;&#x30e5;&#x30fc;&#x30eb;&#x306f;&#x4e88;&#x544a;&#x306a;&#x304f;&#x5909;&#x66f4;&#x3068;&#x306a;&#x308b;&#x5834;&#x5408;&#x304c;&#x3054;&#x3056;&#x3044;&#x307e;&#x3059;&#x306e;&#x3067;&#x3001;&#x4e88;&#x3081;&#x3054;&#x4e86;&#x627f;&#x304f;&#x3060;&#x3055;&#x3044;&#x3002;\n\n<br>\n<br>\n\n\n</p><h3 class=\"logo\">&#x30b0;&#x30e9;&#x30f3;&#x30d7;&#x30ea;/&#x6e96;&#x30b0;&#x30e9;&#x30f3;&#x30d7;&#x30ea;&#x7279;&#x5178;</h3>\n<center>\n<div style=\"margin:10px;color:#fff;background-image:linear-gradient(-90deg,  #b8860b);text-align:center;width:70%;border-radius:30px;padding:3px;\"><b>&#x30b0;&#x30e9;&#x30f3;&#x30d7;&#x30ea;&#xff08;1&#x540d;&#xff09;</b></div>\n</center>\n<p style=\"margin:1px;font-size:16px;\">\n<b>\n&#x30fb;andGIRL<b><font color=\"#D12B34\">&#x300e;&#x30d3;&#x30e5;&#x30fc;&#x30c6;&#x30a3;&#x30fc;&#x30df;&#x30e5;&#x30fc;&#x30ba;&#x300f;</font></b>&#x6c7a;&#x5b9a;&#xff01;<br>\n&#x30fb;<b><font color=\"#D12B34\">&#x300e;&#x30c7;&#x30b8;&#x30bf;&#x30eb;&#x5199;&#x771f;&#x96c6;&#x300f;</font></b>&#x5236;&#x4f5c;&#x6c7a;&#x5b9a;&#xff01;</b>\n<br>\n<br>\n\n\n</p><center>\n<div style=\"margin:10px;color:#fff;background-image:linear-gradient(-90deg,  #808080);text-align:center;width:70%;border-radius:30px;padding:3px;\"><b>&#x6e96;&#x30b0;&#x30e9;&#x30f3;&#x30d7;&#x30ea;&#xff08;2&#x540d;&#xff09;</b></div>\n</center>\n<p style=\"margin:1px;font-size:16px;\">\n<b>\n&#x30fb;<b><font color=\"#D12B34\">&#x300e;&#x30c7;&#x30b8;&#x30bf;&#x30eb;&#x5199;&#x771f;&#x96c6;&#x300f;</font></b>&#x5236;&#x4f5c;&#x6c7a;&#x5b9a;&#xff01;</b>\n<br>\n<br>\n\n</p><h3 class=\"logo\">&#x30b0;&#x30e9;&#x30f3;&#x30d7;&#x30ea;/&#x6e96;&#x30b0;&#x30e9;&#x30f3;&#x30d7;&#x30ea;&#x6c7a;&#x5b9a;&#x65b9;&#x6cd5;</h3>\n<p style=\"margin:10px;font-size:16px;\">\n<b>\n&#x2460;&#x30df;&#x30af;&#x30c1;&#x30e3;&#x30dd;&#x30a4;&#x30f3;&#x30c8;&#x5be9;&#x67fb;<br>\n&#x2461;&#x52d5;&#x753b;Like&#x5be9;&#x67fb;<br>\n&#x2462;&#x9762;&#x63a5;&#x5be9;&#x67fb;<br>\n</b>\n&#x27a1;&#xfe0e;3&#x3064;&#x306e;&#x5be9;&#x67fb;&#x306e;<b><font color=\"#b8860b\">&#x7dcf;&#x5408;&#x30dd;&#x30a4;&#x30f3;&#x30c8;1&#x4f4d;</font></b>&#x304c;<b><font color=\"#b8860b\">&#x30b0;&#x30e9;&#x30f3;&#x30d7;&#x30ea;</font></b>&#x3001;<b><font color=\"#808080\">&#x7dcf;&#x5408;&#x30dd;&#x30a4;&#x30f3;&#x30c8;2&#x301c;3&#x4f4d;</font></b>&#x304c;<b><font color=\"#808080\">&#x6e96;&#x30b0;&#x30e9;&#x30f3;&#x30d7;&#x30ea;</font></b>&#x306b;&#x6c7a;&#x5b9a;&#xff01;\n<br>\n<br>\n\n\n\n</p><h3 class=\"logo\">&#x5404;&#x5be9;&#x67fb;&#x306e;&#x8a73;&#x7d30;</h3>\n\n<center>\n<div style=\"margin:5px;padding:3px;background-color:#cc1d2b;text-align:center;font-size:16px;border-radius:20px;width:80%;\">\n<font color=\"#fffff\"><b>&#x5be9;&#x67fb;&#x2460;&#xff1a;&#x30df;&#x30af;&#x30c1;&#x30e3;&#x30dd;&#x30a4;&#x30f3;&#x30c8;&#x5be9;&#x67fb;</b></font>\n</div>\n</center>\n\n<p style=\"margin:10px;font-size:15px;\">\n&#x30df;&#x30af;&#x30c1;&#x30e3;&#x914d;&#x4fe1;+&#x52d5;&#x753b;&#x6295;&#x7a3f;&#x306b;&#x3088;&#x308b;&#x7372;&#x5f97;&#x30dd;&#x30a4;&#x30f3;&#x30c8;&#x6570;&#x3092;&#x7af6;&#x3044;&#x3001;&#x30e9;&#x30f3;&#x30ad;&#x30f3;&#x30b0;&#x306b;&#x5fdc;&#x3058;&#x3066;&#x7dcf;&#x5408;&#x30dd;&#x30a4;&#x30f3;&#x30c8;&#x3092;&#x4ed8;&#x4e0e;&#x3057;&#x307e;&#x3059;&#x3002;<br>\n<small>&#x203b;&#x2461;&#x52d5;&#x753b;Like&#x5be9;&#x67fb;&#x3067;&#x6295;&#x7a3f;&#x3057;&#x305f;&#x52d5;&#x753b;&#x306b;&#x3088;&#x308a;&#x7372;&#x5f97;&#x3057;&#x305f;&#x30dd;&#x30a4;&#x30f3;&#x30c8;&#x3082;&#x5be9;&#x67fb;&#x306e;&#x5bfe;&#x8c61;&#x3068;&#x3057;&#x307e;&#x3059;&#x3002;</small>\n</p><center>\n<img src=\"https://d2uqarpmf42qy0.cloudfront.net/event/41haba/TIF2026&#xd7;andGIRL_&#x30df;&#x30af;&#x30c1;&#x30e3;.png\" width=\"95%\">\n</center>\n<br>\n\n<center>\n<div style=\"margin:5px;padding:3px;background-color:#f54d8a;text-align:center;font-size:16px;border-radius:20px;width:80%;\">\n<font color=\"#fffff\"><b>&#x5be9;&#x67fb;&#x2461;&#xff1a;&#x52d5;&#x753b;Like&#x5be9;&#x67fb;</b></font>\n</div>\n</center>\n\n<p style=\"margin:10px;font-size:15px;\">\n&#x30df;&#x30af;&#x30c1;&#x30e3;&#x306b;&#x52d5;&#x753b;&#x3092;<b>1&#x3064;</b>&#x6295;&#x7a3f;&#x3057;&#x3066;&#x201d;Like&#x201d;&#x6570;&#x3092;&#x7af6;&#x3044;&#x3001;&#x30e9;&#x30f3;&#x30ad;&#x30f3;&#x30b0;&#x306b;&#x5fdc;&#x3058;&#x3066;&#x7dcf;&#x5408;&#x30dd;&#x30a4;&#x30f3;&#x30c8;&#x3092;&#x4ed8;&#x4e0e;&#x3057;&#x307e;&#x3059;&#x3002;\n\n\n</p><center>\n<img src=\"https://d2uqarpmf42qy0.cloudfront.net/event/41haba/TIF2026&#xd7;andGIRL_like.png\" width=\"95%\">\n</center>\n<br>\n\n<center>\n<div style=\"margin:5px;padding:3px;background-color:#fa8bb8;text-align:center;font-size:16px;border-radius:20px;width:80%;\">\n<font color=\"#fffff\"><b>&#x5be9;&#x67fb;&#x2462;&#xff1a;&#x9762;&#x63a5;&#x5be9;&#x67fb;</b></font>\n</div>\n</center>\n<p style=\"margin:10px;font-size:15px;\">\nandGIRL&#x7de8;&#x96c6;&#x90e8;&#x4ed6;&#x306b;&#x3066;&#x30aa;&#x30f3;&#x30e9;&#x30a4;&#x30f3;&#x9762;&#x63a5;&#x3092;&#x884c;&#x3044;&#x3001;&#x8a55;&#x4fa1;&#x306e;&#x30e9;&#x30f3;&#x30ad;&#x30f3;&#x30b0;&#x306b;&#x5fdc;&#x3058;&#x3066;&#x7dcf;&#x5408;&#x30dd;&#x30a4;&#x30f3;&#x30c8;&#x3092;&#x4ed8;&#x4e0e;&#x3057;&#x307e;&#x3059;&#x3002;\n</p><center>\n<img src=\"https://d2uqarpmf42qy0.cloudfront.net/event/41haba/TIF2026&#xd7;andGIRL_&#x9762;&#x63a5;.png\" width=\"95%\">\n</center>\n\n<br>\n<br>\n\n<h3 class=\"logo\">&#x5be9;&#x67fb;&#x306b;&#x304a;&#x3051;&#x308b;&#x6ce8;&#x610f;&#x4e8b;&#x9805;</h3>\n<center>\n<p style=\"margin:13px;font-size:15px;\">\n<b><font color=\"red\">&#x3010;&#x5fc5;&#x305a;&#x3054;&#x78ba;&#x8a8d;&#x304f;&#x3060;&#x3055;&#x3044;&#x3011;</font></b></p></center>\n<p style=\"margin:13px;font-size:15px;\">\n\n&#x25a0;&#x7dcf;&#x5408;&#x30dd;&#x30a4;&#x30f3;&#x30c8;&#x304c;&#x540c;&#x6570;&#x3068;&#x306a;&#x3063;&#x305f;&#x5834;&#x5408;&#x3001;&#x300c;&#x2460;&#x30df;&#x30af;&#x30c1;&#x30e3;&#x30dd;&#x30a4;&#x30f3;&#x30c8;&#x5be9;&#x67fb;&#x300d;&#x306e;&#x7372;&#x5f97;&#x30dd;&#x30a4;&#x30f3;&#x30c8;&#x4e0a;&#x4f4d;&#x8005;&#x3092;&#x512a;&#x5148;&#x3057;&#x3066;&#x9078;&#x51fa;&#x3092;&#x884c;&#x3044;&#x307e;&#x3059;&#x3002;<br>\n<br>\n&#x25a0;&#x7279;&#x5178;&#x3092;&#x8f9e;&#x9000;&#x3055;&#x308c;&#x305f;&#x65b9;&#x304c;&#x3044;&#x305f;&#x5834;&#x5408;&#x3001;&#x7e70;&#x4e0a;&#x3052;&#x53d7;&#x8cde;&#x3092;&#x884c;&#x3046;&#x3053;&#x3068;&#x3082;&#x3054;&#x3056;&#x3044;&#x307e;&#x3059;&#x306e;&#x3067;&#x3054;&#x4e86;&#x627f;&#x304f;&#x3060;&#x3055;&#x3044;&#x3002;<br>\n<br>\n&#x25a0;&#x500b;&#x4eba;&#x30a2;&#x30ab;&#x30a6;&#x30f3;&#x30c8;&#x3067;&#x306e;&#x3054;&#x53c2;&#x52a0;&#x304c;&#x5fc5;&#x9808;&#x306b;&#x306a;&#x308a;&#x307e;&#x3059;&#x3002;<br>\n<br>\n&#x25a0;&#x300e;&#x660e;&#x3089;&#x304b;&#x306a;&#x95a2;&#x4fc2;&#x8005;&#x3068;&#x308f;&#x304b;&#x308b;&#x30a2;&#x30ab;&#x30a6;&#x30f3;&#x30c8;&#x300f;&#x3084;&#x300e;&#x4e0d;&#x6b63;&#x3068;&#x307f;&#x306a;&#x3057;&#x305f;&#x30a2;&#x30ab;&#x30a6;&#x30f3;&#x30c8;&#x300f;&#x304b;&#x3089;&#x306e;&#x30ae;&#x30d5;&#x30c6;&#x30a3;&#x30f3;&#x30b0;&#x304a;&#x3088;&#x3073;Like&#x306f;&#x7121;&#x52b9;&#x3068;&#x3057;&#x3001;&#x30a4;&#x30d9;&#x30f3;&#x30c8;&#x671f;&#x9593;&#x4e2d;&#x3082;&#x3057;&#x304f;&#x306f;&#x30a4;&#x30d9;&#x30f3;&#x30c8;&#x7d42;&#x4e86;&#x5f8c;&#x306b;&#x6e1b;&#x7b97;&#x3055;&#x305b;&#x3066;&#x9802;&#x304f;&#x5834;&#x5408;&#x304c;&#x3054;&#x3056;&#x3044;&#x307e;&#x3059;&#x3002;<br>\n</p><p style=\"margin:10px;font-size:15px;\">\n<b>&#x203b;&#x300e;&#x660e;&#x3089;&#x304b;&#x306a;&#x95a2;&#x4fc2;&#x8005;&#x3068;&#x308f;&#x304b;&#x308b;&#x30a2;&#x30ab;&#x30a6;&#x30f3;&#x30c8;&#x300f;&#x306b;&#x3064;&#x3044;&#x3066;</b><br>\n<br>\n&#x4e3b;&#x306a;&#x4f8b;&#x3068;&#x3057;&#x3066;&#x4e0b;&#x8a18;&#x304c;&#x6319;&#x3052;&#x3089;&#x308c;&#x307e;&#x3059;&#x3002;<br>\n&#x30fb;&#x6240;&#x5c5e;&#x30b0;&#x30eb;&#x30fc;&#x30d7;&#x306e;&#x30e1;&#x30f3;&#x30d0;&#x30fc;&#x500b;&#x4eba;&#x30a2;&#x30ab;&#x30a6;&#x30f3;&#x30c8;<br>\n&#x30fb;&#x6240;&#x5c5e;&#x4e8b;&#x52d9;&#x6240;&#x306e;&#x30a2;&#x30ab;&#x30a6;&#x30f3;&#x30c8;&#x3082;&#x3057;&#x304f;&#x306f;&#x30b9;&#x30bf;&#x30c3;&#x30d5;&#x306e;&#x500b;&#x4eba;&#x30a2;&#x30ab;&#x30a6;&#x30f3;&#x30c8;<br>\n&#x30fb;&#x540c;&#x4e8b;&#x52d9;&#x6240;&#x6240;&#x5c5e;&#x306e;&#x5225;&#x30b0;&#x30eb;&#x30fc;&#x30d7;&#x306e;&#x30b0;&#x30eb;&#x30fc;&#x30d7;&#x30a2;&#x30ab;&#x30a6;&#x30f3;&#x30c8;&#x3082;&#x3057;&#x304f;&#x306f;&#x30e1;&#x30f3;&#x30d0;&#x30fc;&#x500b;&#x4eba;&#x30a2;&#x30ab;&#x30a6;&#x30f3;&#x30c8;&#x3000;&#x7b49;<br>\n<br>\n<b>&#x203b;&#x300e;&#x4e0d;&#x6b63;&#x3068;&#x307f;&#x306a;&#x3057;&#x305f;&#x30a2;&#x30ab;&#x30a6;&#x30f3;&#x30c8;&#x300f;&#x306b;&#x3064;&#x3044;&#x3066;</b><br>\n<br>\n&#x4e0d;&#x6b63;&#x30a2;&#x30ab;&#x30a6;&#x30f3;&#x30c8;&#x306e;&#x57fa;&#x6e96;&#x306b;&#x95a2;&#x3059;&#x308b;&#x304a;&#x554f;&#x3044;&#x5408;&#x308f;&#x305b;&#x306b;&#x3064;&#x304d;&#x307e;&#x3057;&#x3066;&#x306f;&#x3054;&#x8fd4;&#x7b54;&#x3044;&#x305f;&#x3057;&#x304b;&#x306d;&#x307e;&#x3059;&#x3002;<br>\n&#x5229;&#x7528;&#x898f;&#x7d04;&#x4e26;&#x3073;&#x306b;&#x30ac;&#x30a4;&#x30c9;&#x30e9;&#x30a4;&#x30f3;&#x3092;&#x3054;&#x78ba;&#x8a8d;&#x306e;&#x4e0a;&#x3001;&#x30df;&#x30af;&#x30c1;&#x30e3;&#x3092;&#x3054;&#x5229;&#x7528;&#x4e0b;&#x3055;&#x3044;&#x307e;&#x3059;&#x3088;&#x3046;&#x304a;&#x9858;&#x3044;&#x3044;&#x305f;&#x3057;&#x307e;&#x3059;&#x3002;\n</p>\n<ul>\n<li><a href=\"https://mixch.tv/help/terms.html\" target=\"_blank\" referrerpolicy=\"no-referrer\">&#x5229;&#x7528;&#x898f;&#x7d04;</a></li>\n<li><a href=\"https://mixch.tv/p/nfk6qvdb\" target=\"_blank\" referrerpolicy=\"no-referrer\">&#x30ac;&#x30a4;&#x30c9;&#x30e9;&#x30a4;&#x30f3;</a></li>\n</ul>\n<p style=\"margin:13px;font-size:15px;\">\n&#x25a0;&#x30e1;&#x30f3;&#x30d0;&#x30fc;&#x306e;&#x500b;&#x4eba;&#x30a2;&#x30ab;&#x30a6;&#x30f3;&#x30c8;&#x3067;&#x306e;&#x30b3;&#x30e1;&#x30f3;&#x30c8;&#x306f;&#x554f;&#x984c;&#x306a;&#x3044;&#x3067;&#x3059;&#x304c;&#x3001;&#x30ae;&#x30d5;&#x30c6;&#x30a3;&#x30f3;&#x30b0;&#x306f;NG&#x3068;&#x3055;&#x305b;&#x3066;&#x9802;&#x304d;&#x307e;&#x3059;&#x3002;&#x3082;&#x3057;&#x9593;&#x9055;&#x3063;&#x3066;&#x6295;&#x3052;&#x3066;&#x3057;&#x307e;&#x3063;&#x305f;&#x5834;&#x5408;&#x3001;&#x30a4;&#x30d9;&#x30f3;&#x30c8;&#x7d42;&#x4e86;&#x5f8c;&#x306b;&#x305d;&#x306e;&#x30dd;&#x30a4;&#x30f3;&#x30c8;&#x306f;&#x7121;&#x52b9;&#x3068;&#x306a;&#x308b;&#x3053;&#x3068;&#x304c;&#x3054;&#x3056;&#x3044;&#x307e;&#x3059;&#x3002;<br>\n<br>\n&#x25a0;&#x660e;&#x3089;&#x304b;&#x306a;&#x30a4;&#x30d9;&#x30f3;&#x30c8;&#x7d42;&#x4e86;&#x9593;&#x969b;&#x3067;&#x306e;&#x30a2;&#x30a4;&#x30c6;&#x30e0;&#x6e0b;&#x6ede;&#x306a;&#x3069;&#x306e;&#x60aa;&#x8cea;&#x306a;&#x59a8;&#x5bb3;&#x884c;&#x70ba;&#x304c;&#x78ba;&#x8a8d;&#x3055;&#x308c;&#x305f;&#x5834;&#x5408;&#x306f;&#x904b;&#x55b6;&#x306e;&#x5224;&#x65ad;&#x3067;&#x7279;&#x5225;&#x8cde;&#x306e;&#x5275;&#x8a2d;&#x306a;&#x3069;&#x5bfe;&#x5fdc;&#x3059;&#x308b;&#x5834;&#x5408;&#x304c;&#x3054;&#x3056;&#x3044;&#x307e;&#x3059;&#x306e;&#x3067;&#x516c;&#x5e73;&#x306a;&#x5fdc;&#x63f4;&#x3092;&#x304a;&#x9858;&#x3044;&#x81f4;&#x3057;&#x307e;&#x3059;&#x3002;\n<br>\n</p><div style=\"margin:10px;padding:5px;border:solid 2px #a89374;width:90%;text-align:left;\">\n<center>\n<p style=\"margin:13px;font-size:16px;\"><b><font color=\"red\">&#x26a0;&#xfe0f;&#x6295;&#x7a3f;&#x52d5;&#x753b;&#x306e;&#x6ce8;&#x610f;&#x4e8b;&#x9805;&#x26a0;&#xfe0f;</font></b></p></center>\n<p style=\"margin:13px;font-size:15px;\">\n&#x25c6;&#x6295;&#x7a3f;&#x3059;&#x308b;&#x52d5;&#x753b;&#x306f;<b>&#x201d;1&#x3064;&#x201d;&#x306e;&#x307f;</b>&#x3067;&#x304a;&#x9858;&#x3044;&#x3044;&#x305f;&#x3057;&#x307e;&#x3059;&#x3002;<br>\n<br>\n&#x25c6;&#x6295;&#x7a3f;&#x52d5;&#x753b;&#x3092;&#x524a;&#x9664;&#x3057;&#x3066;&#x518d;&#x6295;&#x7a3f;&#x3059;&#x308b;&#x3053;&#x3068;&#x306b;&#x95a2;&#x3057;&#x3066;&#x306f;&#x554f;&#x984c;&#x3054;&#x3056;&#x3044;&#x307e;&#x305b;&#x3093;&#x304c;&#x3001;&#x5be9;&#x67fb;&#x7d42;&#x4e86;&#x6642;&#x70b9;&#x3067;&#x5bfe;&#x8c61;&#x5916;&#x306e;&#x52d5;&#x753b;&#x6295;&#x7a3f;&#x304c;&#x767a;&#x899a;&#x3057;&#x305f;&#x5834;&#x5408;&#x306f;&#x3001;&#x300c;&#x2461;&#x52d5;&#x753b;Like&#x5be9;&#x67fb;&#x300d;&#x306b;&#x95a2;&#x3057;&#x3066;&#x306f;&#x96c6;&#x8a08;&#x5bfe;&#x8c61;&#x5916;&#x3068;&#x3055;&#x305b;&#x3066;&#x3044;&#x305f;&#x3060;&#x304d;&#x307e;&#x3059;&#x306e;&#x3067;&#x3054;&#x6ce8;&#x610f;&#x304f;&#x3060;&#x3055;&#x3044;&#x3002;<br>\n<small>&#x203b;&#x5be9;&#x67fb;&#x671f;&#x9593;&#x4e2d;&#x306b;&#x524a;&#x9664;&#x3057;&#x305f;&#x52d5;&#x753b;&#x3067;&#x7372;&#x5f97;&#x3057;&#x305f;&#x30dd;&#x30a4;&#x30f3;&#x30c8;&#x6570;&#x306b;&#x95a2;&#x3057;&#x3066;&#x306f;&#x5be9;&#x67fb;&#x96c6;&#x8a08;&#x306e;&#x5bfe;&#x8c61;&#x3068;&#x3044;&#x305f;&#x3057;&#x307e;&#x3059;&#x3002;</small><br>\n<br>\n&#x25c6;&#x6295;&#x7a3f;&#x52d5;&#x753b;&#x3092;&#x524a;&#x9664;&#x3057;&#x3066;&#x518d;&#x6295;&#x7a3f;&#x3057;&#x305f;&#x5834;&#x5408;&#x3001;Like&#x6570;&#x306f;&#x30ea;&#x30bb;&#x30c3;&#x30c8;&#x3055;&#x308c;&#x308b;&#x305f;&#x3081;&#x3054;&#x6ce8;&#x610f;&#x304f;&#x3060;&#x3055;&#x3044;&#x3002;<br>\n<br>\n&#x25c6;&#x52d5;&#x753b;&#x306b;&#x306f;&#x6295;&#x7a3f;&#x8005;&#x672c;&#x4eba;&#x304c;&#x5fc5;&#x305a;&#x6620;&#x308b;&#x3088;&#x3046;&#x304a;&#x9858;&#x3044;&#x3044;&#x305f;&#x3057;&#x307e;&#x3059;&#x3002;<br>\n<br>\n&#x25c6;&#x300c;&#x2461;&#x52d5;&#x753b;Like&#x5be9;&#x67fb;&#x300d;&#x306e;&#x5bfe;&#x8c61;&#x3068;&#x306a;&#x308b;&#x52d5;&#x753b;&#x306f;&#x4e0b;&#x8a18;A&#x301c;C&#x3092;&#x5168;&#x3066;&#x6e80;&#x305f;&#x3057;&#x305f;1&#x52d5;&#x753b;&#x306e;&#x307f;&#x3068;&#x306a;&#x308a;&#x307e;&#x3059;&#x3002;<br>\n<br>\n<font color=\"red\"><b>A.&#x5be9;&#x67fb;&#x671f;&#x9593;&#x4e2d;&#x306b;&#x6295;&#x7a3f;&#x3055;&#x308c;&#x3066;&#x3044;&#x308b;&#x3002;<br>\n<br>\nB.&#x201d;1&#x3064;&#x306e;&#x307f;&#x201d;&#x3068;&#x306a;&#x3063;&#x3066;&#x3044;&#x308b;&#x3002;<br>\n<br>\nC.&#x6295;&#x7a3f;&#x6642;&#x306b;&#x300c;TIF2026&#xd7;andGIRL &#x30d3;&#x30e5;&#x30fc;&#x30c6;&#x30a3;&#x30fc;&#x30df;&#x30e5;&#x30fc;&#x30ba;&#x30aa;&#x30fc;&#x30c7;&#x30a3;&#x30b7;&#x30e7;&#x30f3;&#x300d;&#x306e;&#x30a4;&#x30d9;&#x30f3;&#x30c8;&#x9078;&#x629e;&#x304c;&#x3055;&#x308c;&#x3066;&#x3044;&#x308b;&#x3002;</b></font><br>\n<br>\n<small>&#x203b;&#x5be9;&#x67fb;&#x7d42;&#x4e86;&#x6642;&#x70b9;&#x3067;&#x4e0a;&#x8a18;&#x4ee5;&#x5916;&#x306e;&#x6295;&#x7a3f;&#x304c;&#x767a;&#x899a;&#x3057;&#x305f;&#x5834;&#x5408;&#x306f;&#x3001;&#x4e0a;&#x8a18;A&#x301c;C&#x3092;&#x3059;&#x3079;&#x3066;&#x6e80;&#x305f;&#x3057;&#x305f;&#x52d5;&#x753b;&#x304c;&#x6295;&#x7a3f;&#x3055;&#x308c;&#x3066;&#x3044;&#x305f;&#x5834;&#x5408;&#x3067;&#x3082;&#x5168;&#x3066;&#x5be9;&#x67fb;&#x5bfe;&#x8c61;&#x5916;&#x3068;&#x306a;&#x308a;&#x307e;&#x3059;&#x306e;&#x3067;&#x4e88;&#x3081;&#x3054;&#x4e86;&#x627f;&#x304f;&#x3060;&#x3055;&#x3044;&#x3002;</small><br>\n<br>\n&#x25c6;&#x697d;&#x66f2;&#x3092;&#x4f7f;&#x7528;&#x3059;&#x308b;&#x5834;&#x5408;&#x306f;&#x8457;&#x4f5c;&#x6a29;&#x8005;&#x304b;&#x3089;&#x697d;&#x66f2;&#x5229;&#x7528;&#x306e;&#x8a31;&#x53ef;&#x304c;&#x304a;&#x308a;&#x3066;&#x3044;&#x308b;&#x3082;&#x306e;&#x3092;&#x304a;&#x4f7f;&#x3044;&#x304f;&#x3060;&#x3055;&#x3044;&#x3002;<br>\n<br>\n&#x25c6;&#x30df;&#x30af;&#x30c1;&#x30e3;&#x4ee5;&#x5916;&#x306e;&#x30d7;&#x30e9;&#x30c3;&#x30c8;&#x30d5;&#x30a9;&#x30fc;&#x30e0;&#x3067;&#x4f5c;&#x6210;&#x3057;&#x305f;&#x52d5;&#x753b;&#x3092;&#x30df;&#x30af;&#x30c1;&#x30e3;&#x3067;&#x30a2;&#x30c3;&#x30d7;&#x30ed;&#x30fc;&#x30c9;&#x3059;&#x308b;&#x5834;&#x5408;&#x3001;&#x5f53;&#x8a72;&#x30d7;&#x30e9;&#x30c3;&#x30c8;&#x30d5;&#x30a9;&#x30fc;&#x30e0;&#x306e;&#x5229;&#x7528;&#x898f;&#x7d04;&#x306b;&#x6cbf;&#x3063;&#x3066;&#x6295;&#x7a3f;&#x3057;&#x3066;&#x304f;&#x3060;&#x3055;&#x3044;&#x3002;<br>\n<br>\n&#x25c6;&#x6295;&#x7a3f;&#x3055;&#x308c;&#x305f;&#x52d5;&#x753b;&#x306f;&#x3001;&#x4e07;&#x4e00;&#x7b2c;&#x4e09;&#x8005;&#x304b;&#x3089;&#x306e;&#x6a29;&#x5229;&#x4fb5;&#x5bb3;&#x7b49;&#x306e;&#x7533;&#x3057;&#x7acb;&#x3066;&#x304c;&#x3042;&#x3063;&#x305f;&#x5834;&#x5408;&#x306b;&#x306f;&#x3001;&#x6295;&#x7a3f;&#x8005;&#x3054;&#x81ea;&#x8eab;&#x3082;&#x3057;&#x304f;&#x306f;&#x6240;&#x5c5e;&#x4e8b;&#x52d9;&#x6240;&#x306e;&#x8cac;&#x4efb;&#x3092;&#x3082;&#x3063;&#x3066;&#x89e3;&#x6c7a;&#x3057;&#x3066;&#x3044;&#x305f;&#x3060;&#x304d;&#x307e;&#x3059;&#x306e;&#x3067;&#x3001;&#x4e88;&#x3081;&#x3054;&#x4e86;&#x627f;&#x304f;&#x3060;&#x3055;&#x3044;&#x3002;<br>\n<br>\n&#x25c6;&#x52d5;&#x753b;&#x306e;&#x9332;&#x97f3;&#x72b6;&#x614b;&#x3084;&#x753b;&#x8cea;&#x3001;&#x30d5;&#x30a1;&#x30a4;&#x30eb;&#x306e;&#x30d5;&#x30a9;&#x30fc;&#x30de;&#x30c3;&#x30c8;&#x306b;&#x3088;&#x3063;&#x3066;&#x306f;&#x5f0a;&#x793e;&#x904b;&#x55b6;&#x3088;&#x308a;&#x64ae;&#x308a;&#x76f4;&#x3057;&#x3001;&#x307e;&#x305f;&#x306f;&#x30d5;&#x30a9;&#x30fc;&#x30de;&#x30c3;&#x30c8;&#x306e;&#x5909;&#x63db;&#x7b49;&#x3092;&#x304a;&#x9858;&#x3044;&#x3092;&#x3059;&#x308b;&#x3053;&#x3068;&#x3082;&#x3054;&#x3056;&#x3044;&#x307e;&#x3059;&#x306e;&#x3067;&#x3001;&#x4e88;&#x3081;&#x3054;&#x4e86;&#x627f;&#x304f;&#x3060;&#x3055;&#x3044;&#x3002;<br>\n</p></div>\n<br>\n\n\n\n<br><center><img src=\"https://d2uqarpmf42qy0.cloudfront.net/event/NIKU/mixch_LOGO.png\" width=\"15%\"></center><br>\n\n</div>\n</div>\n\n<!-- 2タブの中身おわり💡 -->\n\n<!--css start -->\n\n<style type=\"text/css\">.main-content { max-width: 480px; color: rgb(0, 0, 0); background: url(\"https://d2uqarpmf42qy0.cloudfront.net/event/41haba/TIF_haikei.png\") center top / 100% repeat rgba(255, 255, 255, 0.5); }\n.tab-content label { display: inline-block; padding: 5px; font-weight: bold; font-size: 15px; color: rgb(209, 43, 52); cursor: pointer; border-radius: 5px 5px 0px 0px; box-sizing: border-box; border-width: 2px 2px medium; border-style: solid solid none; border-color: rgb(209, 43, 52) rgb(209, 43, 52) currentcolor; border-image: initial; background-color: rgba(255, 242, 247, 0.7); }\n.tab-content label:hover { opacity: 0.5; }\n.tab-content input[type=\"radio\"]:checked + label { color: rgb(255, 255, 255); background-color: rgb(209, 43, 52); border-width: 2px 2px medium; border-style: solid solid none; border-color: rgb(209, 43, 52) rgb(209, 43, 52) currentcolor; border-image: initial; }\n.tab-content .tab-box { width: 100%; height: auto; padding: 10px; box-sizing: border-box; border-radius: 15px; }\n.tab-content > .tab-box > div { display: none; }\n.box1 { height: auto; padding: 0px; background-color: rgb(255, 251, 240); color: rgb(255, 255, 255); border: 2.5px solid rgb(255, 187, 0); position: relative; margin: 2em; }\n.box2 { height: auto; padding: 0px; background-color: rgb(255, 255, 255); color: rgb(0, 0, 0); border: 2.5px solid rgb(240, 84, 116); position: relative; margin: 2em; }\n.tab-content > .tab-box > div { display: none; }\n#tab1:checked ~ .tab-box > #tabView1, #tab2:checked ~ .tab-box > #tabView2, #tab3:checked ~ .tab-box > #tabView3, #tab4:checked ~ .tab-box > #tabView4, #tab5:checked ~ .tab-box > #tabView5 { display: block; background-color: rgba(255, 242, 247, 0.2); }\ndiv.content { color: rgb(101, 221, 206); line-height: 1.75; font-size: 15px; margin: 20px 0px; }\n.tab-box h3.logo { margin: 0px 15px 10px; padding: 15px 5px 10px; color: rgb(209, 43, 52); background-image: linear-gradient(120deg, rgb(209, 43, 52) 10%, rgb(209, 43, 52) 100%); background-repeat: no-repeat; background-size: 88% 2px; background-position: 0px 100%; line-height: 2em; }\n.tab-box h3.logo::before { background: url(\"https://d2uqarpmf42qy0.cloudfront.net/event/25_hatamura/img/common/mixcha-logo-white-outline-512x512px.png\") center center / contain no-repeat rgb(209, 43, 52); display: inline-block; margin: 0px 5px 0px 0px; content: \"\"; width: 2em; height: 2em; vertical-align: middle; line-height: 2em; border-radius: 7px; padding: 0px; }\n#tabView1, #tabView2, #tabView3, #tabView4, #tabView5 { background-color: rgb(255, 255, 255); }\n.tab-box p { margin: 10px; }\n.box_gold { position: relative; margin: 0.3em; border: 3px solid rgb(101, 221, 206); color: rgb(101, 221, 206); }\n.tab-content input[type=\"radio\"] { display: none; }\ndiv.content ul { padding: 0px 2em 0px 3em; }\ndiv.content table { padding: 5px 2em; }\ndiv.content table tr { line-height: 1.5; }\ndiv.content table tr { vertical-align: bottom; }\ndiv.content table th { font-weight: bold; text-align: left; }\ndiv.button-container { margin: 20px 20px 30px; font-size: 16px; font-weight: bold; text-align: center; }\ndiv.button-container img { display: inline-block; }\n.precaution { line-height: 1.25; color: rgb(96, 96, 96); margin-bottom: 20px; }\ndiv.content div.judges, div.content div.yad-members { padding: 0px 40px; }\ndiv.content div.judges h4 { font-size: 16px; font-weight: bold; border-bottom: 1px solid rgb(128, 128, 128); margin: 40px 20px 10px; }\ndiv.content div.yad-members h4 { font-size: 16px; font-weight: bold; margin: 40px 20px 10px; }\ndiv.content div.judges .portrait, div.content div.yad-members .portrait { text-align: center; }\ndiv.content div.judges .portrait img, div.content div.yad-members .portrait img { width: 160px; display: inline-block; margin: 5px 0px; }\ndiv.content img.footer-logo { width: 20%; margin: 0px auto; padding: 40px 0px; display: block; }\ndiv.content div.yad-members h5 { font-size: 15px; font-weight: bold; margin: 5px 20px 0px; }\ndiv.content a.link-btn, div.content a.link-btn:link, div.content a.link-btn:visited { margin: 5px 0px; display: inline-block; padding: 5px 10px; border: 2px solid rgb(209, 43, 52); border-radius: 70px; transition: 0.125s; text-decoration: none; font-size: 15px; font-weight: bold; line-height: 1.5; color: rgb(209, 43, 52); }\ndiv.content a.link-btn > span, div.content a.link-btn:link > span, div.content a.link-btn:visited > span { color: rgb(209, 43, 52); transition: 0.125s; font-size: 20px; }\ndiv.content a.link-btn:hover { background-color: rgb(209, 43, 52); color: rgb(255, 255, 255); }\ndiv.content a.link-btn:hover > span { color: rgb(0, 0, 0); }\ndiv.content a.link-btn:active {\n  background-color: rgb(209, 43, 52); box-shadow: rgba(0, 0, 0, 0) 0px 0px 0px; transition: all;\n  & strong { text-align: center; background: linear-gradient(transparent 80%, rgb(178, 17, 149) 80%); }\n  & .button_p { margin: 10px; padding: 5px; background-color: rgb(101, 221, 206); text-align: center; color: rgb(255, 255, 255); font-size: 12px; font-weight: bold; border-radius: 30px; border: 4px outset rgb(101, 221, 206); }\n  & div.content div.apply-button-container { max-width: 480px; float: left; position: fixed; width: 100%; font-weight: bold; top: 0px; text-align: center; background-color: rgba(255, 255, 255, 0.75); backdrop-filter: blur(8px); z-index: 1; box-shadow: rgba(0, 0, 0, 0.66) 0px 2px 4px; }\n  & div.content div.apply-button-container img { max-width: 116px; margin: 0px 0px 8px; }\n}\n</style>\n\n<!-- css end -->\n\n<p></p></div>\n</div>\n</div><p></p>\n</div>",
  "ogDescription": "開催期間 2026/06/29 12:00 ~ 2026/07/08 22:00",
  "bannerImageUrl": "https://d2uqarpmf42qy0.cloudfront.net/torte/event/24234/banner.png"
}