{
  "profileId": "18813342",
  "currentName": "莨願陸髮幄脅(縺吶∪)宖瀬窶ｪ宖酷JC繝溘せ繧ｳ繝ｳ",
  "nameHistory": [
    {
      "name": "莨願陸髮幄脅(縺吶∪)宖瀬窶ｪ宖酷JC繝溘せ繧ｳ繝ｳ",
      "firstSeenAt": "2026-07-09T13:44:53.466Z",
      "lastSeenAt": "2026-07-09T14:39:29.973Z"
    }
  ],
  "profileUrl": "https://mixch.tv/u/18813342",
  "iconUrl": "https://d2jtsb989t238a.cloudfront.net/p/18813342/1773657342/small",
  "firstSeenAt": "2026-07-09T13:44:53.466Z",
  "lastSeenAt": "2026-07-09T14:39:29.973Z",
  "eventKeys": [
    "24294_20260706_20260712"
  ]
}