{
  "profileId": "18867524",
  "currentName": "京生7/8最終美🍒🐨#ｶﾚｯｼﾞ",
  "nameHistory": [
    {
      "name": "京生7/8最終美🍒🐨#ｶﾚｯｼﾞ",
      "firstSeenAt": "2026-07-08T14:09:46.855Z",
      "lastSeenAt": "2026-07-08T14:09:46.855Z"
    }
  ],
  "profileUrl": "https://mixch.tv/u/18867524",
  "iconUrl": "https://d2jtsb989t238a.cloudfront.net/p/18867524/1782064292/small",
  "firstSeenAt": "2026-07-08T14:09:46.855Z",
  "lastSeenAt": "2026-07-08T14:09:46.855Z",
  "eventKeys": [
    "24237_20260629_20260709"
  ]
}