{
  "profileId": "18890522",
  "currentName": "гВКгБУвЪЊпЄПрЯОІж•ље§©еІЛзРГеЉПгВ§гГЩ",
  "nameHistory": [
    {
      "name": "гВКгБУвЪЊпЄПрЯОІж•ље§©еІЛзРГеЉПгВ§гГЩ",
      "firstSeenAt": "2026-07-08T14:09:20.608Z",
      "lastSeenAt": "2026-07-08T14:09:20.608Z"
    }
  ],
  "profileUrl": "https://mixch.tv/u/18890522",
  "iconUrl": "https://d2jtsb989t238a.cloudfront.net/p/18890522/1780589948/small",
  "firstSeenAt": "2026-07-08T14:09:20.608Z",
  "lastSeenAt": "2026-07-08T14:09:20.608Z",
  "eventKeys": [
    "24305_20260705_20260713"
  ]
}