{
  "profileId": "18908399",
  "currentName": "銀座から日本ワインを発信🍷🇯🇵あきほっち",
  "nameHistory": [
    {
      "name": "銀座から日本ワインを発信🍷🇯🇵あきほっち",
      "firstSeenAt": "2026-07-08T14:09:10.083Z",
      "lastSeenAt": "2026-07-08T14:09:10.083Z"
    }
  ],
  "profileUrl": "https://mixch.tv/u/18908399",
  "iconUrl": "https://d2jtsb989t238a.cloudfront.net/p/18908399/1781151571/small",
  "firstSeenAt": "2026-07-08T14:09:10.083Z",
  "lastSeenAt": "2026-07-08T14:09:10.083Z",
  "eventKeys": [
    "24289_20260701_20260713"
  ]
}