{
  "eventKey": "24151_20260701_20260713",
  "eventId": "24151",
  "eventUrl": "https://mixch.tv/live/event/24151",
  "title": "「音楽と食の祭典 埼玉 MUSIC&FOOD FESTIVAL 2026」ステージ出演＆パンフレット掲載オーディション",
  "startAt": "2026-07-01T18:00:00+09:00",
  "endAt": "2026-07-13T00:00:00+09:00",
  "detailCapturedAt": "2026-07-08T14:04:55.358Z",
  "detailHash": "27dbbf5b5846ae188ce235dad44f084b9183331632680671c140fe1d4994f57c",
  "rawText": "イベント概要\n8/8～8/9、川口文化総合センター・リリアで開催される\n\n \n【音楽と食の祭典】\n\n埼玉 MUSIC&FOOD\n\nFESTIVAL 2026 \n\nそのステージ出演やパンフレット掲載をかけたオーディションを開催✨\n\n多くのアイドルやアーティストが出演するステージに立ち、あなたの魅力を発揮するチャンス！\n\n聴いて楽しみ、食べて楽しみながら、フェスを盛り上げよう🔥\n\n皆様のご参加をお待ちしております💛\n\n【音楽と食の祭典】\n\n　　　 埼玉 MUSIC&FOOD FESTIVAL 2026\n聴いて楽しみ、食べて楽しみ・・・埼玉県にて食と音楽のフェスを開催。\n\n【音楽と食の祭典】埼玉MUSIC&FOOD FESTIVALは、アイドルによるライブイベントと物産展を行う食と音楽の祭典です。\n\n本イベントは2025年に大宮・川口・所沢で3回開催、大盛況につき4回目の開催が決定いたしました。\n\n JR川口駅西口直結という抜群のアクセス性を誇る川口文化総合センター・リリアは、駅利用者・買い物客・地域住民など、平日・週末を問わず多くの人々が行き交う川口市の中核エリアです。\n\nそんな川口にある川口文化総合センター・リリアにて【音楽と食の祭典】埼玉MUSIC&FOODFESTIVAL2026を開催いたします。\n\n食べ物と音楽を通じて、それぞれの魅力を味わい、体験しましょう。\n\n開催場所：川口文化総合センター・リリア\n \n\n \n \n \n \n \n 【音楽と食の祭典】埼玉MUSIC&FOOD FESTIVAL\n公式Webサイト \n \n \n 【音楽と食の祭典】埼玉MUSIC&FOOD FESTIVAL\n公式X\n\n埼玉美少女図鑑\n「美少女図鑑」は全国に展開し、その地元の美少女を取り上げていく地域密着型のメディアです。\n\nこの地域性という強みと、フリーペーパー・SNS・ライブ配信といった多岐にわたる媒体を駆使し、\n\nこれまでに「二階堂ふみ」「山本舞香」「桜井日奈子」「馬場ふみか」をはじめとする国民的女優を数多く輩出してきました。\n\n各地方でそれぞれの形で盛り上がりを見せてきた『美少女図鑑』。\n\n埼玉ならではの美少女を発掘しながら、様々なメディア提携などを仕掛けて\n埼玉の中での『美少女図鑑』を大きくしていきます。\n\n \n 埼玉美少女図鑑 公式HP\n\n参加条件\n本イベントはソロアカウントのみ参加できるイベントです。\n\n原則、本イベントに関しては、\n\n■顔出しできる方、イベント当日にご参加いただける方のみご応募ください。\n\n■未成年の方は保護者の同意が必要です。\n\n■1アカウントにつき1名でご参加ください。\n\n■当イベントは配信者報酬がございます。\n\n■HP・SNS・『美少女図鑑』が管理・発信する媒体にて肖像の露出が可能な方のみご応募ください。\n\n■特定の芸能事務所やプロダクションへの所属有無は問いません。必要な場合はご自身で許可をお取りいただくよう、お願いいたします。\n\n \n \n \nこのイベントでは\n\n ライブ配信 +ムービー 合算 \n\nのポイントがランキングに表示されます！\n \n\n \n \n\n※入賞者へのお知らせは、 ミクチャアプリ内の「あなたへのお知らせ」に届きます ので、必ずご確認ください。\n\n募集中の最新イベントのご案内始めました\n✉毎週水曜と金曜日に更新✉ \n\n 友だち追加で募集中のイベント情報が送られてくるよ！\n\nあなたにぴったりのイベントがきっと見つかるはず👍\n\n審査について\n●ライブ配信・動画投稿をする際は必ず [ 「音楽と食の祭典 埼玉 MUSIC&FOOD FESTIVAL 2026」ステージ出演＆パンフレット掲載オーディション ]のイベント選択 をお願いします。正しく選択をしていない場合は獲得したミクチャポイントがランキングに反映されませんのでご注意ください。また、誤ってイベント選択した際にポイントを対象イベントに反映することはできかねますので予めご了承ください。\n\n●当該ページの審査項目に沿って受賞者が決定いたします。なお、審査の過程や受賞者の決定に至った理由等につきましてはお答え出来ませんのであらかじめご了承ください。\n\n●獲得したポイントが同一の場合は、下記の条件に従って順位を決定します。((1)から条件を適用し、順位が決定しない場合はその次の条件を適用して決定し、以下同様の処理をします。)\n\n \n　(1) 対象となるイベントを選択してライブ配信をした「配信時間」の合計が多いユーザーを上位とします。\n\n　(2) 対象となるイベントを選択してライブ配信をした「配信回数」の合計が多いユーザーを上位とします。\n\n　(3) 対象となるイベントを選択して行ったライブ配信・投稿動画に対して受け取った「コメント数」の合計が多いユーザーを上位とします。\n\n　(4) 対象となるイベントへの応募申し込みが早かったユーザーを上位とします。\n\n　(5) もし(1)～(5)全てが同じ場合はミクチャの「ユーザーIDの数字が小さい」ユーザーを上位とします。\n\n \n\n ※下記の注意事項も必ずお読みください。\n\nアイテム送信に関する注意点\n●ライブ配信で、イベント終了間際など同時間帯に大量のアイテムを投げると、多数のアイテムリクエストによりコイン消費に遅延が生じる可能性がございます。ムービーでは遅延が生じることはないので、ムービーイベントの場合は投稿動画への積極的な送信をご検討ください。\n\n●ライブ配信の場合、イベント期間中にライバーの端末側でアイテムのアニメーション再生が始まったアイテムはイベントのポイントに加算されます。イベント期間中に再生失敗したアイテムやイベント期間をすぎてから再生されたアイテムは、イベントのポイントに加算されません。\n\n●なお、上記の事象が発生した場合においても、イベントへのポイント反映やコインの返却などのご対応は出来かねますのでご了承くださいませ。\n\nそのため、ライブ配信ではできるだけ一気に大量に送るのではなく、定期的にアイテムを送るかムービーへのアイテム送信を推奨いたします。\n\n応募規約\n本キャンペーンに応募いただける方（以下、「応募者」といいます。）は、以下をよくお読みいただき、同意の上ご応募ください。\n\nミクチャにて、「イベントに参加する」をタップした時点で本規約に同意したものとみなします。万が一ご同意いただけない場合は応募を中止してください。\n\n本規約の内容は、事前の告知なく変更される場合がありますので、予めご了承ください。\n\n \n　▪️動画投稿・ライブ配信での注意事項\n\n \n●撮影・ライブ配信が禁止されている場所または危険な場所での撮影やライブ配信はお控え下さい。\n\n●楽曲を使用する場合は著作権者から楽曲利用の許可がおりているものをお使いください。\n\n●大声を出す・大音量で音楽を流す、道を塞ぐなど、人の迷惑になる行為は控えて、撮影やライブ配信を実施してください。\n\n \n●応募者と一緒に投稿動画・ライブ配信に写っている方がいらっしゃる場合や、第三者の知的財産権が含まれる場合、必ず投稿やライブ配信前に権利者から使用許諾を得てください。\n\nまた、応募者は投稿動画・ライブ配信について自らが投稿・ライブ配信することについての適法な権利を有していること及び第三者の一切の権利を侵害していないことについて当社に対し表明し、保証するものとします。万が一、第三者からの権利侵害等の申し立てがあった場合には、投稿者や配信者ご自身の責任をもって解決していただきますので、予めご了承ください。\n\n●ミクチャ以外のプラットフォームで作成した動画をミクチャでアップロードする場合、当該プラットフォームの利用規約に沿って投稿してください。\n\n●未成年の方は保護者の同意を得た上でご応募ください。また、必要に応じて、在籍する学校または所属する部活動が加盟する連盟等へ確認をとったうえで応募してください。\n\n●事務所、劇団、その他の団体（以下「事務所等」といいます）に所属されている方は、ご自身の責任で事務所等に本キャンペーンへの応募の可否につきご確認ください。\n\n●コンテストなどの新しい才能の発掘を目的としたものや、事務所所属者や新グループメンバーの選定を目的とした一般的な「オーディション」に関するイベントには、キャッシュバックのお支払いはございません。なお、一部対象外のものもございますので、ご不明な場合はお問い合わせください。\n\n●上記各項への違反や極端に他人に不快感を与えるような言動や、法律に抵触する内容、ミクチャの利用規約に違反した内容、運営事務局が不適切と判断した動画やライブ配信については削除、もしくはキャッシュバックや審査、受賞の対象外とする可能性がございますのでご了承ください。\n\n●本応募規約に定める事項のほか、ミクチャ利用規約及びプライバシーポリシーが適用されますので、確認の上、ご応募ください。\n\n \n　▪️賞品・受賞について\n\n \n●受賞者と連絡がつかない場合、賞品受領の意思が確認できない場合、指定された期日までに連絡先をご返信いただけない場合等には、受賞を辞退されたものとみなし、受賞を無効とさせていただきます。予めご了承ください。\n\n●受賞の権利は受賞者ご本人のものであって、第三者へ譲渡・換金等することはできません。また、受領した賞品の紛失等による再送付、受賞者の事情による変更、その他クレーム等には一切応じることができません。\n\n●当社は、賞品の品質及び、目的適合性について何ら保証することはできかねます。賞品の使用に当たっては、賞品に記載の注意事項をご確認の上、ご使用ください。受賞された賞品の使用中に生じた事故等のトラブルについての責任は、当社では負いかねます。\n\n●賞品提供元の何らかの事由により特典不履行となる事案が生じた場合は、代替賞品による補填などで対応することがございますのでご了承くださいませ。\n\n \n　▪️禁止事項\n\n \n本キャンペーンへの応募に際し、以下の行為を禁止します。当社は、応募者が以下に該当する行為を行ったと判断した場合は、応募者への事前通告なく、対象投稿を掲載しない、掲載後削除する、応募・受賞を無効とするなどの対応をとる場合があります。\n\n・本規約または法令に違反する行為\n\n・本キャンペーンの運営を妨げる行為\n\n・他人に迷惑、不利益、損害または不快感を与える行為\n\n・他人を誹謗中傷し、またはその名誉若しくは信用を毀損する行為\n\n・第三者の著作権その他の知的財産権を侵害する行為\n\n・他人の財産、プライバシー若しくは肖像権を侵害する行為\n\n・わいせつ、児童ポルノ及び児童の性的搾取を助長するデータを投稿する行為\n\n・営利を目的とした情報提供、広告宣伝もしくは勧誘行為\n\n・公序良俗に反する行為\n\n・ミクチャの利用規約に違反する行為\n\n・その他、前各号に類する行為\n\n \n　▪️免責・その他\n\n \n本キャンペーンは、細心の注意を払って運営をしていますが、提供する情報、プログラム、各種サービス、その他本キャンペーンに関するすべての事項について、その完全性、正確性、安全性、有用性等について、いかなる保証もするものではありません。また、利用者または第三者が被った以下の事例を含む損害については、当社は責任を負いかねます。\n\n1.本キャンペーンへの応募に際して、ソフトウェア・ハードウェア上の事故、火災、停電、通信環境の悪化、地震、事変等の非常事態が発生した場合。\n\n2.本キャンペーンにおけるシステムの保守を定期的あるいは緊急に行う場合。\n\n3.利用者間または利用者と第三者の間におけるトラブル等が生じた場合。\n\n4.第三者による本キャンペーンのサービスの妨害、情報改変などによりサービスが中断もしくは遅延し、何らかの欠陥が生じた場合。\n\n5.当社が推奨する環境以外から本キャンペーンに応募したために情報を完全に取得できない場合。\n\n6.故意または重過失なくして本キャンペーンが提供する情報が誤送信されるか、もしくは欠陥があった場合。\n\n当社は、本キャンペーンの応募により応募者に生じた一切のトラブル・損害（直接・間接を問いません）について、如何なる責任も負いません。\n\n本キャンペーンの応募にかかるインターネット接続料及び通信費は応募者のご負担となります。\n\n本キャンペーンは、ミクチャを提供している当社（株式会社Donuts）が運営しているものであり、Apple社によって提供されているものではございません。\n\n \n　▪️個人情報の取り扱いについて\n\n \n住所、電話番号、氏名、性別、年齢、ミクチャアカウントURLの情報（以下「個人情報」といいます。）は、株式会社Donutsが管理します（管理責任者：ミクチャグループリーダー）。お客様の個人情報は、本キャンペーンの当選者への連絡・賞品の送付等の目的で利用し、それ以外の目的では使用致しません。また、お客様の個人情報をお客様の同意なしに業務委託先以外の第三者に開示・提供することはありません（法令等により開示を求められた場合を除きます。）。\n\nまた、個人情報開示、訂正等のお問い合わせは、ミクチャ運営事務局（mixch-support@donuts.ne.jp）までお願い致します。\n\n \n　▪️キャンペーンに関するお問い合わせ窓口\n\n \n[ミクチャスポンサー事務局]\n\nmixch-support@donuts.ne.jp\n\nスケジュール\n募集期間 \n\n \n　　6/19(金)18:00～7/12(日)24:00\n\n \n 本選期間 \n\n \n　　7/1(水)18:00～7/12(日)24:00\n\n \n 結果発表 \n\n \n　　7/13(月)\n\n \n 撮影 \n\n \n　　7/21(火) 17:00~20:00の間の1~2時間\n\n　　@都内予定\n\n \n 音楽と食の祭典\n埼玉 MUSIC&FOOD FESTIVAL \n\n \n　　出演：8/9(日)\n\n本選特典\n🥇ポイントランキング1位 \n\n \n \n\n \n イベントアンバサダーとして\n ステージ出演権を獲得！ \n\n↪ 🎤歌・ダンス披露💃 \nまたは\n トークショー✨\n を選択可能！\n\n \n\n 📚パンフレット表紙掲載 \n（撮影あり）\n\n交通費上限2万円支給 \n\n 🥈ポイントランキング2位 \n\n \n \n イベントアンバサダーとして\n トークショーステージ \n出演権を獲得！ \n\n \n\n 📚パンフレット中面1/2ページ掲載 \n（データ提出）\n\n50万pt達成で\n交通費上限1万円支給 \n\n 🏅審査員特別賞(3~5位から1名) \n\n \n \n イベントアンバサダーとして\n トークショーステージ \n出演権を獲得！ \n\n \n\n 📚パンフレット中面1/2ページ掲載 \n（データ提出）\n\n50万pt達成で\n交通費上限1万円支給\n\n特典に関する注意事項\nステージ出演に関して\n \n \n・ステージ出演内容（歌・ダンス披露またはトークショー）は、ポイントランキング1位の方のみが選択できます。\n\n・ポイントランキング2位および審査員特別賞受賞者の出演形式はトークショーとなります。\n\n・ステージ出演は8/9(日) 10~13時のうち10分間になります。\n\n1位の方が「歌・ダンス披露」を選択した場合、\n\n1位：単独で5分間の歌・ダンス披露\n\n2位・審査員特別賞：2名で5分間のトークショー出演\n\n1位の方が「トークショー」を選択した場合、\n\n1位・2位・審査員特別賞で、10分間のトークショー出演\n\nとなります。予めご了承ください。\n\n \n提出データに関して\n \n \n・ポイントランキング2位、審査員特別賞の方につきましては、7月20日までにデータの提出をお願い致します。\n\n・ 5MB以上、バストアップで1枚 の画像データをご提出くださいますようお願いいたします。\n\n・ポイントランキング2位、審査員特別賞の方は撮影がございません。予めご了承ください。\n\n \nその他注意事項\n \n \n・ステージ出演の際、受賞者3名の内撮影NGの方がいた場合、客席からの撮影が不可となる場合もあります。予めご了承ください。\n\n・1位の方のステージ出演内容は結果発表日から5日後までに選択いただきます。それ以上経過してもご連絡がない場合は運営側で決めさせていただきます。\n\n・トークショーはMC2名と受賞者で実施いたします。内容はイベント主催側で決めさせていただきます。\n\n・撮影、ステージ出演共に、衣装やへアイメイクなどはご自身での準備となります。\n\n・当日リハーサルがございます。\n\n・20時以降の出演はございません。\n\n・当日のイベント放映や配信はございません。\n\n・出演日時・ステージ内容は主催者都合により変更となる場合がございます。\n\n・ポイントの同率についてはイベントページ概要の「審査について」をご確認ください。\n\n・辞退などによりランキングが繰り上がる場合がございます。\n\n・受賞特典以外で、交通費や宿泊費の支給はございません。\n\n・受賞者は指定された上限金額まで、実費分を後日精算で支給致します。公共交通機関(タクシーを除く)を利用した領収書を後日提出頂きますので保管をお願い致します。領収書は運営事務局までご提出をお願い致します。\n\nゲリラ結果\n🥇期間中指定アイテム獲得数ランキング1位 \n\n \n \n \n \n れんふぁ【FR2PON!】 \n\n 🌟星の命名権獲得🌟 \n＆\n🔥TOP枠獲得 5/31(日)0:00~2:00\n \n\n 🥈期間中指定アイテム獲得数ランキング2位 \n \n\n \n \n \n \n さやか🍡🐒 \n \n\n 🔥TOP枠獲得 5/30(土)0:00~2:00\n \n\n \n \n🎖️‪ゲリラ期間中アイテム獲得数ランキング\n(獲得者のみ表示)\n \n \n \n \n \n \n \n \n \n 順位 \n 画像 \n お名前 \n 総獲得数 \n \n\n 1位 れんふぁ【FR2PON!】 476個 \n 2位 さやか🍡🐒 272個 \n 3位 メロン🍈コーラ🥤🦢 158個 \n 4位 小夏みなみ☘️🐠 審査員賞🙏👘🎋 68個 \n 5位 水希まゆ🍼 67個 \n 6位 希姫(kiki)👑💖 4個 \n 7位 メリー 3個 \n 8位 あおい🤸✏️#ZOZOマリンCM 1個 \n 9位 陣 慎志🪼🪼🪼 1個\n\nゲリラのお知らせ\n今週末にゲリライベントの開催が決定！\n\n今回のゲリラ特典で獲得できるのはなんと、\n\n ＼🌟星の命名権🌟／ \n\n指定アイテムをたくさん獲得して、\n\n世界で唯一の星に名前をつけよう！\n\n ⏰️ゲリラ期間\n\n 5/23(土) 10:00 ~ 5/24(日) 24:00\n\n指定アイテム\nMusic Life ：1,000pt \n ▷Music Life1個 → 1個としてカウント \n \n\n \n \n スターラッシュ ：10,000pt \n ▷スターラッシュ → 12個としてカウント\n\nゲリラ特典\n🥇期間中指定アイテム獲得数ランキング1位 \n\n 🌟星の命名権獲得🌟 \n＆\n🔥TOP枠獲得 5/31(日)0:00~2:00\n\nTOP枠とは？\nミクチャのアプリを開くと最初に表示される、注目ライバーがズラーっと並ぶあのエリア✨\n\nたくさん見てもらえること間違いナシ！ ※同時間に公式配信・有料ライブ配信があった場合は掲載表示位置が下側に表示される場合があります。予めご理解ご了承ください。 \n\n \n \n \n\n 🥈期間中指定アイテム獲得数ランキング2位 \n \n\n 🔥TOP枠獲得 5/30(土)0:00~2:00\n \n\n注意事項 \n \n \n※命名した名前はスプリングブルック天文台の台帳へ登録されますが、学術名としては登録されません。\n\n※命名する星は選べず、星座が選択可能です。\n\n※スプリングブルック天文台から星命名証明書が発行されます。\n\n※賞品は日本国内のご住所にのみ発送が可能です。\n\n※入賞者へのお知らせは、ミクチャアプリ内の\n\n「あなたへのお知らせ」に届きますので、必ずご確認ください。",
  "sections": [
    {
      "sectionId": "イベント概要-1",
      "label": "イベント概要",
      "normalizedLabel": "イベント概要",
      "text": "8/8～8/9、川口文化総合センター・リリアで開催される\n\n \n【音楽と食の祭典】\n\n埼玉 MUSIC&FOOD\n\nFESTIVAL 2026 \n\nそのステージ出演やパンフレット掲載をかけたオーディションを開催✨\n\n多くのアイドルやアーティストが出演するステージに立ち、あなたの魅力を発揮するチャンス！\n\n聴いて楽しみ、食べて楽しみながら、フェスを盛り上げよう🔥\n\n皆様のご参加をお待ちしております💛",
      "order": 1
    },
    {
      "sectionId": "音楽と食の祭典-埼玉-musicfood-festival-2026-2",
      "label": "【音楽と食の祭典】\n\n　　　 埼玉 MUSIC&FOOD FESTIVAL 2026",
      "normalizedLabel": "【音楽と食の祭典】\n\n　　　 埼玉 MUSIC&FOOD FESTIVAL 2026",
      "text": "聴いて楽しみ、食べて楽しみ・・・埼玉県にて食と音楽のフェスを開催。\n\n【音楽と食の祭典】埼玉MUSIC&FOOD FESTIVALは、アイドルによるライブイベントと物産展を行う食と音楽の祭典です。\n\n本イベントは2025年に大宮・川口・所沢で3回開催、大盛況につき4回目の開催が決定いたしました。\n\n JR川口駅西口直結という抜群のアクセス性を誇る川口文化総合センター・リリアは、駅利用者・買い物客・地域住民など、平日・週末を問わず多くの人々が行き交う川口市の中核エリアです。\n\nそんな川口にある川口文化総合センター・リリアにて【音楽と食の祭典】埼玉MUSIC&FOODFESTIVAL2026を開催いたします。\n\n食べ物と音楽を通じて、それぞれの魅力を味わい、体験しましょう。\n\n開催場所：川口文化総合センター・リリア\n \n\n \n \n \n \n \n 【音楽と食の祭典】埼玉MUSIC&FOOD FESTIVAL\n公式Webサイト \n \n \n 【音楽と食の祭典】埼玉MUSIC&FOOD FESTIVAL\n公式X",
      "order": 2
    },
    {
      "sectionId": "埼玉美少女図鑑-3",
      "label": "埼玉美少女図鑑",
      "normalizedLabel": "埼玉美少女図鑑",
      "text": "「美少女図鑑」は全国に展開し、その地元の美少女を取り上げていく地域密着型のメディアです。\n\nこの地域性という強みと、フリーペーパー・SNS・ライブ配信といった多岐にわたる媒体を駆使し、\n\nこれまでに「二階堂ふみ」「山本舞香」「桜井日奈子」「馬場ふみか」をはじめとする国民的女優を数多く輩出してきました。\n\n各地方でそれぞれの形で盛り上がりを見せてきた『美少女図鑑』。\n\n埼玉ならではの美少女を発掘しながら、様々なメディア提携などを仕掛けて\n埼玉の中での『美少女図鑑』を大きくしていきます。\n\n \n 埼玉美少女図鑑 公式HP",
      "order": 3
    },
    {
      "sectionId": "参加条件-4",
      "label": "参加条件",
      "normalizedLabel": "参加条件",
      "text": "本イベントはソロアカウントのみ参加できるイベントです。\n\n原則、本イベントに関しては、\n\n■顔出しできる方、イベント当日にご参加いただける方のみご応募ください。\n\n■未成年の方は保護者の同意が必要です。\n\n■1アカウントにつき1名でご参加ください。\n\n■当イベントは配信者報酬がございます。\n\n■HP・SNS・『美少女図鑑』が管理・発信する媒体にて肖像の露出が可能な方のみご応募ください。\n\n■特定の芸能事務所やプロダクションへの所属有無は問いません。必要な場合はご自身で許可をお取りいただくよう、お願いいたします。\n\n \n \n \nこのイベントでは\n\n ライブ配信 +ムービー 合算 \n\nのポイントがランキングに表示されます！\n \n\n \n \n\n※入賞者へのお知らせは、 ミクチャアプリ内の「あなたへのお知らせ」に届きます ので、必ずご確認ください。",
      "order": 4
    },
    {
      "sectionId": "募集中の最新イベントのご案内始めました-5",
      "label": "募集中の最新イベントのご案内始めました",
      "normalizedLabel": "募集中の最新イベントのご案内始めました",
      "text": "✉毎週水曜と金曜日に更新✉ \n\n 友だち追加で募集中のイベント情報が送られてくるよ！\n\nあなたにぴったりのイベントがきっと見つかるはず👍",
      "order": 5
    },
    {
      "sectionId": "審査について-6",
      "label": "審査について",
      "normalizedLabel": "審査について",
      "text": "●ライブ配信・動画投稿をする際は必ず [ 「音楽と食の祭典 埼玉 MUSIC&FOOD FESTIVAL 2026」ステージ出演＆パンフレット掲載オーディション ]のイベント選択 をお願いします。正しく選択をしていない場合は獲得したミクチャポイントがランキングに反映されませんのでご注意ください。また、誤ってイベント選択した際にポイントを対象イベントに反映することはできかねますので予めご了承ください。\n\n●当該ページの審査項目に沿って受賞者が決定いたします。なお、審査の過程や受賞者の決定に至った理由等につきましてはお答え出来ませんのであらかじめご了承ください。\n\n●獲得したポイントが同一の場合は、下記の条件に従って順位を決定します。((1)から条件を適用し、順位が決定しない場合はその次の条件を適用して決定し、以下同様の処理をします。)\n\n \n　(1) 対象となるイベントを選択してライブ配信をした「配信時間」の合計が多いユーザーを上位とします。\n\n　(2) 対象となるイベントを選択してライブ配信をした「配信回数」の合計が多いユーザーを上位とします。\n\n　(3) 対象となるイベントを選択して行ったライブ配信・投稿動画に対して受け取った「コメント数」の合計が多いユーザーを上位とします。\n\n　(4) 対象となるイベントへの応募申し込みが早かったユーザーを上位とします。\n\n　(5) もし(1)～(5)全てが同じ場合はミクチャの「ユーザーIDの数字が小さい」ユーザーを上位とします。\n\n \n\n ※下記の注意事項も必ずお読みください。",
      "order": 6
    },
    {
      "sectionId": "アイテム送信に関する注意点-7",
      "label": "アイテム送信に関する注意点",
      "normalizedLabel": "アイテム送信に関する注意点",
      "text": "●ライブ配信で、イベント終了間際など同時間帯に大量のアイテムを投げると、多数のアイテムリクエストによりコイン消費に遅延が生じる可能性がございます。ムービーでは遅延が生じることはないので、ムービーイベントの場合は投稿動画への積極的な送信をご検討ください。\n\n●ライブ配信の場合、イベント期間中にライバーの端末側でアイテムのアニメーション再生が始まったアイテムはイベントのポイントに加算されます。イベント期間中に再生失敗したアイテムやイベント期間をすぎてから再生されたアイテムは、イベントのポイントに加算されません。\n\n●なお、上記の事象が発生した場合においても、イベントへのポイント反映やコインの返却などのご対応は出来かねますのでご了承くださいませ。\n\nそのため、ライブ配信ではできるだけ一気に大量に送るのではなく、定期的にアイテムを送るかムービーへのアイテム送信を推奨いたします。",
      "order": 7
    },
    {
      "sectionId": "応募規約-8",
      "label": "応募規約",
      "normalizedLabel": "応募規約",
      "text": "本キャンペーンに応募いただける方（以下、「応募者」といいます。）は、以下をよくお読みいただき、同意の上ご応募ください。\n\nミクチャにて、「イベントに参加する」をタップした時点で本規約に同意したものとみなします。万が一ご同意いただけない場合は応募を中止してください。\n\n本規約の内容は、事前の告知なく変更される場合がありますので、予めご了承ください。\n\n \n　▪️動画投稿・ライブ配信での注意事項\n\n \n●撮影・ライブ配信が禁止されている場所または危険な場所での撮影やライブ配信はお控え下さい。\n\n●楽曲を使用する場合は著作権者から楽曲利用の許可がおりているものをお使いください。\n\n●大声を出す・大音量で音楽を流す、道を塞ぐなど、人の迷惑になる行為は控えて、撮影やライブ配信を実施してください。\n\n \n●応募者と一緒に投稿動画・ライブ配信に写っている方がいらっしゃる場合や、第三者の知的財産権が含まれる場合、必ず投稿やライブ配信前に権利者から使用許諾を得てください。\n\nまた、応募者は投稿動画・ライブ配信について自らが投稿・ライブ配信することについての適法な権利を有していること及び第三者の一切の権利を侵害していないことについて当社に対し表明し、保証するものとします。万が一、第三者からの権利侵害等の申し立てがあった場合には、投稿者や配信者ご自身の責任をもって解決していただきますので、予めご了承ください。\n\n●ミクチャ以外のプラットフォームで作成した動画をミクチャでアップロードする場合、当該プラットフォームの利用規約に沿って投稿してください。\n\n●未成年の方は保護者の同意を得た上でご応募ください。また、必要に応じて、在籍する学校または所属する部活動が加盟する連盟等へ確認をとったうえで応募してください。\n\n●事務所、劇団、その他の団体（以下「事務所等」といいます）に所属されている方は、ご自身の責任で事務所等に本キャンペーンへの応募の可否につきご確認ください。\n\n●コンテストなどの新しい才能の発掘を目的としたものや、事務所所属者や新グループメンバーの選定を目的とした一般的な「オーディション」に関するイベントには、キャッシュバックのお支払いはございません。なお、一部対象外のものもございますので、ご不明な場合はお問い合わせください。\n\n●上記各項への違反や極端に他人に不快感を与えるような言動や、法律に抵触する内容、ミクチャの利用規約に違反した内容、運営事務局が不適切と判断した動画やライブ配信については削除、もしくはキャッシュバックや審査、受賞の対象外とする可能性がございますのでご了承ください。\n\n●本応募規約に定める事項のほか、ミクチャ利用規約及びプライバシーポリシーが適用されますので、確認の上、ご応募ください。\n\n \n　▪️賞品・受賞について\n\n \n●受賞者と連絡がつかない場合、賞品受領の意思が確認できない場合、指定された期日までに連絡先をご返信いただけない場合等には、受賞を辞退されたものとみなし、受賞を無効とさせていただきます。予めご了承ください。\n\n●受賞の権利は受賞者ご本人のものであって、第三者へ譲渡・換金等することはできません。また、受領した賞品の紛失等による再送付、受賞者の事情による変更、その他クレーム等には一切応じることができません。\n\n●当社は、賞品の品質及び、目的適合性について何ら保証することはできかねます。賞品の使用に当たっては、賞品に記載の注意事項をご確認の上、ご使用ください。受賞された賞品の使用中に生じた事故等のトラブルについての責任は、当社では負いかねます。\n\n●賞品提供元の何らかの事由により特典不履行となる事案が生じた場合は、代替賞品による補填などで対応することがございますのでご了承くださいませ。\n\n \n　▪️禁止事項\n\n \n本キャンペーンへの応募に際し、以下の行為を禁止します。当社は、応募者が以下に該当する行為を行ったと判断した場合は、応募者への事前通告なく、対象投稿を掲載しない、掲載後削除する、応募・受賞を無効とするなどの対応をとる場合があります。\n\n・本規約または法令に違反する行為\n\n・本キャンペーンの運営を妨げる行為\n\n・他人に迷惑、不利益、損害または不快感を与える行為\n\n・他人を誹謗中傷し、またはその名誉若しくは信用を毀損する行為\n\n・第三者の著作権その他の知的財産権を侵害する行為\n\n・他人の財産、プライバシー若しくは肖像権を侵害する行為\n\n・わいせつ、児童ポルノ及び児童の性的搾取を助長するデータを投稿する行為\n\n・営利を目的とした情報提供、広告宣伝もしくは勧誘行為\n\n・公序良俗に反する行為\n\n・ミクチャの利用規約に違反する行為\n\n・その他、前各号に類する行為\n\n \n　▪️免責・その他\n\n \n本キャンペーンは、細心の注意を払って運営をしていますが、提供する情報、プログラム、各種サービス、その他本キャンペーンに関するすべての事項について、その完全性、正確性、安全性、有用性等について、いかなる保証もするものではありません。また、利用者または第三者が被った以下の事例を含む損害については、当社は責任を負いかねます。\n\n1.本キャンペーンへの応募に際して、ソフトウェア・ハードウェア上の事故、火災、停電、通信環境の悪化、地震、事変等の非常事態が発生した場合。\n\n2.本キャンペーンにおけるシステムの保守を定期的あるいは緊急に行う場合。\n\n3.利用者間または利用者と第三者の間におけるトラブル等が生じた場合。\n\n4.第三者による本キャンペーンのサービスの妨害、情報改変などによりサービスが中断もしくは遅延し、何らかの欠陥が生じた場合。\n\n5.当社が推奨する環境以外から本キャンペーンに応募したために情報を完全に取得できない場合。\n\n6.故意または重過失なくして本キャンペーンが提供する情報が誤送信されるか、もしくは欠陥があった場合。\n\n当社は、本キャンペーンの応募により応募者に生じた一切のトラブル・損害（直接・間接を問いません）について、如何なる責任も負いません。\n\n本キャンペーンの応募にかかるインターネット接続料及び通信費は応募者のご負担となります。\n\n本キャンペーンは、ミクチャを提供している当社（株式会社Donuts）が運営しているものであり、Apple社によって提供されているものではございません。\n\n \n　▪️個人情報の取り扱いについて\n\n \n住所、電話番号、氏名、性別、年齢、ミクチャアカウントURLの情報（以下「個人情報」といいます。）は、株式会社Donutsが管理します（管理責任者：ミクチャグループリーダー）。お客様の個人情報は、本キャンペーンの当選者への連絡・賞品の送付等の目的で利用し、それ以外の目的では使用致しません。また、お客様の個人情報をお客様の同意なしに業務委託先以外の第三者に開示・提供することはありません（法令等により開示を求められた場合を除きます。）。\n\nまた、個人情報開示、訂正等のお問い合わせは、ミクチャ運営事務局（mixch-support@donuts.ne.jp）までお願い致します。\n\n \n　▪️キャンペーンに関するお問い合わせ窓口\n\n \n[ミクチャスポンサー事務局]\n\nmixch-support@donuts.ne.jp",
      "order": 8
    },
    {
      "sectionId": "スケジュール-9",
      "label": "スケジュール",
      "normalizedLabel": "スケジュール",
      "text": "募集期間 \n\n \n　　6/19(金)18:00～7/12(日)24:00\n\n \n 本選期間 \n\n \n　　7/1(水)18:00～7/12(日)24:00\n\n \n 結果発表 \n\n \n　　7/13(月)\n\n \n 撮影 \n\n \n　　7/21(火) 17:00~20:00の間の1~2時間\n\n　　@都内予定\n\n \n 音楽と食の祭典\n埼玉 MUSIC&FOOD FESTIVAL \n\n \n　　出演：8/9(日)",
      "order": 9
    },
    {
      "sectionId": "本選特典-10",
      "label": "本選特典",
      "normalizedLabel": "本選特典",
      "text": "🥇ポイントランキング1位 \n\n \n \n\n \n イベントアンバサダーとして\n ステージ出演権を獲得！ \n\n↪ 🎤歌・ダンス披露💃 \nまたは\n トークショー✨\n を選択可能！\n\n \n\n 📚パンフレット表紙掲載 \n（撮影あり）\n\n交通費上限2万円支給 \n\n 🥈ポイントランキング2位 \n\n \n \n イベントアンバサダーとして\n トークショーステージ \n出演権を獲得！ \n\n \n\n 📚パンフレット中面1/2ページ掲載 \n（データ提出）\n\n50万pt達成で\n交通費上限1万円支給 \n\n 🏅審査員特別賞(3~5位から1名) \n\n \n \n イベントアンバサダーとして\n トークショーステージ \n出演権を獲得！ \n\n \n\n 📚パンフレット中面1/2ページ掲載 \n（データ提出）\n\n50万pt達成で\n交通費上限1万円支給",
      "order": 10
    },
    {
      "sectionId": "特典に関する注意事項-11",
      "label": "特典に関する注意事項",
      "normalizedLabel": "特典に関する注意事項",
      "text": "ステージ出演に関して\n \n \n・ステージ出演内容（歌・ダンス披露またはトークショー）は、ポイントランキング1位の方のみが選択できます。\n\n・ポイントランキング2位および審査員特別賞受賞者の出演形式はトークショーとなります。\n\n・ステージ出演は8/9(日) 10~13時のうち10分間になります。\n\n1位の方が「歌・ダンス披露」を選択した場合、\n\n1位：単独で5分間の歌・ダンス披露\n\n2位・審査員特別賞：2名で5分間のトークショー出演\n\n1位の方が「トークショー」を選択した場合、\n\n1位・2位・審査員特別賞で、10分間のトークショー出演\n\nとなります。予めご了承ください。\n\n \n提出データに関して\n \n \n・ポイントランキング2位、審査員特別賞の方につきましては、7月20日までにデータの提出をお願い致します。\n\n・ 5MB以上、バストアップで1枚 の画像データをご提出くださいますようお願いいたします。\n\n・ポイントランキング2位、審査員特別賞の方は撮影がございません。予めご了承ください。\n\n \nその他注意事項\n \n \n・ステージ出演の際、受賞者3名の内撮影NGの方がいた場合、客席からの撮影が不可となる場合もあります。予めご了承ください。\n\n・1位の方のステージ出演内容は結果発表日から5日後までに選択いただきます。それ以上経過してもご連絡がない場合は運営側で決めさせていただきます。\n\n・トークショーはMC2名と受賞者で実施いたします。内容はイベント主催側で決めさせていただきます。\n\n・撮影、ステージ出演共に、衣装やへアイメイクなどはご自身での準備となります。\n\n・当日リハーサルがございます。\n\n・20時以降の出演はございません。\n\n・当日のイベント放映や配信はございません。\n\n・出演日時・ステージ内容は主催者都合により変更となる場合がございます。\n\n・ポイントの同率についてはイベントページ概要の「審査について」をご確認ください。\n\n・辞退などによりランキングが繰り上がる場合がございます。\n\n・受賞特典以外で、交通費や宿泊費の支給はございません。\n\n・受賞者は指定された上限金額まで、実費分を後日精算で支給致します。公共交通機関(タクシーを除く)を利用した領収書を後日提出頂きますので保管をお願い致します。領収書は運営事務局までご提出をお願い致します。",
      "order": 11
    },
    {
      "sectionId": "ゲリラ開催-12",
      "label": "ゲリラ結果",
      "normalizedLabel": "ゲリラ開催",
      "text": "🥇期間中指定アイテム獲得数ランキング1位 \n\n \n \n \n \n れんふぁ【FR2PON!】 \n\n 🌟星の命名権獲得🌟 \n＆\n🔥TOP枠獲得 5/31(日)0:00~2:00\n \n\n 🥈期間中指定アイテム獲得数ランキング2位 \n \n\n \n \n \n \n さやか🍡🐒 \n \n\n 🔥TOP枠獲得 5/30(土)0:00~2:00\n \n\n \n \n🎖️‪ゲリラ期間中アイテム獲得数ランキング\n(獲得者のみ表示)\n \n \n \n \n \n \n \n \n \n 順位 \n 画像 \n お名前 \n 総獲得数 \n \n\n 1位 れんふぁ【FR2PON!】 476個 \n 2位 さやか🍡🐒 272個 \n 3位 メロン🍈コーラ🥤🦢 158個 \n 4位 小夏みなみ☘️🐠 審査員賞🙏👘🎋 68個 \n 5位 水希まゆ🍼 67個 \n 6位 希姫(kiki)👑💖 4個 \n 7位 メリー 3個 \n 8位 あおい🤸✏️#ZOZOマリンCM 1個 \n 9位 陣 慎志🪼🪼🪼 1個",
      "order": 12
    },
    {
      "sectionId": "ゲリラ開催-13",
      "label": "ゲリラのお知らせ",
      "normalizedLabel": "ゲリラ開催",
      "text": "今週末にゲリライベントの開催が決定！\n\n今回のゲリラ特典で獲得できるのはなんと、\n\n ＼🌟星の命名権🌟／ \n\n指定アイテムをたくさん獲得して、\n\n世界で唯一の星に名前をつけよう！\n\n ⏰️ゲリラ期間\n\n 5/23(土) 10:00 ~ 5/24(日) 24:00",
      "order": 13
    },
    {
      "sectionId": "指定アイテム-14",
      "label": "指定アイテム",
      "normalizedLabel": "指定アイテム",
      "text": "Music Life ：1,000pt \n ▷Music Life1個 → 1個としてカウント \n \n\n \n \n スターラッシュ ：10,000pt \n ▷スターラッシュ → 12個としてカウント",
      "order": 14
    },
    {
      "sectionId": "ゲリラ開催-15",
      "label": "ゲリラ特典",
      "normalizedLabel": "ゲリラ開催",
      "text": "🥇期間中指定アイテム獲得数ランキング1位 \n\n 🌟星の命名権獲得🌟 \n＆\n🔥TOP枠獲得 5/31(日)0:00~2:00",
      "order": 15
    },
    {
      "sectionId": "top枠とは-16",
      "label": "TOP枠とは？",
      "normalizedLabel": "TOP枠とは？",
      "text": "ミクチャのアプリを開くと最初に表示される、注目ライバーがズラーっと並ぶあのエリア✨\n\nたくさん見てもらえること間違いナシ！ ※同時間に公式配信・有料ライブ配信があった場合は掲載表示位置が下側に表示される場合があります。予めご理解ご了承ください。 \n\n \n \n \n\n 🥈期間中指定アイテム獲得数ランキング2位 \n \n\n 🔥TOP枠獲得 5/30(土)0:00~2:00\n \n\n注意事項 \n \n \n※命名した名前はスプリングブルック天文台の台帳へ登録されますが、学術名としては登録されません。\n\n※命名する星は選べず、星座が選択可能です。\n\n※スプリングブルック天文台から星命名証明書が発行されます。\n\n※賞品は日本国内のご住所にのみ発送が可能です。\n\n※入賞者へのお知らせは、ミクチャアプリ内の\n\n「あなたへのお知らせ」に届きますので、必ずご確認ください。",
      "order": 16
    }
  ],
  "tabs": [
    {
      "key": "ranking",
      "label": "ランキング",
      "order": 1
    },
    {
      "key": "live",
      "label": "ライブ",
      "order": 2
    },
    {
      "key": "movie",
      "label": "ムービー",
      "order": 3
    },
    {
      "key": "about",
      "label": "概要",
      "order": 4
    }
  ],
  "bannerImageUrl": "https://d2uqarpmf42qy0.cloudfront.net/torte/event/24151/banner.png"
}